Workbook
Name \: #REF!
Name \0: #REF!
Name \a: #REF!
Name \b: #N/A
Name \C: #REF!
Name \l: #REF!
Name \m: #REF!
Name \n: #REF!
Name \p: #REF!
Name \r: #REF!
Name \s: #REF!
Name \v: #N/A
Name \w: #N/A
Name \x: #REF!
Name _: #REF!
Name ____________________________________________________b111121: #REF!
Name ____________________________________________________Ki1: #REF!
Name ____________________________________________________Ki2: #REF!
Name ____________________________________________________MAN1: #REF!
Name ____________________________________________________PB1: #REF!
Name ____________________________________________________TB2: #REF!
Name ___________________________________________________b111121: #REF!
Name ___________________________________________________Ki1: #REF!
Name ___________________________________________________Ki2: #REF!
Name ___________________________________________________MAN1: #REF!
Name ___________________________________________________PB1: #REF!
Name ___________________________________________________TB2: #REF!
Name __________________________________________________b111121: #REF!
Name __________________________________________________Ki1: #REF!
Name __________________________________________________Ki2: #REF!
Name __________________________________________________MAN1: #REF!
Name __________________________________________________PB1: #REF!
Name __________________________________________________TB2: #REF!
Name _________________________________________________b111121: #REF!
Name _________________________________________________Ki1: #REF!
Name _________________________________________________Ki2: #REF!
Name _________________________________________________MAN1: #REF!
Name _________________________________________________PB1: #REF!
Name _________________________________________________TB2: #REF!
Name ________________________________________________b111121: #REF!
Name ________________________________________________Ki1: #REF!
Name ________________________________________________Ki2: #REF!
Name ________________________________________________MAN1: #REF!
Name ________________________________________________PB1: #REF!
Name ________________________________________________TB2: #REF!
Name _______________________________________________b111121: #REF!
Name _______________________________________________Ki1: #REF!
Name _______________________________________________Ki2: #REF!
Name _______________________________________________MAN1: #REF!
Name _______________________________________________PB1: #REF!
Name _______________________________________________TB2: #REF!
Name ______________________________________________b111121: #REF!
Name ______________________________________________Ki1: #REF!
Name ______________________________________________Ki2: #REF!
Name ______________________________________________MAN1: #REF!
Name ______________________________________________PB1: #REF!
Name ______________________________________________TB2: #REF!
Name _____________________________________________b111121: #REF!
Name _____________________________________________Ki1: #REF!
Name _____________________________________________Ki2: #REF!

Sheet Cover
A2: GOVT OF ASSAM
A13: PUBLIC WORKS DEPARTMENT
A14: (BUILDING WINGS)
B16: Name of Work | E16: :- | F16: =Report!D3 -> Repairing and Renovation of Circuit House at Bokakhat Co District under Golaghat District
B19: Name of Circle | E19: :- | F19: Jorhat Building Circle, Jorhat
B20: Name of Division | E20: :- | F20: PW(B&NH)D, Golaghat District Territorial Building Division, Golaghat.
B21: Name of Sub- Division | E21: :- | F21: PW(B&NH)D, Bokakhat & Dergaon Territorial Building Sub-Division, Bokakhat.
B24: Estimated Amount | E24: :- | F24: =Report!D7 -> 4623500
B26: =Report!D8 -> (Rupees forty eight lakh twenty three thousand five hundred ) only.

Sheet Report
A1: GOVERNMENT OF ASSAM PUBLIC WORKS DEPARTMENT (BUILDING WINGS)
A3: Name of Work | C3: : | D3: Repairing and Renovation of Circuit House at Bokakhat Co District under Golaghat District
A4: Name of Circle : | C4: : | D4: Jorhat Building Circle, Jorhat
A5: Name of Division:- | C5: : | D5: PW(B&NH)D, Golaghat District Territorial Building Division, Golaghat.
A6: Name of Sub-Division:- | C6: : | D6: PW(B&NH)D, Bokakhat & Dergaon Territorial Building Sub- Division, Bokakhat
A7: Estimated Amount | C7: : | D7: =Abstract!G20 -> 4623500
D8: =Abstract!B22 -> (Rupees forty eight lakh twenty three thousand five hundred ) only.
A11: This estimate has been prepared to show the probable cost for construction of the above noted work.
A13: R E P O R T
A15: =" The estimate amounting to Rs. "&TEXT(D7,"#,##0.00")&" "&D8&" "&"has been prepared to show the probable cost for work for """&D3&"""" & "This estimate is prepared as per letter received from Co-District Commissioner, Bokakhat vide No- BNZ.5/2026/, dtd 09/09/2026." -> The estimate amounting to Rs. 46,23,500.00 (Rupees forty eight lakh twenty three thousand five hundred ) only. has been prepared to show the probable cost for work for "Repairing and Renovation of Circuit House at Bokakhat Co District under Golaghat District"This estimate is prepared as per letter received from Co-District Commissioner, Bokakhat vide No- BNZ.5/2026/, dtd 09/09/2026.
A16: Location :
B17: Circuit House, Bokakhat.
A19: Necessity: The Circuit House, Bokakhat is an important Government accommodation facility used for the stay of Government officers, dignitaries, visiting officials and other authorised guests during their official visits to Bokakhat and adjoining areas. The existing building requires necessary repair and renovation to improve its safety, functionality and overall conditions. Accordingly, this estimate has been prepared for proper functioning of the building.
A23: Provisions:
A24: This estimate contains the following provisions:-
A25: 1 Repairing and Renovation of Circuit House RCC G+1 First Floor A/Type Residential Building, Kitchen , Dormitory and Cottage (Guest Room
A26: 2 Sanitary and Water Supply Fitting works
A27: 3 Electrical Works.
A28: 4 Installation of Solar Street Lights.
A29: This estimate is based on CPWD Plinth area Rate 2021 and CPWD schedule of Rate (Building) DSR Vol. 1 & Vol. 2 for the year 2021 and E & M (for Electrical) for the year 2022. The provision for Contingencies @5%, Premium is also considered as per norms. All works will be carried out as per PWD general specifications current in the state and as per IS code of practice.

Sheet Abstract
B3: ='AType Cottage'!A1 -> Name of Work :- Repairing and Renovation of Circuit House at Bokakhat Co District under Golaghat District
B5: ABSTRACT OF COST
B7: PARTICULARS | G7: Estimated Amount
B8: 1. Repairing and Renovation Works….................. | F8: = | G8: ='Rennovation BOQ'!M40 -> 2357162
B9: 2. Sanitary and Water Supply Fittings…................ | F9: = | G9: ='Sanitart Works'!N40 -> 498118
B10: 3. Cost of Electrification Works.………………… | F10: = | G10: =[50]Electrical!$G$31 -> 720512
B11: 4. Installation of Solar Street lights…............................. | F11: = | G11: =[51]est!$G$6 -> 162192
B12: Total (A) | F12: = | G12: =SUM(G8:G11) -> 3737984
B13: Add 6.33% GST | F13: = | G13: =ROUND(6.33%*G12,0) -> 236614
B14: Total (B) | F14: = | G14: =SUM(G12:G13) -> 3974598 | H14: =G14/G20 -> 0.85965135
B15: Quotation Items:
B16: 1. Furniture…....................................................... | F16: = | G16: =furniture!F12 -> 428772
B17: Total (C) | F17: = | G17: =SUM(G14:G16) -> 4403370 | H17: =#REF!+G16 -> #REF! | I17: =H17/G20 -> #REF!
B18: Add Contigency 5% | F18: = | G18: =ROUND(5%*G17,0) -> 220169
B19: Grand Total | F19: = | G19: =SUM(G17:G18) -> 4623539 | H19: 4898500
B20: SAY | F20: = | G20: =ROUND(G19,-2) -> 4623500
B22: =CU39 -> (Rupees forty eight lakh twenty three thousand five hundred ) only.
A39: =G20 -> 4623500 | B39: COPY CELLS=> | C39: 1 | D39: one | E39: 2 | F39: two | G39: 3 | H39: three | I39: 4 | J39: four | K39: 5 | L39: five | M39: 6 | N39: six | O39: 7 | P39: seven | Q39: 8 | R39: eight | S39: 9 | T39: nine | U39: 10 | V39: ten | W39: 11 | X39: eleven | Y39: 12 | Z39: twelve | AA39: 13 | AB39: thirteen | AC39: 14 | AD39: fourteen | AE39: 15 | AF39: fifteen | AG39: 16 | AH39: sixteen | AI39: 17 | AJ39: seventeen | AK39: 18 | AL39: eighteen | AM39: 19 | AN39: nineteen | AO39: <=COPY CELLS | AP39: WORDS-> | AQ39: CRORE | AR39: =IF(AX39="","",IF(AX39>=90,"ninety "&IF((AX39-ROUNDDOWN(AX39,-1))=C39,D39,"")&IF((AX39-ROUNDDOWN(AX39,-1))=E39,F39,"")&IF((AX39-ROUNDDOWN(AX39,-1))=G39,H39,"")&IF((AX39-ROUNDDOWN(AX39,-1))=I39,J39,"")&IF((AX39-ROUNDDOWN(AX39,-1))=K39,L39,"")&IF((AX39-ROUNDDOWN(AX39,-1))=M39,N39,"")&IF((AX39-ROUNDDOWN(AX39,-1))=O39,P39,"")&IF((AX39-ROUNDDOWN(AX39,-1))=Q39,R39,"")&IF((AX39-ROUNDDOWN(AX39,-1))=S39,T39,""),IF(AX39>=80,"eighty "&IF((AX39-ROUNDDOWN(AX39,-1))=1,D39,"")&IF((AX39-ROUNDDOWN(AX39,-1))=2,F39,"")&IF((AX39-ROUNDDOWN(AX39,-1))=G39,H39,"")&IF((AX39-ROUNDDOWN(AX39,-1))=I39,J39,"")&IF((AX39-ROUNDDOWN(AX39,-1))=K39,L39,"")&IF((AX39-ROUNDDOWN(AX39,-1))=M39,N39,"")&IF((AX39-ROUNDDOWN(AX39,-1))=O39,P39,"")&IF((AX39-ROUNDDOWN(AX39,-1))=Q39,R39,"")&IF((AX39-ROUNDDOWN(AX39,-1))=S39,T39,""),""))) | AS39: =IF(AX39="","",IF(AX39>79,"",IF(AX39>=70,"seventy "&IF((AX39-ROUNDDOWN(AX39,-1))=C39,D39,"")&IF((AX39-ROUNDDOWN(AX39,-1))=E39,F39,"")&IF((AX39-ROUNDDOWN(AX39,-1))=G39,H39,"")&IF((AX39-ROUNDDOWN(AX39,-1))=I39,J39,"")&IF((AX39-ROUNDDOWN(AX39,-1))=K39,L39,"")&IF((AX39-ROUNDDOWN(AX39,-1))=M39,N39,"")&IF((AX39-ROUNDDOWN(AX39,-1))=O39,P39,"")&IF((AX39-ROUNDDOWN(AX39,-1))=Q39,R39,"")&IF((AX39-ROUNDDOWN(AX39,-1))=S39,T39,""),IF(AX39>=60,"sixty "&IF((AX39-ROUNDDOWN(AX39,-1))=1,D39,"")&IF((AX39-ROUNDDOWN(AX39,-1))=2,F39,"")&IF((AX39-ROUNDDOWN(AX39,-1))=G39,H39,"")&IF((AX39-ROUNDDOWN(AX39,-1))=I39,J39,"")&IF((AX39-ROUNDDOWN(AX39,-1))=K39,L39,"")&IF((AX39-ROUNDDOWN(AX39,-1))=M39,N39,"")&IF((AX39-ROUNDDOWN(AX39,-1))=O39,P39,"")&IF((AX39-ROUNDDOWN(AX39,-1))=Q39,R39,"")&IF((AX39-ROUNDDOWN(AX39,-1))=S39,T39,""),"")))) | AT39: =IF(AX39="","",IF(AX39>59,"",IF(AX39>=50,"fifty "&IF((AX39-ROUNDDOWN(AX39,-1))=C39,D39,"")&IF((AX39-ROUNDDOWN(AX39,-1))=E39,F39,"")&IF((AX39-ROUNDDOWN(AX39,-1))=G39,H39,"")&IF((AX39-ROUNDDOWN(AX39,-1))=I39,J39,"")&IF((AX39-ROUNDDOWN(AX39,-1))=K39,L39,"")&IF((AX39-ROUNDDOWN(AX39,-1))=M39,N39,"")&IF((AX39-ROUNDDOWN(AX39,-1))=O39,P39,"")&IF((AX39-ROUNDDOWN(AX39,-1))=Q39,R39,"")&IF((AX39-ROUNDDOWN(AX39,-1))=S39,T39,""),IF(AX39>=40,"forty "&IF((AX39-ROUNDDOWN(AX39,-1))=1,D39,"")&IF((AX39-ROUNDDOWN(AX39,-1))=2,F39,"")&IF((AX39-ROUNDDOWN(AX39,-1))=G39,H39,"")&IF((AX39-ROUNDDOWN(AX39,-1))=I39,J39,"")&IF((AX39-ROUNDDOWN(AX39,-1))=K39,L39,"")&IF((AX39-ROUNDDOWN(AX39,-1))=M39,N39,"")&IF((AX39-ROUNDDOWN(AX39,-1))=O39,P39,"")&IF((AX39-ROUNDDOWN(AX39,-1))=Q39,R39,"")&IF((AX39-ROUNDDOWN(AX39,-1))=S39,T39,""),"")))) | AU39: =IF(AX39="","",IF(AX39>39,"",IF(AX39>=30,"thirty "&IF((AX39-ROUNDDOWN(AX39,-1))=C39,D39,"")&IF((AX39-ROUNDDOWN(AX39,-1))=E39,F39,"")&IF((AX39-ROUNDDOWN(AX39,-1))=G39,H39,"")&IF((AX39-ROUNDDOWN(AX39,-1))=I39,J39,"")&IF((AX39-ROUNDDOWN(AX39,-1))=K39,L39,"")&IF((AX39-ROUNDDOWN(AX39,-1))=M39,N39,"")&IF((AX39-ROUNDDOWN(AX39,-1))=O39,P39,"")&IF((AX39-ROUNDDOWN(AX39,-1))=Q39,R39,"")&IF((AX39-ROUNDDOWN(AX39,-1))=S39,T39,""),IF(AX39>=20,"twenty "&IF((AX39-ROUNDDOWN(AX39,-1))=1,D39,"")&IF((AX39-ROUNDDOWN(AX39,-1))=2,F39,"")&IF((AX39-ROUNDDOWN(AX39,-1))=G39,H39,"")&IF((AX39-ROUNDDOWN(AX39,-1))=I39,J39,"")&IF((AX39-ROUNDDOWN(AX39,-1))=K39,L39,"")&IF((AX39-ROUNDDOWN(AX39,-1))=M39,N39,"")&IF((AX39-ROUNDDOWN(AX39,-1))=O39,P39,"")&IF((AX39-ROUNDDOWN(AX39,-1))=Q39,R39,"")&IF((AX39-ROUNDDOWN(AX39,-1))=S39,T39,""),"")))) | AV39: =IF(AX39="","",IF(AX39=C39,D39,"")&IF(AX39=E39,F39,"")&IF(AX39=G39,H39,"")&IF(AX39=I39,J39,"")&IF(AX39=K39,L39,"")&IF(AX39=M39,N39,"")&IF(AX39=O39,P39,"")&IF(AX39=Q39,R39,"")&IF(AX39=S39,T39,"")&IF(AX39=U39,V39,"")&IF(AX39=W39,X39,"")&IF(AX39=Y39,Z39,"")&IF(AX39=AA39,AB39,"")&IF(AX39=AC39,AD39,"")&IF(AX39=AE39,AF39,"")&IF(AX39=AG39,AH39,"")&IF(AX39=AI39,AJ39,"")&IF(AX39=AK39,AL39,"")&IF(AX39=AM39,AN39,"")) | AX39: =IF(A39>=10000000,ROUNDDOWN(A39,-7)/10000000,"") | AY39: =IF(AR39="","",AR39)&IF(AS39="","",AS39)&IF(AT39="","",AT39)&IF(AU39="","",AU39)&IF(AV39="","",AV39) | AZ39: LAKH | BA39: =IF(BG39="","",IF(BG39>=90,"ninety "&IF((BG39-ROUNDDOWN(BG39,-1))=C39,D39,"")&IF((BG39-ROUNDDOWN(BG39,-1))=E39,F39,"")&IF((BG39-ROUNDDOWN(BG39,-1))=G39,H39,"")&IF((BG39-ROUNDDOWN(BG39,-1))=I39,J39,"")&IF((BG39-ROUNDDOWN(BG39,-1))=K39,L39,"")&IF((BG39-ROUNDDOWN(BG39,-1))=M39,N39,"")&IF((BG39-ROUNDDOWN(BG39,-1))=O39,P39,"")&IF((BG39-ROUNDDOWN(BG39,-1))=Q39,R39,"")&IF((BG39-ROUNDDOWN(BG39,-1))=S39,T39,""),IF(BG39>=80,"eighty "&IF((BG39-ROUNDDOWN(BG39,-1))=1,D39,"")&IF((BG39-ROUNDDOWN(BG39,-1))=2,F39,"")&IF((BG39-ROUNDDOWN(BG39,-1))=G39,H39,"")&IF((BG39-ROUNDDOWN(BG39,-1))=I39,J39,"")&IF((BG39-ROUNDDOWN(BG39,-1))=K39,L39,"")&IF((BG39-ROUNDDOWN(BG39,-1))=M39,N39,"")&IF((BG39-ROUNDDOWN(BG39,-1))=O39,P39,"")&IF((BG39-ROUNDDOWN(BG39,-1))=Q39,R39,"")&IF((BG39-ROUNDDOWN(BG39,-1))=S39,T39,""),""))) | BB39: =IF(BG39="","",IF(BG39>79,"",IF(BG39>=70,"seventy "&IF((BG39-ROUNDDOWN(BG39,-1))=C39,D39,"")&IF((BG39-ROUNDDOWN(BG39,-1))=E39,F39,"")&IF((BG39-ROUNDDOWN(BG39,-1))=G39,H39,"")&IF((BG39-ROUNDDOWN(BG39,-1))=I39,J39,"")&IF((BG39-ROUNDDOWN(BG39,-1))=K39,L39,"")&IF((BG39-ROUNDDOWN(BG39,-1))=M39,N39,"")&IF((BG39-ROUNDDOWN(BG39,-1))=O39,P39,"")&IF((BG39-ROUNDDOWN(BG39,-1))=Q39,R39,"")&IF((BG39-ROUNDDOWN(BG39,-1))=S39,T39,""),IF(BG39>=60,"sixty "&IF((BG39-ROUNDDOWN(BG39,-1))=1,D39,"")&IF((BG39-ROUNDDOWN(BG39,-1))=2,F39,"")&IF((BG39-ROUNDDOWN(BG39,-1))=G39,H39,"")&IF((BG39-ROUNDDOWN(BG39,-1))=I39,J39,"")&IF((BG39-ROUNDDOWN(BG39,-1))=K39,L39,"")&IF((BG39-ROUNDDOWN(BG39,-1))=M39,N39,"")&IF((BG39-ROUNDDOWN(BG39,-1))=O39,P39,"")&IF((BG39-ROUNDDOWN(BG39,-1))=Q39,R39,"")&IF((BG39-ROUNDDOWN(BG39,-1))=S39,T39,""),"")))) | BC39: =IF(BG39="","",IF(BG39>59,"",IF(BG39>=50,"fifty "&IF((BG39-ROUNDDOWN(BG39,-1))=C39,D39,"")&IF((BG39-ROUNDDOWN(BG39,-1))=E39,F39,"")&IF((BG39-ROUNDDOWN(BG39,-1))=G39,H39,"")&IF((BG39-ROUNDDOWN(BG39,-1))=I39,J39,"")&IF((BG39-ROUNDDOWN(BG39,-1))=K39,L39,"")&IF((BG39-ROUNDDOWN(BG39,-1))=M39,N39,"")&IF((BG39-ROUNDDOWN(BG39,-1))=O39,P39,"")&IF((BG39-ROUNDDOWN(BG39,-1))=Q39,R39,"")&IF((BG39-ROUNDDOWN(BG39,-1))=S39,T39,""),IF(BG39>=40,"forty "&IF((BG39-ROUNDDOWN(BG39,-1))=1,D39,"")&IF((BG39-ROUNDDOWN(BG39,-1))=2,F39,"")&IF((BG39-ROUNDDOWN(BG39,-1))=G39,H39,"")&IF((BG39-ROUNDDOWN(BG39,-1))=I39,J39,"")&IF((BG39-ROUNDDOWN(BG39,-1))=K39,L39,"")&IF((BG39-ROUNDDOWN(BG39,-1))=M39,N39,"")&IF((BG39-ROUNDDOWN(BG39,-1))=O39,P39,"")&IF((BG39-ROUNDDOWN(BG39,-1))=Q39,R39,"")&IF((BG39-ROUNDDOWN(BG39,-1))=S39,T39,""),"")))) -> forty eight | BD39: =IF(BG39="","",IF(BG39>39,"",IF(BG39>=30,"thirty "&IF((BG39-ROUNDDOWN(BG39,-1))=C39,D39,"")&IF((BG39-ROUNDDOWN(BG39,-1))=E39,F39,"")&IF((BG39-ROUNDDOWN(BG39,-1))=G39,H39,"")&IF((BG39-ROUNDDOWN(BG39,-1))=I39,J39,"")&IF((BG39-ROUNDDOWN(BG39,-1))=K39,L39,"")&IF((BG39-ROUNDDOWN(BG39,-1))=M39,N39,"")&IF((BG39-ROUNDDOWN(BG39,-1))=O39,P39,"")&IF((BG39-ROUNDDOWN(BG39,-1))=Q39,R39,"")&IF((BG39-ROUNDDOWN(BG39,-1))=S39,T39,""),IF(BG39>=20,"twenty "&IF((BG39-ROUNDDOWN(BG39,-1))=1,D39,"")&IF((BG39-ROUNDDOWN(BG39,-1))=2,F39,"")&IF((BG39-ROUNDDOWN(BG39,-1))=G39,H39,"")&IF((BG39-ROUNDDOWN(BG39,-1))=I39,J39,"")&IF((BG39-ROUNDDOWN(BG39,-1))=K39,L39,"")&IF((BG39-ROUNDDOWN(BG39,-1))=M39,N39,"")&IF((BG39-ROUNDDOWN(BG39,-1))=O39,P39,"")&IF((BG39-ROUNDDOWN(BG39,-1))=Q39,R39,"")&IF((BG39-ROUNDDOWN(BG39,-1))=S39,T39,""),"")))) | BE39: =IF(BG39="","",IF(BG39=C39,D39,"")&IF(BG39=E39,F39,"")&IF(BG39=G39,H39,"")&IF(BG39=I39,J39,"")&IF(BG39=K39,L39,"")&IF(BG39=M39,N39,"")&IF(BG39=O39,P39,"")&IF(BG39=Q39,R39,"")&IF(BG39=S39,T39,"")&IF(BG39=U39,V39,"")&IF(BG39=W39,X39,"")&IF(BG39=Y39,Z39,"")&IF(BG39=AA39,AB39,"")&IF(BG39=AC39,AD39,"")&IF(BG39=AE39,AF39,"")&IF(BG39=AG39,AH39,"")&IF(BG39=AI39,AJ39,"")&IF(BG39=AK39,AL39,"")&IF(BG39=AM39,AN39,"")) | BG39: 48 | BH39: =IF(BA39="","",BA39)&IF(BB39="","",BB39)&IF(BC39="","",BC39)&IF(BD39="","",BD39)&IF(BE39="","",BE39) -> forty eight | BI39: THOUSAND | BJ39: =IF(BP39="","",IF(BP39>=90,"ninety "&IF((BP39-ROUNDDOWN(BP39,-1))=1,D39,"")&IF((BP39-ROUNDDOWN(BP39,-1))=2,F39,"")&IF((BP39-ROUNDDOWN(BP39,-1))=G39,H39,"")&IF((BP39-ROUNDDOWN(BP39,-1))=I39,J39,"")&IF((BP39-ROUNDDOWN(BP39,-1))=K39,L39,"")&IF((BP39-ROUNDDOWN(BP39,-1))=M39,N39,"")&IF((BP39-ROUNDDOWN(BP39,-1))=O39,P39,"")&IF((BP39-ROUNDDOWN(BP39,-1))=Q39,R39,"")&IF((BP39-ROUNDDOWN(BP39,-1))=S39,T39,""),IF(BP39>=80,"eighty "&IF((BP39-ROUNDDOWN(BP39,-1))=1,D39,"")&IF((BP39-ROUNDDOWN(BP39,-1))=2,F39,"")&IF((BP39-ROUNDDOWN(BP39,-1))=G39,H39,"")&IF((BP39-ROUNDDOWN(BP39,-1))=I39,J39,"")&IF((BP39-ROUNDDOWN(BP39,-1))=K39,L39,"")&IF((BP39-ROUNDDOWN(BP39,-1))=M39,N39,"")&IF((BP39-ROUNDDOWN(BP39,-1))=O39,P39,"")&IF((BP39-ROUNDDOWN(BP39,-1))=Q39,R39,"")&IF((BP39-ROUNDDOWN(BP39,-1))=S39,T39,""),""))) | BK39: =IF(BP39="","",IF(BP39>79,"",IF(BP39>=70,"seventy "&IF((BP39-ROUNDDOWN(BP39,-1))=1,D39,"")&IF((BP39-ROUNDDOWN(BP39,-1))=2,F39,"")&IF((BP39-ROUNDDOWN(BP39,-1))=G39,H39,"")&IF((BP39-ROUNDDOWN(BP39,-1))=I39,J39,"")&IF((BP39-ROUNDDOWN(BP39,-1))=K39,L39,"")&IF((BP39-ROUNDDOWN(BP39,-1))=M39,N39,"")&IF((BP39-ROUNDDOWN(BP39,-1))=O39,P39,"")&IF((BP39-ROUNDDOWN(BP39,-1))=Q39,R39,"")&IF((BP39-ROUNDDOWN(BP39,-1))=S39,T39,""),IF(BP39>=60,"sixty "&IF((BP39-ROUNDDOWN(BP39,-1))=1,D39,"")&IF((BP39-ROUNDDOWN(BP39,-1))=2,F39,"")&IF((BP39-ROUNDDOWN(BP39,-1))=G39,H39,"")&IF((BP39-ROUNDDOWN(BP39,-1))=I39,J39,"")&IF((BP39-ROUNDDOWN(BP39,-1))=K39,L39,"")&IF((BP39-ROUNDDOWN(BP39,-1))=M39,N39,"")&IF((BP39-ROUNDDOWN(BP39,-1))=O39,P39,"")&IF((BP39-ROUNDDOWN(BP39,-1))=Q39,R39,"")&IF((BP39-ROUNDDOWN(BP39,-1))=S39,T39,""),"")))) | BL39: =IF(BP39="","",IF(BP39>59,"",IF(BP39>=50,"fifty "&IF((BP39-ROUNDDOWN(BP39,-1))=1,D39,"")&IF((BP39-ROUNDDOWN(BP39,-1))=2,F39,"")&IF((BP39-ROUNDDOWN(BP39,-1))=G39,H39,"")&IF((BP39-ROUNDDOWN(BP39,-1))=I39,J39,"")&IF((BP39-ROUNDDOWN(BP39,-1))=K39,L39,"")&IF((BP39-ROUNDDOWN(BP39,-1))=M39,N39,"")&IF((BP39-ROUNDDOWN(BP39,-1))=O39,P39,"")&IF((BP39-ROUNDDOWN(BP39,-1))=Q39,R39,"")&IF((BP39-ROUNDDOWN(BP39,-1))=S39,T39,""),IF(BP39>=40,"forty "&IF((BP39-ROUNDDOWN(BP39,-1))=1,D39,"")&IF((BP39-ROUNDDOWN(BP39,-1))=2,F39,"")&IF((BP39-ROUNDDOWN(BP39,-1))=G39,H39,"")&IF((BP39-ROUNDDOWN(BP39,-1))=I39,J39,"")&IF((BP39-ROUNDDOWN(BP39,-1))=K39,L39,"")&IF((BP39-ROUNDDOWN(BP39,-1))=M39,N39,"")&IF((BP39-ROUNDDOWN(BP39,-1))=O39,P39,"")&IF((BP39-ROUNDDOWN(BP39,-1))=Q39,R39,"")&IF((BP39-ROUNDDOWN(BP39,-1))=S39,T39,""),"")))) | BM39: =IF(BP39="","",IF(BP39>39,"",IF(BP39>=30,"thirty "&IF((BP39-ROUNDDOWN(BP39,-1))=1,D39,"")&IF((BP39-ROUNDDOWN(BP39,-1))=2,F39,"")&IF((BP39-ROUNDDOWN(BP39,-1))=G39,H39,"")&IF((BP39-ROUNDDOWN(BP39,-1))=I39,J39,"")&IF((BP39-ROUNDDOWN(BP39,-1))=K39,L39,"")&IF((BP39-ROUNDDOWN(BP39,-1))=M39,N39,"")&IF((BP39-ROUNDDOWN(BP39,-1))=O39,P39,"")&IF((BP39-ROUNDDOWN(BP39,-1))=Q39,R39,"")&IF((BP39-ROUNDDOWN(BP39,-1))=S39,T39,""),IF(BP39>=20,"twenty "&IF((BP39-ROUNDDOWN(BP39,-1))=1,D39,"")&IF((BP39-ROUNDDOWN(BP39,-1))=2,F39,"")&IF((BP39-ROUNDDOWN(BP39,-1))=G39,H39,"")&IF((BP39-ROUNDDOWN(BP39,-1))=I39,J39,"")&IF((BP39-ROUNDDOWN(BP39,-1))=K39,L39,"")&IF((BP39-ROUNDDOWN(BP39,-1))=M39,N39,"")&IF((BP39-ROUNDDOWN(BP39,-1))=O39,P39,"")&IF((BP39-ROUNDDOWN(BP39,-1))=Q39,R39,"")&IF((BP39-ROUNDDOWN(BP39,-1))=S39,T39,""),"")))) -> twenty three | BN39: =IF(BP39="","",IF(BP39=C39,D39,"")&IF(BP39=E39,F39,"")&IF(BP39=G39,H39,"")&IF(BP39=I39,J39,"")&IF(BP39=K39,L39,"")&IF(BP39=M39,N39,"")&IF(BP39=O39,P39,"")&IF(BP39=Q39,R39,"")&IF(BP39=S39,T39,"")&IF(BP39=U39,V39,"")&IF(BP39=W39,X39,"")&IF(BP39=Y39,Z39,"")&IF(BP39=AA39,AB39,"")&IF(BP39=AC39,AD39,"")&IF(BP39=AE39,AF39,"")&IF(BP39=AG39,AH39,"")&IF(BP39=AI39,AJ39,"")&IF(BP39=AK39,AL39,"")&IF(BP39=AM39,AN39,"")) | BP39: =IF(A39>=1000,ROUNDDOWN((A39-ROUNDDOWN(A39,-5))/1000,0),"") -> 23 | BQ39: =IF(BJ39="","",BJ39)&IF(BK39="","",BK39)&IF(BL39="","",BL39)&IF(BM39="","",BM39)&IF(BN39="","",BN39) -> twenty three | BR39: HUNDRED | BS39: =IF(BY39="","",IF(BY39>=90,"ninety "&IF((BY39-ROUNDDOWN(BY39,-1))=1,D39,"")&IF((BY39-ROUNDDOWN(BY39,-1))=2,F39,"")&IF((BY39-ROUNDDOWN(BY39,-1))=G39,H39,"")&IF((BY39-ROUNDDOWN(BY39,-1))=I39,J39,"")&IF((BY39-ROUNDDOWN(BY39,-1))=K39,L39,"")&IF((BY39-ROUNDDOWN(BY39,-1))=M39,N39,"")&IF((BY39-ROUNDDOWN(BY39,-1))=O39,P39,"")&IF((BY39-ROUNDDOWN(BY39,-1))=Q39,R39,"")&IF((BY39-ROUNDDOWN(BY39,-1))=S39,T39,""),IF(BY39>=80,"eighty "&IF((BY39-ROUNDDOWN(BY39,-1))=1,D39,"")&IF((BY39-ROUNDDOWN(BY39,-1))=2,F39,"")&IF((BY39-ROUNDDOWN(BY39,-1))=G39,H39,"")&IF((BY39-ROUNDDOWN(BY39,-1))=I39,J39,"")&IF((BY39-ROUNDDOWN(BY39,-1))=K39,L39,"")&IF((BY39-ROUNDDOWN(BY39,-1))=M39,N39,"")&IF((BY39-ROUNDDOWN(BY39,-1))=O39,P39,"")&IF((BY39-ROUNDDOWN(BY39,-1))=Q39,R39,"")&IF((BY39-ROUNDDOWN(BY39,-1))=S39,T39,""),""))) | BT39: =IF(BY39="","",IF(BY39>79,"",IF(BY39>=70,"seventy "&IF((BY39-ROUNDDOWN(BY39,-1))=1,D39,"")&IF((BY39-ROUNDDOWN(BY39,-1))=2,F39,"")&IF((BY39-ROUNDDOWN(BY39,-1))=G39,H39,"")&IF((BY39-ROUNDDOWN(BY39,-1))=I39,J39,"")&IF((BY39-ROUNDDOWN(BY39,-1))=K39,L39,"")&IF((BY39-ROUNDDOWN(BY39,-1))=M39,N39,"")&IF((BY39-ROUNDDOWN(BY39,-1))=O39,P39,"")&IF((BY39-ROUNDDOWN(BY39,-1))=Q39,R39,"")&IF((BY39-ROUNDDOWN(BY39,-1))=S39,T39,""),IF(BY39>=60,"sixty "&IF((BY39-ROUNDDOWN(BY39,-1))=1,D39,"")&IF((BY39-ROUNDDOWN(BY39,-1))=2,F39,"")&IF((BY39-ROUNDDOWN(BY39,-1))=G39,H39,"")&IF((BY39-ROUNDDOWN(BY39,-1))=I39,J39,"")&IF((BY39-ROUNDDOWN(BY39,-1))=K39,L39,"")&IF((BY39-ROUNDDOWN(BY39,-1))=M39,N39,"")&IF((BY39-ROUNDDOWN(BY39,-1))=O39,P39,"")&IF((BY39-ROUNDDOWN(BY39,-1))=Q39,R39,"")&IF((BY39-ROUNDDOWN(BY39,-1))=S39,T39,""),"")))) | BU39: =IF(BY39="","",IF(BY39>59,"",IF(BY39>=50,"fifty "&IF((BY39-ROUNDDOWN(BY39,-1))=1,D39,"")&IF((BY39-ROUNDDOWN(BY39,-1))=2,F39,"")&IF((BY39-ROUNDDOWN(BY39,-1))=G39,H39,"")&IF((BY39-ROUNDDOWN(BY39,-1))=I39,J39,"")&IF((BY39-ROUNDDOWN(BY39,-1))=K39,L39,"")&IF((BY39-ROUNDDOWN(BY39,-1))=M39,N39,"")&IF((BY39-ROUNDDOWN(BY39,-1))=O39,P39,"")&IF((BY39-ROUNDDOWN(BY39,-1))=Q39,R39,"")&IF((BY39-ROUNDDOWN(BY39,-1))=S39,T39,""),IF(BY39>=40,"forty "&IF((BY39-ROUNDDOWN(BY39,-1))=1,D39,"")&IF((BY39-ROUNDDOWN(BY39,-1))=2,F39,"")&IF((BY39-ROUNDDOWN(BY39,-1))=G39,H39,"")&IF((BY39-ROUNDDOWN(BY39,-1))=I39,J39,"")&IF((BY39-ROUNDDOWN(BY39,-1))=K39,L39,"")&IF((BY39-ROUNDDOWN(BY39,-1))=M39,N39,"")&IF((BY39-ROUNDDOWN(BY39,-1))=O39,P39,"")&IF((BY39-ROUNDDOWN(BY39,-1))=Q39,R39,"")&IF((BY39-ROUNDDOWN(BY39,-1))=S39,T39,""),"")))) | BV39: =IF(BY39="","",IF(BY39>39,"",IF(BY39>=30,"thirty "&IF((BY39-ROUNDDOWN(BY39,-1))=1,D39,"")&IF((BY39-ROUNDDOWN(BY39,-1))=2,F39,"")&IF((BY39-ROUNDDOWN(BY39,-1))=G39,H39,"")&IF((BY39-ROUNDDOWN(BY39,-1))=I39,J39,"")&IF((BY39-ROUNDDOWN(BY39,-1))=K39,L39,"")&IF((BY39-ROUNDDOWN(BY39,-1))=M39,N39,"")&IF((BY39-ROUNDDOWN(BY39,-1))=O39,P39,"")&IF((BY39-ROUNDDOWN(BY39,-1))=Q39,R39,"")&IF((BY39-ROUNDDOWN(BY39,-1))=S39,T39,""),IF(BY39>=20,"twenty "&IF((BY39-ROUNDDOWN(BY39,-1))=1,D39,"")&IF((BY39-ROUNDDOWN(BY39,-1))=2,F39,"")&IF((BY39-ROUNDDOWN(BY39,-1))=G39,H39,"")&IF((BY39-ROUNDDOWN(BY39,-1))=I39,J39,"")&IF((BY39-ROUNDDOWN(BY39,-1))=K39,L39,"")&IF((BY39-ROUNDDOWN(BY39,-1))=M39,N39,"")&IF((BY39-ROUNDDOWN(BY39,-1))=O39,P39,"")&IF((BY39-ROUNDDOWN(BY39,-1))=Q39,R39,"")&IF((BY39-ROUNDDOWN(BY39,-1))=S39,T39,""),"")))) | BW39: =IF(BY39="","",IF(BY39=C39,D39,"")&IF(BY39=E39,F39,"")&IF(BY39=G39,H39,"")&IF(BY39=I39,J39,"")&IF(BY39=K39,L39,"")&IF(BY39=M39,N39,"")&IF(BY39=O39,P39,"")&IF(BY39=Q39,R39,"")&IF(BY39=S39,T39,"")&IF(BY39=U39,V39,"")&IF(BY39=W39,X39,"")&IF(BY39=Y39,Z39,"")&IF(BY39=AA39,AB39,"")&IF(BY39=AC39,AD39,"")&IF(BY39=AE39,AF39,"")&IF(BY39=AG39,AH39,"")&IF(BY39=AI39,AJ39,"")&IF(BY39=AK39,AL39,"")&IF(BY39=AM39,AN39,"")) -> five | BY39: =IF(A39>=100,ROUNDDOWN((A39-ROUNDDOWN(A39,-3))/100,0),"") -> 5 | BZ39: =IF(BS39="","",BS39)&IF(BT39="","",BT39)&IF(BU39="","",BU39)&IF(BV39="","",BV39)&IF(BW39="","",BW39) -> five | CA39: TENS | CB39: =IF(CH39="","",IF(CH39>=90,"ninety "&IF((CH39-ROUNDDOWN(CH39,-1))=1,D39,"")&IF((CH39-ROUNDDOWN(CH39,-1))=2,F39,"")&IF((CH39-ROUNDDOWN(CH39,-1))=G39,H39,"")&IF((CH39-ROUNDDOWN(CH39,-1))=I39,J39,"")&IF((CH39-ROUNDDOWN(CH39,-1))=K39,L39,"")&IF((CH39-ROUNDDOWN(CH39,-1))=M39,N39,"")&IF((CH39-ROUNDDOWN(CH39,-1))=O39,P39,"")&IF((CH39-ROUNDDOWN(CH39,-1))=Q39,R39,"")&IF((CH39-ROUNDDOWN(CH39,-1))=S39,T39,""),IF(CH39>=80,"eighty "&IF((CH39-ROUNDDOWN(CH39,-1))=1,D39,"")&IF((CH39-ROUNDDOWN(CH39,-1))=2,F39,"")&IF((CH39-ROUNDDOWN(CH39,-1))=G39,H39,"")&IF((CH39-ROUNDDOWN(CH39,-1))=I39,J39,"")&IF((CH39-ROUNDDOWN(CH39,-1))=K39,L39,"")&IF((CH39-ROUNDDOWN(CH39,-1))=M39,N39,"")&IF((CH39-ROUNDDOWN(CH39,-1))=O39,P39,"")&IF((CH39-ROUNDDOWN(CH39,-1))=Q39,R39,"")&IF((CH39-ROUNDDOWN(CH39,-1))=S39,T39,""),""))) | CC39: =IF(CH39="","",IF(CH39>79,"",IF(CH39>=70,"seventy "&IF((CH39-ROUNDDOWN(CH39,-1))=1,D39,"")&IF((CH39-ROUNDDOWN(CH39,-1))=2,F39,"")&IF((CH39-ROUNDDOWN(CH39,-1))=G39,H39,"")&IF((CH39-ROUNDDOWN(CH39,-1))=I39,J39,"")&IF((CH39-ROUNDDOWN(CH39,-1))=K39,L39,"")&IF((CH39-ROUNDDOWN(CH39,-1))=M39,N39,"")&IF((CH39-ROUNDDOWN(CH39,-1))=O39,P39,"")&IF((CH39-ROUNDDOWN(CH39,-1))=Q39,R39,"")&IF((CH39-ROUNDDOWN(CH39,-1))=S39,T39,""),IF(CH39>=60,"sixty "&IF((CH39-ROUNDDOWN(CH39,-1))=1,D39,"")&IF((CH39-ROUNDDOWN(CH39,-1))=2,F39,"")&IF((CH39-ROUNDDOWN(CH39,-1))=G39,H39,"")&IF((CH39-ROUNDDOWN(CH39,-1))=I39,J39,"")&IF((CH39-ROUNDDOWN(CH39,-1))=K39,L39,"")&IF((CH39-ROUNDDOWN(CH39,-1))=M39,N39,"")&IF((CH39-ROUNDDOWN(CH39,-1))=O39,P39,"")&IF((CH39-ROUNDDOWN(CH39,-1))=Q39,R39,"")&IF((CH39-ROUNDDOWN(CH39,-1))=S39,T39,""),"")))) | CD39: =IF(CH39="","",IF(CH39>59,"",IF(CH39>=50,"fifty "&IF((CH39-ROUNDDOWN(CH39,-1))=1,D39,"")&IF((CH39-ROUNDDOWN(CH39,-1))=2,F39,"")&IF((CH39-ROUNDDOWN(CH39,-1))=G39,H39,"")&IF((CH39-ROUNDDOWN(CH39,-1))=I39,J39,"")&IF((CH39-ROUNDDOWN(CH39,-1))=K39,L39,"")&IF((CH39-ROUNDDOWN(CH39,-1))=M39,N39,"")&IF((CH39-ROUNDDOWN(CH39,-1))=O39,P39,"")&IF((CH39-ROUNDDOWN(CH39,-1))=Q39,R39,"")&IF((CH39-ROUNDDOWN(CH39,-1))=S39,T39,""),IF(CH39>=40,"forty "&IF((CH39-ROUNDDOWN(CH39,-1))=1,D39,"")&IF((CH39-ROUNDDOWN(CH39,-1))=2,F39,"")&IF((CH39-ROUNDDOWN(CH39,-1))=G39,H39,"")&IF((CH39-ROUNDDOWN(CH39,-1))=I39,J39,"")&IF((CH39-ROUNDDOWN(CH39,-1))=K39,L39,"")&IF((CH39-ROUNDDOWN(CH39,-1))=M39,N39,"")&IF((CH39-ROUNDDOWN(CH39,-1))=O39,P39,"")&IF((CH39-ROUNDDOWN(CH39,-1))=Q39,R39,"")&IF((CH39-ROUNDDOWN(CH39,-1))=S39,T39,""),"")))) | CE39: =IF(CH39="","",IF(CH39>39,"",IF(CH39>=30,"thirty "&IF((CH39-ROUNDDOWN(CH39,-1))=1,D39,"")&IF((CH39-ROUNDDOWN(CH39,-1))=2,F39,"")&IF((CH39-ROUNDDOWN(CH39,-1))=G39,H39,"")&IF((CH39-ROUNDDOWN(CH39,-1))=I39,J39,"")&IF((CH39-ROUNDDOWN(CH39,-1))=K39,L39,"")&IF((CH39-ROUNDDOWN(CH39,-1))=M39,N39,"")&IF((CH39-ROUNDDOWN(CH39,-1))=O39,P39,"")&IF((CH39-ROUNDDOWN(CH39,-1))=Q39,R39,"")&IF((CH39-ROUNDDOWN(CH39,-1))=S39,T39,""),IF(CH39>=20,"twenty "&IF((CH39-ROUNDDOWN(CH39,-1))=1,D39,"")&IF((CH39-ROUNDDOWN(CH39,-1))=2,F39,"")&IF((CH39-ROUNDDOWN(CH39,-1))=G39,H39,"")&IF((CH39-ROUNDDOWN(CH39,-1))=I39,J39,"")&IF((CH39-ROUNDDOWN(CH39,-1))=K39,L39,"")&IF((CH39-ROUNDDOWN(CH39,-1))=M39,N39,"")&IF((CH39-ROUNDDOWN(CH39,-1))=O39,P39,"")&IF((CH39-ROUNDDOWN(CH39,-1))=Q39,R39,"")&IF((CH39-ROUNDDOWN(CH39,-1))=S39,T39,""),"")))) | CF39: =IF(CH39="","",IF(CH39=C39,D39,"")&IF(CH39=E39,F39,"")&IF(CH39=G39,H39,"")&IF(CH39=I39,J39,"")&IF(CH39=K39,L39,"")&IF(CH39=M39,N39,"")&IF(CH39=O39,P39,"")&IF(CH39=Q39,R39,"")&IF(CH39=S39,T39,"")&IF(CH39=U39,V39,"")&IF(CH39=W39,X39,"")&IF(CH39=Y39,Z39,"")&IF(CH39=AA39,AB39,"")&IF(CH39=AC39,AD39,"")&IF(CH39=AE39,AF39,"")&IF(CH39=AG39,AH39,"")&IF(CH39=AI39,AJ39,"")&IF(CH39=AK39,AL39,"")&IF(CH39=AM39,AN39,"")) | CH39: =IF(A39>=1,ROUNDDOWN(A39-ROUNDDOWN(A39,-2),0),"") -> 0 | CI39: =IF(CB39="","",CB39)&IF(CC39="","",CC39)&IF(CD39="","",CD39)&IF(CE39="","",CE39)&IF(CF39="","",CF39) | CJ39: PAISE | CK39: =IF(CQ39="","",IF(CQ39>=90,"ninety "&IF((CQ39-ROUNDDOWN(CQ39,-1))=1,D39,"")&IF((CQ39-ROUNDDOWN(CQ39,-1))=2,F39,"")&IF((CQ39-ROUNDDOWN(CQ39,-1))=G39,H39,"")&IF((CQ39-ROUNDDOWN(CQ39,-1))=I39,J39,"")&IF((CQ39-ROUNDDOWN(CQ39,-1))=K39,L39,"")&IF((CQ39-ROUNDDOWN(CQ39,-1))=M39,N39,"")&IF((CQ39-ROUNDDOWN(CQ39,-1))=O39,P39,"")&IF((CQ39-ROUNDDOWN(CQ39,-1))=Q39,R39,"")&IF((CQ39-ROUNDDOWN(CQ39,-1))=S39,T39,""),IF(CQ39>=80,"eighty "&IF((CQ39-ROUNDDOWN(CQ39,-1))=1,D39,"")&IF((CQ39-ROUNDDOWN(CQ39,-1))=2,F39,"")&IF((CQ39-ROUNDDOWN(CQ39,-1))=G39,H39,"")&IF((CQ39-ROUNDDOWN(CQ39,-1))=I39,J39,"")&IF((CQ39-ROUNDDOWN(CQ39,-1))=K39,L39,"")&IF((CQ39-ROUNDDOWN(CQ39,-1))=M39,N39,"")&IF((CQ39-ROUNDDOWN(CQ39,-1))=O39,P39,"")&IF((CQ39-ROUNDDOWN(CQ39,-1))=Q39,R39,"")&IF((CQ39-ROUNDDOWN(CQ39,-1))=S39,T39,""),""))) | CL39: =IF(CQ39="","",IF(CQ39>79,"",IF(CQ39>=70,"seventy "&IF((CQ39-ROUNDDOWN(CQ39,-1))=1,D39,"")&IF((CQ39-ROUNDDOWN(CQ39,-1))=2,F39,"")&IF((CQ39-ROUNDDOWN(CQ39,-1))=G39,H39,"")&IF((CQ39-ROUNDDOWN(CQ39,-1))=I39,J39,"")&IF((CQ39-ROUNDDOWN(CQ39,-1))=K39,L39,"")&IF((CQ39-ROUNDDOWN(CQ39,-1))=M39,N39,"")&IF((CQ39-ROUNDDOWN(CQ39,-1))=O39,P39,"")&IF((CQ39-ROUNDDOWN(CQ39,-1))=Q39,R39,"")&IF((CQ39-ROUNDDOWN(CQ39,-1))=S39,T39,""),IF(CQ39>=60,"sixty "&IF((CQ39-ROUNDDOWN(CQ39,-1))=1,D39,"")&IF((CQ39-ROUNDDOWN(CQ39,-1))=2,F39,"")&IF((CQ39-ROUNDDOWN(CQ39,-1))=G39,H39,"")&IF((CQ39-ROUNDDOWN(CQ39,-1))=I39,J39,"")&IF((CQ39-ROUNDDOWN(CQ39,-1))=K39,L39,"")&IF((CQ39-ROUNDDOWN(CQ39,-1))=M39,N39,"")&IF((CQ39-ROUNDDOWN(CQ39,-1))=O39,P39,"")&IF((CQ39-ROUNDDOWN(CQ39,-1))=Q39,R39,"")&IF((CQ39-ROUNDDOWN(CQ39,-1))=S39,T39,""),"")))) | CM39: =IF(CQ39="","",IF(CQ39>59,"",IF(CQ39>=50,"fifty "&IF((CQ39-ROUNDDOWN(CQ39,-1))=1,D39,"")&IF((CQ39-ROUNDDOWN(CQ39,-1))=2,F39,"")&IF((CQ39-ROUNDDOWN(CQ39,-1))=G39,H39,"")&IF((CQ39-ROUNDDOWN(CQ39,-1))=I39,J39,"")&IF((CQ39-ROUNDDOWN(CQ39,-1))=K39,L39,"")&IF((CQ39-ROUNDDOWN(CQ39,-1))=M39,N39,"")&IF((CQ39-ROUNDDOWN(CQ39,-1))=O39,P39,"")&IF((CQ39-ROUNDDOWN(CQ39,-1))=Q39,R39,"")&IF((CQ39-ROUNDDOWN(CQ39,-1))=S39,T39,""),IF(CQ39>=40,"forty "&IF((CQ39-ROUNDDOWN(CQ39,-1))=1,D39,"")&IF((CQ39-ROUNDDOWN(CQ39,-1))=2,F39,"")&IF((CQ39-ROUNDDOWN(CQ39,-1))=G39,H39,"")&IF((CQ39-ROUNDDOWN(CQ39,-1))=I39,J39,"")&IF((CQ39-ROUNDDOWN(CQ39,-1))=K39,L39,"")&IF((CQ39-ROUNDDOWN(CQ39,-1))=M39,N39,"")&IF((CQ39-ROUNDDOWN(CQ39,-1))=O39,P39,"")&IF((CQ39-ROUNDDOWN(CQ39,-1))=Q39,R39,"")&IF((CQ39-ROUNDDOWN(CQ39,-1))=S39,T39,""),"")))) | CN39: =IF(CQ39="","",IF(CQ39>39,"",IF(CQ39>=30,"thirty "&IF((CQ39-ROUNDDOWN(CQ39,-1))=1,D39,"")&IF((CQ39-ROUNDDOWN(CQ39,-1))=2,F39,"")&IF((CQ39-ROUNDDOWN(CQ39,-1))=G39,H39,"")&IF((CQ39-ROUNDDOWN(CQ39,-1))=I39,J39,"")&IF((CQ39-ROUNDDOWN(CQ39,-1))=K39,L39,"")&IF((CQ39-ROUNDDOWN(CQ39,-1))=M39,N39,"")&IF((CQ39-ROUNDDOWN(CQ39,-1))=O39,P39,"")&IF((CQ39-ROUNDDOWN(CQ39,-1))=Q39,R39,"")&IF((CQ39-ROUNDDOWN(CQ39,-1))=S39,T39,""),IF(CQ39>=20,"twenty "&IF((CQ39-ROUNDDOWN(CQ39,-1))=1,D39,"")&IF((CQ39-ROUNDDOWN(CQ39,-1))=2,F39,"")&IF((CQ39-ROUNDDOWN(CQ39,-1))=G39,H39,"")&IF((CQ39-ROUNDDOWN(CQ39,-1))=I39,J39,"")&IF((CQ39-ROUNDDOWN(CQ39,-1))=K39,L39,"")&IF((CQ39-ROUNDDOWN(CQ39,-1))=M39,N39,"")&IF((CQ39-ROUNDDOWN(CQ39,-1))=O39,P39,"")&IF((CQ39-ROUNDDOWN(CQ39,-1))=Q39,R39,"")&IF((CQ39-ROUNDDOWN(CQ39,-1))=S39,T39,""),"")))) | CO39: =IF(CQ39="","",IF(CQ39=C39,D39,"")&IF(CQ39=E39,F39,"")&IF(CQ39=G39,H39,"")&IF(CQ39=I39,J39,"")&IF(CQ39=K39,L39,"")&IF(CQ39=M39,N39,"")&IF(CQ39=O39,P39,"")&IF(CQ39=Q39,R39,"")&IF(CQ39=S39,T39,"")&IF(CQ39=U39,V39,"")&IF(CQ39=W39,X39,"")&IF(CQ39=Y39,Z39,"")&IF(CQ39=AA39,AB39,"")&IF(CQ39=AC39,AD39,"")&IF(CQ39=AE39,AF39,"")&IF(CQ39=AG39,AH39,"")&IF(CQ39=AI39,AJ39,"")&IF(CQ39=AK39,AL39,"")&IF(CQ39=AM39,AN39,"")) | CQ39: =IF((A39-ROUNDDOWN(A39,0))>0,ROUND((A39-ROUNDDOWN(A39,0))*100,0),"") | CR39: =IF(CK39="","",CK39)&IF(CL39="","",CL39)&IF(CM39="","",CM39)&IF(CN39="","",CN39)&IF(CO39="","",CO39) | CS39: <= IN WORDS | CU39: =IF(A39="","","(Rupees "&IF(AY39="","",AY39&" crore ")&IF(BH39="","",BH39&" lakh ")&IF(BQ39="","",BQ39&" thousand ")&IF(BZ39="","",BZ39&" hundred ")&IF(CI39="","",CI39)&IF(CR39="",""," and paise "&CR39)&") only.") -> (Rupees forty eight lakh twenty three thousand five hundred ) only.

Sheet Rennovation Measurement
A1: Name of Work :- Repairing and Renovation of Circuit House at Bokakhat Co District under Golaghat District
A2: (Rates are quoted from DSR (civil) of 2021)
A3: DETAIL ESTIMATE
A4: SL. No. | B4: CODE NO | C4: PARTICULARS | K4: QTY | L4: Unit | M4: RATE | N4: AMOUNT
A6: 1 | B6: 15.7 | C6: Demolishing brick work manually/ by mechanical means including stacking of serviceable material and disposal of unserviceable material within 50 metres lead as per direction of Engineer-in-charge.15.7.4 in cement mortar
C7: In cement mortar | D7: 1 | E7: x | F7: 10.45 | G7: x | H7: 0.12 | I7: x | J7: 0.78 | K7: =D7*F7*H7*J7 -> 0.98 | L7: Cum
C8: In cement mortar | D8: 1 | E8: x | F8: 2.3 | G8: x | H8: 0.12 | I8: x | J8: 2.1 | K8: =D8*F8*H8*J8 -> 0.58 | L8: Cum
C9: Total | K9: =ROUND(SUM(K7:K8), 2) -> 1.56 | L9: Cum | M9: 1698.45 | N9: =ROUND(K9*M9, 2) -> 2649.58
A10: 2 | B10: 15.23.1 | C10: Dismantling tile work in floors and roofs laid in cement mortar including stacking material within 50 metres lead. 15.23.1 For thickness of tiles 10 mm to 25 mm
C11: Ground floor.Toilet | D11: 3 | E11: x | F11: 3.15 | I11: x | J11: 1.45 | K11: =D11*F11*J11 -> 13.7 | L11: Sqm
C12: Ground floor.Toilet | D12: 1 | E12: x | F12: 2.05 | I12: x | J12: 1.45 | K12: =D12*F12*J12 -> 2.97 | L12: Sqm
C13: Ground floor.Toilet | D13: 3 | E13: x | F13: 9.2 | I13: x | J13: 1.5 | K13: =D13*F13*J13 -> 41.4 | L13: Sqm
C14: Ground floor.Toilet | D14: 1 | E14: x | F14: 7 | I14: x | J14: 2.1 | K14: =D14*F14*J14 -> 14.7 | L14: Sqm
C15: First floor.Toilet | D15: 4 | E15: x | F15: 3.8 | I15: x | J15: 1.8 | K15: =D15*F15*J15 -> 27.36 | L15: Sqm
C16: First floor.Toilet | D16: 4 | E16: x | F16: 11.2 | I16: x | J16: 2.1 | K16: =D16*F16*J16 -> 94.08 | L16: Sqm
C17: A-Type Cottage Room 1 | D17: 1 | E17: x | F17: 5 | I17: x | J17: 7.5 | K17: =D17*F17*J17 -> 37.5 | L17: Sqm
C18: A-Type Cottage Room 2 | D18: 1 | E18: x | F18: 2.2 | I18: x | J18: 2.5 | K18: =D18*F18*J18 -> 5.5 | L18: Sqm
C19: Total | K19: =ROUND(SUM(K11:K18), 2) -> 237.21 | L19: Sqm | M19: 60.5 | N19: =ROUND(K19*M19, 2) -> 14351.21
A20: 3 | B20: 15.28 | C20: Dismantling roofing including ridges, hips, valleys and gutters etc., and stacking the material within 50 metres lead of: 15.28.1G.S. Sheet
C21: G.S. Sheet | D21: 2 | E21: x | F21: 2.1 | I21: x | J21: 0.85 | K21: =D21*F21*J21 -> 3.57 | L21: Sqm
C22: Total | K22: =ROUND(SUM(K21:K21), 2) -> 3.57 | L22: Sqm | M22: 136 | N22: =ROUND(K22*M22, 2) -> 485.52
A23: 4 | B23: 2.25 | C23: Filling available excavated earth (excluding rock) in trenches, plinth, sides of foundations etc. in layers not exceeding 20cm in depth, consolidating each deposited layer by ramming and watering, lead up to 50 m and lift upto 1.5 m.
C24: Plinth & trenches | D24: 1 | E24: x | F24: 7.7 | G24: x | H24: 2.6 | I24: x | J24: 0.65 | K24: =D24*F24*H24*J24 -> 13.01 | L24: Cum
C25: Total | K25: =ROUND(SUM(K24:K24), 2) -> 13.01 | L25: Cum | M25: 253.95 | N25: =ROUND(K25*M25, 2) -> 3303.89
A26: 5 | B26: 11.2 | C26: Dry brick on edge flooring in required pattern with bricks of class designation 7.5 on a bed of 12 mm mud mortar, including filling joints with Jamuna sand, with common burnt clay non modular bricks.
C27: Flooring area | D27: 1 | E27: x | F27: 6 | I27: x | J27: 1.65 | K27: =D27*F27*J27 -> 9.9 | L27: Sqm
C28: Total | K28: =ROUND(SUM(K27:K27), 2) -> 9.9 | L28: Sqm | M28: 733.3 | N28: =ROUND(K28*M28, 2) -> 7259.67
A29: 6 | B29: 11.5 | C29: 62 mm thick cement concrete flooring with concrete hardener topping, under layer 50 mm thick cement concrete 1:2:4 (1 cement : 2 coarse sand : 4 graded stone aggregate 20mm nominal size) and top layer 12mm thick cement hardener consisting of mix 1:2 (1 cement hardener mix : 2 graded stone aggregate, 6mm nominal size) by volume, hardening compound mixed @ 2 litre per 50 kg of cement or as per manufacture’s specifications. This includes cost of cement slurry, but excluding the cost of nosing of steps etc. complete.
C30: Flooring area | D30: 1 | E30: x | F30: 6 | I30: x | J30: 1.65 | K30: =D30*F30*J30 -> 9.9 | L30: Sqm
C31: Total | K31: =ROUND(SUM(K30:K30), 2) -> 9.9 | L31: Sqm | M31: 928.65 | N31: =ROUND(K31*M31, 2) -> 9193.64
A32: 7 | B32: 11.41 | C32: Providing and laying vitrified floor tiles in different sizes (thickness to be specified by the manufacturer) with water absorption less than 0.08% and conforming to IS: 15622, of approved make, in all colours and shades, laid on 20mm thick cement mortar 1:4 (1 cement : 4 coarse sand), jointing with grey cement slurry @ 3.3 kg/ sqm including grouting the joints with white cement and matching pigments etc., complete. 11.41.2 Size of Tile 600x600 mm.
C33: Existing Kitchen | D33: 1 | E33: x | F33: 6 | I33: x | J33: 3.55 | K33: =D33*F33*J33 -> 21.3 | L33: Sqm
C34: Chawkidar room | D34: 1 | E34: x | F34: 2.95 | I34: x | J34: 3.6 | K34: =D34*F34*J34 -> 10.62 | L34: Sqm
C35: Verandah | D35: 1 | E35: x | F35: 4.25 | I35: x | J35: 7.5 | K35: =D35*F35*J35 -> 31.88 | L35: Sqm
C36: Ground floor toilet | D36: 3 | E36: x | F36: 3.15 | I36: x | J36: 1.45 | K36: =D36*F36*J36 -> 13.7 | L36: Sqm
C37: Ground floor toilet | D37: 1 | E37: x | F37: 2.05 | I37: x | J37: 1.45 | K37: =D37*F37*J37 -> 2.97 | L37: Sqm
C38: First floor toilet | D38: 4 | E38: x | F38: 3.8 | I38: x | J38: 1.8 | K38: =D38*F38*J38 -> 27.36 | L38: Sqm
C39: Dormitory | D39: 1 | E39: x | F39: 9.15 | I39: x | J39: 6 | K39: =D39*F39*J39 -> 54.9 | L39: Sqm
C40: Dormitory portion | D40: 1 | E40: x | F40: 6.4 | I40: x | J40: 3.5 | K40: =D40*F40*J40 -> 22.4 | L40: Sqm
C41: Dormitory portion | D41: 1 | E41: x | F41: 6.4 | I41: x | J41: 1.85 | K41: =D41*F41*J41 -> 11.84 | L41: Sqm
C42: Dormitory Front step | D42: 4 | E42: x | F42: 3.3 | I42: x | J42: 0.35 | K42: =D42*F42*J42 -> 4.62 | L42: Sqm
C43: Dormitory Front step | D43: 4 | E43: x | F43: 3.3 | I43: x | J43: 0.16 | K43: =D43*F43*J43 -> 2.11 | L43: Sqm
C44: A-Type Cottage Room 1 | D44: 1 | E44: x | F44: 5 | I44: x | J44: 7.5 | K44: =D44*F44*J44 -> 37.5 | L44: Sqm
C45: A-Type Cottage Room 2 | D45: 1 | E45: x | F45: 2.2 | I45: x | J45: 2.5 | K45: =D45*F45*J45 -> 5.5 | L45: Sqm
C46: Total | K46: =ROUND(SUM(K33:K45), 2) -> 246.7 | L46: Sqm | M46: 1416.65 | N46: =ROUND(K46*M46, 2) -> 349487.56
A47: 8 | B47: 8.31 | C47: Providing and fixing Ist quality ceramic glazed wall tiles conforming to IS: 15622 (thickness to be specified by the manufacturer), of approved make, in all colours, shades except burgundy, bottle green, black of any size as approved by Engineer-in-Charge, in skirting, risers of steps and dados, over 12 mm thick bed of cement mortar 1:3 (1 cement : 3 coarse sand) and jointing with grey cement slurry @ 3.3kg per sqm, including pointing in white cement mixed with pigment of matching shade complete.
C48: Ground floor toilet | D48: 3 | E48: x | F48: 9.2 | I48: x | J48: 1.5 | K48: =D48*F48*J48 -> 41.4 | L48: Sqm
C49: Ground floor toilet | D49: 1 | E49: x | F49: 7 | I49: x | J49: 2.1 | K49: =D49*F49*J49 -> 14.7 | L49: Sqm
C50: First floor toilet | D50: 4 | E50: x | F50: 11.2 | I50: x | J50: 2.1 | K50: =D50*F50*J50 -> 94.08 | L50: Sqm
C51: Dormitory toilet | D51: 4 | E51: x | F51: 6.9 | I51: x | J51: 2.1 | K51: =D51*F51*J51 -> 57.96 | L51: Sqm
C52: A-Type Cottage Toilet wall | D52: 2 | E52: x | F52: 2.1 | I52: x | J52: 1.5 | K52: =D52*F52*J52 -> 6.3 | L52: Sqm
C53: A-Type Cottage Toilet wall | D53: 2 | E53: x | F53: 2.5 | I53: x | J53: 1.5 | K53: =D53*F53*J53 -> 7.5 | L53: Sqm
C54: Deduct , Door | D54: -1 | E54: x | F54: 1.2 | I54: x | J54: 1.5 | K54: =D54*F54*J54 -> -1.8 | L54: Sqm
C55: Total | K55: =ROUND(SUM(K48:K54), 2) -> 220.14 | L55: Sqm | M55: 1063.45 | N55: =ROUND(K55*M55, 2) -> 234107.88
A56: 9 | B56: 13.26 | C56: Providing and applying plaster of paris putty of 2 mm thickness over plastered surface to prepare the surface even and smooth complete.
C57: Ground floor kitchen | D57: 3 | E57: x | F57: 3.6 | I57: x | J57: 2.95 | K57: =D57*F57*J57 -> 31.86 | L57: Sqm
C58: Ground floor kitchen | D58: 4 | E58: x | F58: 6 | I58: x | J58: 2.95 | K58: =D58*F58*J58 -> 70.8 | L58: Sqm
C59: Chawkidar room | D59: 3 | E59: x | F59: 3.6 | I59: x | J59: 2.95 | K59: =D59*F59*J59 -> 31.86 | L59: Sqm
C60: Chawkidar room | D60: 4 | E60: x | F60: 2.95 | I60: x | J60: 2.95 | K60: =D60*F60*J60 -> 34.81 | L60: Sqm
C61: Ded. Door | D61: -2 | E61: x | F61: 2.1 | I61: x | J61: 1.3 | K61: =D61*F61*J61 -> -5.46 | L61: Sqm
C62: Ded. Window | D62: -2 | E62: x | F62: 1.1 | I62: x | J62: 1.2 | K62: =D62*F62*J62 -> -2.64 | L62: Sqm
C63: Toilet wall | D63: 3 | E63: x | F63: 9.2 | I63: x | J63: 1.5 | K63: =D63*F63*J63 -> 41.4 | L63: Sqm
C64: Toilet wall | D64: 1 | E64: x | F64: 7 | I64: x | J64: 0.95 | K64: =D64*F64*J64 -> 6.65 | L64: Sqm
C65: First floor toilet | D65: 4 | E65: x | F65: 11.2 | I65: x | J65: 0.95 | K65: =D65*F65*J65 -> 42.56 | L65: Sqm
C66: Vip room | D66: 2 | E66: x | F66: 6.4 | I66: x | J66: 3.05 | K66: =D66*F66*J66 -> 39.04 | L66: Sqm
C67: Vip room | D67: 2 | E67: x | F67: 4.7 | I67: x | J67: 3.05 | K67: =D67*F67*J67 -> 28.67 | L67: Sqm
C68: Vip room | D68: 1 | E68: x | F68: 9.96 | I68: x | J68: 3.05 | K68: =D68*F68*J68 -> 30.38 | L68: Sqm
... C74: Room 4 | D74: 2 | E74: x | F74: 6.4 | I74: x | J74: 3.05 | K74: =D74*F74*J74 -> 39.04 | L74: Sqm
C75: Total | K75: =ROUND(SUM(K57:K74), 2) -> 559.9 | L75: Sqm | M75: 214.3 | N75: =ROUND(K75*M75, 2) -> 119986.57
A76: 10 | B76: 13.85 | C76: Applying priming coats with primer of approved brand and manufacture, having low VOC (Volatile Organic Compound ) content 13.85.3 With water thinnable cement primer on wall surface having VOC content less than 50 grams/litre
C77: Interior wall surface (Item 11) | D77: 1 | F77: 1768 | K77: =D77*F77 -> 1768 | L77: Sqm
C78: Exterior wall surface (Item 12) | D78: 1 | F78: 631.8 | K78: =D78*F78 -> 631.8 | L78: Sqm
C79: Total | K79: =ROUND(SUM(K77:K78), 2) -> 2399.8 | L79: Sqm | M79: 64.45 | N79: =ROUND(K79*M79, 2) -> 154667.11
A80: 11 | B80: 13.83 | C80: Wall painting with premium acrylic emulsion paint of interior grade, having VOC (Volatile Organic Compound ) content less than 50 grams/ litre of approved brand and manufacture, including applying additional coats wherever required to achieve even shade and colour. 13.83.2 Two coats
C81: Room 1 (Bed Room: 5.644m x 5.508m)
C82: All round walls (Perimeter = 2*(5.644+5.508)m) | D82: 1 | E82: x | F82: 22.3 | I82: x | J82: 3.05 | K82: =D82*F82*J82 -> 68.02 | L82: sqm
C83: Deduct : Door to corridor (D1) | D83: -1 | E83: x | F83: 1.2 | I83: x | J83: 2.1 | K83: =D83*F83*J83 -> -2.52 | L83: sqm
C84: Deduct : Windows (W1 - 2 nos) | D84: -2 | E84: x | F84: 1.5 | I84: x | J84: 1.8 | K84: =D84*F84*J84 -> -5.4 | L84: sqm
C85: Room 2 (Large Room / Suite: 6.500m x 5.508m)
C86: All round walls (Perimeter = 2*(6.500+5.508)m) | D86: 1 | E86: x | F86: 24.02 | I86: x | J86: 3.05 | K86: =D86*F86*J86 -> 73.26 | L86: sqm
C87: Deduct : Door to corridor (D1) | D87: -1 | E87: x | F87: 1.2 | I87: x | J87: 2.1 | K87: =D87*F87*J87 -> -2.52 | L87: sqm
C88: Deduct : Windows (W1 - 3 nos) | D88: -3 | E88: x | F88: 1.5 | I88: x | J88: 1.8 | K88: =D88*F88*J88 -> -8.1 | L88: sqm
C89: Room 3 (Bed Room: 5.644m x 4.512m)
C90: All round walls (Perimeter = 2*(5.644+4.512)m) | D90: 1 | E90: x | F90: 20.31 | I90: x | J90: 3.05 | K90: =D90*F90*J90 -> 61.95 | L90: sqm
C91: Deduct : Door to corridor (D1) | D91: -1 | E91: x | F91: 1.2 | I91: x | J91: 2.1 | K91: =D91*F91*J91 -> -2.52 | L91: sqm
C92: Deduct : Window (W1 - left wall) | D92: -1 | E92: x | F92: 1.5 | I92: x | J92: 1.8 | K92: =D92*F92*J92 -> -2.7 | L92: sqm
C93: Room 4 (Bed Room: 5.644m x 3.912m)
C94: All round walls (Perimeter = 2*(5.644+3.912)m) | D94: 1 | E94: x | F94: 19.11 | I94: x | J94: 3.05 | K94: =D94*F94*J94 -> 58.29 | L94: sqm
C95: Deduct : Door to corridor (D1) | D95: -1 | E95: x | F95: 1.2 | I95: x | J95: 2.1 | K95: =D95*F95*J95 -> -2.52 | L95: sqm
C96: Deduct : Window (W1 - left wall) | D96: -1 | E96: x | F96: 1.5 | I96: x | J96: 1.8 | K96: =D96*F96*J96 -> -2.7 | L96: sqm
C97: Room 5 (Bed Room: 5.644m x 4.512m)
C98: All round walls (Perimeter = 2*(5.644+4.512)m) | D98: 1 | E98: x | F98: 20.31 | I98: x | J98: 3.05 | K98: =D98*F98*J98 -> 61.95 | L98: sqm
C99: Deduct : Door to corridor (D1) | D99: -1 | E99: x | F99: 1.2 | I99: x | J99: 2.1 | K99: =D99*F99*J99 -> -2.52 | L99: sqm
C100: Deduct : Window (W1 - left wall) | D100: -1 | E100: x | F100: 1.5 | I100: x | J100: 1.8 | K100: =D100*F100*J100 -> -2.7 | L100: sqm
C101: Room 6 (Meeting / Living Hall with Annex: 7.944m x 2.944m)
C102: All round walls (Perimeter = 2*(7.944+2.944)m) | D102: 1 | E102: x | F102: 21.78 | I102: x | J102: 3.05 | K102: =D102*F102*J102 -> 66.43 | L102: sqm
C103: Deduct : Double Door (to corridor) | D103: -1 | E103: x | F103: 1.5 | I103: x | J103: 2.1 | K103: =D103*F103*J103 -> -3.15 | L103: sqm
C104: Deduct : Window (W1 - west wall) | D104: -1 | E104: x | F104: 1.5 | I104: x | J104: 1.8 | K104: =D104*F104*J104 -> -2.7 | L104: sqm
C105: Room 7 (Attached Room / Toilet: 2.300m x 3.228m)
C106: All round walls (Perimeter = 2*(2.300+3.228)m) | D106: 1 | E106: x | F106: 11.06 | I106: x | J106: 3.05 | K106: =D106*F106*J106 -> 33.73 | L106: sqm
...

Sheet Rennovation BOQ
A1: ='AType Cottage'!A1 -> Name of Work :- Repairing and Renovation of Circuit House at Bokakhat Co District under Golaghat District
A2: ITEM NO. | B2: Sl No | C2: DESCRIPTION OF ITEM | J2: Qty | K2: UNIT | L2: RATE Rs | M2: AMOUNT
A3: 1 | B3: 15.7 | C3: Demolishing brick work manually/ by mechanical means including stacking of serviceable material and disposal of unserviceable material within 50 metres lead as per direction of Engineer-in-charge.15.7.4 in cement mortar | J3: ='Rennovation Measurement'!K9 -> 1.56 | K3: Cum | L3: 1698.45 | M3: =ROUND(J3*L3,0) -> 2650 | P3: =+J3*L3 -> 2649.58
A4: 2 | B4: 15.23.1 | C4: Dismantling tile work in floors and roofs laid in cement mortar including stacking material within 50 metres lead. 15.23.1 For thickness of tiles 10 mm to 25 mm | J4: ='Rennovation Measurement'!K19 -> 237.21 | K4: Sqm | L4: 60.5 | M4: =ROUND(J4*L4,0) -> 14351 | O4: =5.95+3.1 -> 9.05
A5: 3 | B5: 15.28 | C5: Dismantling roofing including ridges, hips, valleys and gutters etc., and stacking the material within 50 metres lead of: 15.28.1G.S. Sheet | J5: ='Rennovation Measurement'!K22 -> 3.57 | K5: Sqm | L5: 136 | M5: =ROUND(J5*L5,0) -> 486
A6: 4 | B6: 2.25 | C6: Filling available excavated earth (excluding rock) in trenches, plinth, sides of foundations etc. in layers not exceeding 20cm in depth, consolidating each deposited layer by ramming and watering, lead up to 50 m and lift upto 1.5 m. | J6: ='Rennovation Measurement'!K25 -> 13.01 | K6: Cum | L6: 253.95 | M6: =ROUND(J6*L6,0) -> 3304
A7: 5 | B7: 11.2 | C7: Dry brick on edge flooring in required pattern with bricks of class designation 7.5 on a bed of 12 mm mud mortar, including filling joints with Jamuna sand, with common burnt clay non modular bricks. | J7: ='Rennovation Measurement'!K28 -> 9.9 | K7: Sqm | L7: 733.3 | M7: =ROUND(J7*L7,0) -> 7260
A8: 6 | B8: 11.5 | C8: 62 mm thick cement concrete flooring with concrete hardener topping, under layer 50 mm thick cement concrete 1:2:4 (1 cement : 2 coarse sand : 4 graded stone aggregate 20mm nominal size) and top layer 12mm thick cement hardener consisting of mix 1:2 (1 cement hardener mix : 2 graded stone aggregate, 6mm nominal size) by volume, hardening compound mixed @ 2 litre per 50 kg of cement or as per manufacture’s specifications. This includes cost of cement slurry, but excluding the cost of nosing of steps etc. complete. | J8: ='Rennovation Measurement'!K31 -> 9.9 | K8: Sqm | L8: 928.65 | M8: =ROUND(J8*L8,0) -> 9194
A9: 7 | B9: 11.41 | C9: Providing and laying vitrified floor tiles in different sizes (thickness to be specified by the manufacturer) with water absorption less than 0.08% and conforming to IS: 15622, of approved make, in all colours and shades, laid on 20mm thick cement mortar 1:4 (1 cement : 4 coarse sand), jointing with grey cement slurry @ 3.3 kg/ sqm including grouting the joints with white cement and matching pigments etc., complete. 11.41.2 Size of Tile 600x600 mm. | J9: ='Rennovation Measurement'!K46 -> 246.7 | K9: Sqm | L9: 1416.65 | M9: =ROUND(J9*L9,0) -> 349488
A10: 8 | B10: 8.31 | C10: Providing and fixing Ist quality ceramic glazed wall tiles conforming to IS: 15622 (thickness to be specified by the manufacturer), of approved make, in all colours, shades except burgundy, bottle green, black of any size as approved by Engineer-in-Charge, in skirting, risers of steps and dados, over 12 mm thick bed of cement mortar 1:3 (1 cement : 3 coarse sand) and jointing with grey cement slurry @ 3.3kg per sqm, including pointing in white cement mixed with pigment of matching shade complete. | J10: ='Rennovation Measurement'!K55 -> 220.14 | K10: Sqm | L10: 1063.45 | M10: =ROUND(J10*L10,0) -> 234108
A11: 9 | B11: 13.26 | C11: Providing and applying plaster of paris putty of 2 mm thickness over plastered surface to prepare the surface even and smooth complete. | J11: ='Rennovation Measurement'!K75 -> 559.9 | K11: Sqm | L11: 214.3 | M11: =ROUND(J11*L11,0) -> 119987
A12: 10 | B12: 13.85 | C12: Applying priming coats with primer of approved brand and manufacture, having low VOC (Volatile Organic Compound ) content 13.85.3 With water thinnable cement primer on wall surface having VOC content less than 50 grams/litre | J12: ='Rennovation Measurement'!K79 -> 2399.8 | K12: Sqm | L12: 64.45 | M12: =ROUND(J12*L12,0) -> 154667 | Q12: =21.5+21.5+13+13 -> 69 | R12: 3.2 | S12: =Q12*R12*2 -> 441.6 | T12: =21.5*2*3.2 -> 137.6 | V12: 9.75*2*3.2 | W12: =9.75*4*3.2 -> 124.8 | Z12: 21.5 | AA12: 13 | AB12: 3.2
A13: 11 | B13: 13.83 | C13: Wall painting with premium acrylic emulsion paint of interior grade, having VOC (Volatile Organic Compound ) content less than 50 grams/ litre of approved brand and manufacture, including applying additional coats wherever required to achieve even shade and colour. 13.83.2 Two coats | J13: ='Rennovation Measurement'!K200 -> 2217.57 | K13: Sqm | L13: 121.55 | M13: =ROUND(J13*L13,0) -> 269546 | Q13: 2.15 | R13: 1.5 | S13: =Q13*R13*13*2 -> 83.85 | T13: =R13*Q13*8 -> 25.8 | W13: =0.81*2.1*8 -> 13.608 | Z13: 21.5 | AA13: 13 | AB13: 3.2
A14: 12 | B14: 13.48A | C14: Finishing walls with 100% Premium acrylic emulsion paint having VOC less than 50 gm/litre and UV resistance as per IS 15489:2004, Alkali & fungal resistance, dirt resistance exterior paint of required shade (Company Depot Tinted) with silicon additives. 13.48A.1 New work (Two or more coats applied @ 1.43 litre/ 10 sqm. Over and including priming coat of exterior primer applied @ 0.90 litre/10 sqm. | J14: ='Rennovation Measurement'!K220 -> 559.9 | K14: Sqm | L14: 154.45 | M14: =ROUND(J14*L14,0) -> 86477
A15: 13 | B15: ='AType Cottage'!B27 -> 15.12 | C15: ='AType Cottage'!C27 -> Dismantling doors, windows and clerestory windows (steel or wood) shutter including chowkhats, architrave, holdfasts etc. complete and stacking within 50 metres lead : 15.12.1Of area 3 sq. metres and below | J15: ='Rennovation Measurement'!K225 -> 11 | K15: each | L15: ='AType Cottage'!M31 -> 302.7 | M15: =ROUND(J15*L15,0) -> 3330
A16: 14 | B16: ='AType Cottage'!B6 -> 9.1 | C16: ='AType Cottage'!C6 -> Providing wood work in frames of doors, windows, clerestory windows and other frames, wrought framed and fixed in position with hold fast lugs or with dash fasteners of required dia & length (hold fast lugs or dash fastener shall be paid for separately). 9.1.3 Kiln seasoned and chemically treated hollock wood | J16: ='Rennovation Measurement'!K230 -> 0.36 | K16: ='AType Cottage'!L11 -> cum | L16: ='AType Cottage'!M11 -> 74199.7 | M16: =ROUND(J16*L16,0) -> 26712
A17: 15 | B17: ='AType Cottage'!B12 -> 9.5 | C17: ='AType Cottage'!C12 -> Providing and fixing panelled or panelled and glazed shutters for doors, windows and clerestory windows, fixing with butt hinges of required size with necessary screws, excluding panelling which will be paid for separately, all complete as per direction of Engineer-in-charge. (Note:- Butt hinges and necessary screws shall be paid separately) 9.5.2 Kiln seasoned and chemically treated hollock wood 9.5.2.1 35 mm thick shutters | J17: ='Rennovation Measurement'!K235 -> 16.7 | K17: Sqm | L17: ='AType Cottage'!M17 -> 2511.95 | M17: =ROUND(J17*L17,0) -> 41950
A18: 16 | B18: 10.17 | C18: Providing and fixing M.S. fan clamp type I or II of 16 mm dia M.S. bar, bent to shape with hooked ends in R.C.C. slabs or beams during laying, including painting the exposed portion of loop, all as per standard design complete. | J18: ='Rennovation Measurement'!K238 -> 2 | K18: Each | L18: 185.95 | M18: =ROUND(J18*L18,0) -> 372
A19: 17 | B19: 10.14 | C19: Providing and fixing pressed steel door frames conforming to IS: 4351, manufactured from commercial mild steel sheet of 1.60 mm thickness, including hinges, jamb, lock jamb, bead and if required angle threshold of mild steel angle of section 50x25 mm, or base ties of 1.60 mm, pressed mild steel welded or rigidly fixed together by mechanical means, including M.S. pressed butt hinges 2.5 mm thick with mortar guards, lock strike-plate and shock absorbers as specified and applying a coat of approved steel primer after pre-treatment of the surface as directed by Engineer-in-charge: 10.14.1.1 Fixing with adjustable lugs with split end tail to each jamb | J19: ='Rennovation Measurement'!K241 -> 10.5 | K19: Rm | L19: 444.5 | M19: =ROUND(J19*L19,0) -> 4667
A20: 18 | B20: 9.2 | C20: Providing and fixing ISI marked flush door shutters conforming to IS : 2202 (Part I) decorative type, core of block board construction with frame of 1st class hard wood and well matched teak 3 ply veneering with vertical grains or cross bands and face veneers on both faces of shutters. 9.20.1 35 mm thick including ISI marked Stainless Steel butt hinges with necessary screws. | J20: ='Rennovation Measurement'!K244 -> 4.2 | K20: Sqm | L20: 3086.1 | M20: =ROUND(J20*L20,0) -> 12962
A21: 19 | B21: 9.96 | C21: Providing and fixing aluminium sliding door bolts, ISI marked anodised (anodic coating not less than grade AC 10 as per IS : 1868), transparent or dyed to required colour or shade, with nuts and screws etc. complete 9.96.1 300x16 mm | J21: ='Rennovation Measurement'!K247 -> 4 | K21: Each | L21: 260.3 | M21: =ROUND(J21*L21,0) -> 1041
A22: 20 | B22: 9.97 | C22: Providing and fixing aluminium tower bolts, ISI marked, anodised (anodic coating not less than grade AC 10 as per IS : 1868 ) transparent or dyed to required colour or shade, with necessary screws etc. complete : 9.97.1 300x10 mm | J22: ='Rennovation Measurement'!K250 -> 2 | K22: Each | L22: 117.65 | M22: =ROUND(J22*L22,0) -> 235
A23: 21 | B23: 9.1 | C23: Providing and fixing aluminium handles, ISI marked, anodised (anodic coating not less than grade AC 10 as per IS : 1868) transparent or dyed to required colour or shade, with necessary screws etc. complete 9.100.1 125 mm | J23: 2 | K23: Each | L23: 60.05 | M23: =ROUND(J23*L23,0) -> 120
A24: 22 | B24: 9.119 | C24: Providing and fixing factory made P.V.C. door frame of size 50x47 mm with awall thickness of 5 mm, made out of extruded 5mm rigid PVC foam sheet, mitred at corners and joined with 2 Nos of 150 mm long brackets of 15x15 mm M.S. square tube, the vertical door frame profiles to be reinforced with 19x19 mm M.S. square tube of 19 gauge, EPDM rubber gasket weather seal to be provided through out the frame. The door frame to be fixed to the wall using M.S. screws of 65/100 mm size, complete as per manufacturer’s specification and direction of Engineerin- Charge. | J24: ='Rennovation Measurement'!K258 -> 69.3 | K24: R.M | L24: 408.25 | M24: =ROUND(J24*L24,0) -> 28292
A25: 23 | B25: 9.12 | C25: Providing and fixing factory made panel PVC door shutter consisting of frame made out of M.S. tubes of 19 gauge thickness and size of 19 mm x 19 mm for styles and 15x15 mm for top & bottom rails. M.S. frame shall have a coat of steel primers of approved make and manufacture.M.S. frame covered with 5 mm thick heat moulded PVC 'C' channel of size 30 mm thickness, 70 mm width out of which 50 mm shall be flat and 20 mm shall be tapered in 45 degree angle on both side forming styles and 5 mm thick, 95 mm wide PVC sheet out of which 75mm shall be flat and 20 mm shall be tapered in 45 degree on the inner side to form top and bottom rail and 115 mm wide PVC sheet out of which 75 mm shall be flat and 20 mm shall be tapered on both sides to form lock rail. Top, bottom and lock rails shall be provided both side of the panel. 10 mm (5 mm x 2 ) thick, 20 mm wide cross PVC sheet be provided as gap insert for top rail & bottom rail, paneling of 5 mm thick both side PVC sheet to be fitted in the M.S. frame welded/ sealed to the styles & rails with 7 mm (5 mm+2 mm) thick x 15 mm wide PVC sheet beading on inner side, and joined together with solvent cement adhesive. An additional 5 mm thick PVC strip of 20 mm width is to be stuck on the interior side of the 'C' Channel using PVC solvent adhesive etc. complete as per direction of Engineer-in-charge, manufacturer's specification & drawing. 9.120.1 30 mm thick plain PVC door shutters | J25: ='Rennovation Measurement'!K263 -> 22.05 | K25: Sqm | L25: 2455.1 | M25: =ROUND(J25*L25,0) -> 54135
A26: 24 | B26: 10.16 | C26: Steel work in built up tubular (round, square or rectangular hollow tubes etc.) trusses etc., including cutting, hoisting, fixing in position and applying a priming coat of approved steel primer, including welding and bolted with special shaped washers etc. complete. 10.16.2 Hot finished seamless type tubes (60x60x3.2) | J26: ='Rennovation Measurement'!K267 -> 281 | K26: Kg | L26: 168.95 | M26: =ROUND(J26*L26,0) -> 47475
A27: 25 | B27: 12.50 | C27: Providing and fixing precoated galvanised iron profile sheets (size, shape and pitch of corrugation as approved by Engineer-in-charge) 0.50 mm (+ 0.05 %) total coated thickness with zinc coating 120 grams per sqm as per IS: 277, in 240 mpa steel grade, 5-7 microns epoxy primer on both side of the sheet and polyester top coat 15-18 microns. Sheet should have protective guard film of 25 microns minimum to avoid scratches during transportation and should be supplied in single length upto 12 metre or as desired by Engineer in-charge. The sheet shall be fixed using self drilling /self tapping screws of size (5.5x 55 mm) with EPDM seal, complete upto any pitch in horizontal/ vertical or curved surfaces, excluding the cost of purlins, rafters and trusses and including cutting to size and shape wherever required. | J27: ='Rennovation Measurement'!K271 -> 237.2 | K27: sqm | L27: 671.55 | M27: =ROUND(J27*L27,0) -> 159292 | P27: =SQRT(((R27)^2)+((S27)^2)) -> 3.982 | Q27: =(5.2+0.5+0.5)/2 -> 3.1 | R27: 2.5 | S27: =Q27 -> 3.1
A28: 26 | B28: 12.4.2 | C28: Providing ridges or hips of width 60 cm overall width plain G.S. sheet fixed with polymer coated J or L hooks, bolts and nuts 8 mm dia G.I. limpet and bitumen washers complete. 12.4.2 / 0.63 mm thick with zinc coating not less than 275 gm/m2 | J28: ='Rennovation Measurement'!K274 -> 20.5 | K28: Rm | L28: 750.85 | M28: =ROUND(J28*L28,0) -> 15392
A29: 27 | B29: 12.52 | C29: Providing and fixing tiled false ceiling of specified materials of size 595x595 mm in true horizontal level, suspended on inter locking metal grid of hot dipped galvanized steel sections ( galvanized @ 120 grams/ sqm, both side inclusive) consisting of main "T" runner with suitably spaced joints to get required length and of size 24x38 mm made from 0.30 mm thick (minimum) sheet, spaced at 1200 mm center to center and cross "T" of size 24x25 mm made of 0.30 mm thick (minimum) sheet, 1200 mm long spaced between main "T" at 600 mm center to center to form a grid of 1200x600 mm and secondary cross "T" of length 600 mm and size 24x25 mm made of 0.30 mm thick (minimum) sheet to be interlocked at middle of the 1200x600 mm panel to form grids of 600x600 mm and wall angle of size 24x24x0.3 mm and laying false ceiling tiles of approved texture in the grid including, required cutting/making, opening for services like diffusers, grills, light fittings, fixtures, smoke detectors etc. Main"T" runners to be suspended from ceiling using GI slotted cleats ofsize 27 x 37 x 25 x1.6 mm fixed to ceiling with 12.5 mm dia and 50mm long dash fasteners, 4 mm GI adjustable rods with galvanisedbutterfly level clips of size 85 x 30 x 0.8 mm spaced at 1200 mmcenter to center along main T, bottom exposed width of 24 mm of allT-sections shall be pre-painted with polyester paint, all complete forall heights as per specifications, drawings and as rected byEngineer-in-charge. 12.52.3 12.5 mm thick square edge PVC Laminated Gypsum Tile of size 595x595 mm, made of Gypsum plasterboard, manufactured from natural gypsum as per IS 2095 part I and laminated with white 0.16mm thick fire retardant PVC film on the face side and 12micron metalized polyester on the back side with all edges sealed with | J29: ='Rennovation Measurement'!K282 -> 146.92 | K29: Sqm | L29: 1948.95 | M29: =ROUND(J29*L29,0) -> 286340
A30: 28 | B30: 16.78 | C30: Construction of granular sub-base by providing close graded Material conforming to specifications, mixing in a mechanical mix plant at OMC, carriage of mixed material by tippers to work site, for all leads & lifts, spreading in uniform layers of specified thickness with motor grader on prepared surface and compacting with vibratory power roller to achieve the desired density, complete as per specifications and directions of Engineer-in-Charge. 16.78.1 With material conforming to Grade-I (size range 75 mm to 0.075 mm) having CBR Value-30 | J30: ='Rennovation Measurement'!K285 -> 23.65 | K30: Cum | L30: 2658.1 | M30: =ROUND(J30*L30,0) -> 62864
A31: 29 | B31: 16.68 | C31: Providing and laying 60mm thick factory made cement concrete interlocking paver block of M -30 grade made by block making machine with strong vibratory compaction, of approved size, design & shape, laid in required colour and pattern over and including 50mm thick compacted bed of coarse sand, filling the joints with line sand etc. all complete as per the direction of Engineer-in-charge. | J31: ='Rennovation Measurement'!K288 -> 236.5 | K31: Sqm | L31: 951 | M31: =ROUND(J31*L31,0) -> 224912
A32: 30 | B32: 22.6 | C32: {='Rennovation Measurement'!C289:C289} -> Providing and laying water proofing treatment on roofs of slabs by applying cement slurry mixed with water proofing cement compound consisting of applying: (a) after surface preparation, first layer of slurry of cement @ 0.488 kg/sqm mixed with water proofing cement compound @ 0.253 kg/sqm. (b) laying second layer of Fibre glass cloth when the first layer is still green. Overlaps of joints of fibre cloth should not be less than 10 cm. (c) third layer of 1.5 mm thickness consisting of slurry of cement @ 1.289 kg/sqm mixed with water proofing cement compound @ 0.670 kg/sqm and coarse sand @ 1.289 kg/sqm. This will be allowed to air cure for 4 hours followed by water curing for 48 hours. The entire treatment will be taken upto 30 cm on parapet wall and tucked into groove in parapet all around. (d) fourth and final layer of brick tiling with cement mortar (which will be paid for separately. For the purpose of measurement the entire treated surface will be measured. | J32: ='Rennovation Measurement'!K291 -> 198 | K32: Sqm | L32: 585.5 | M32: =ROUND(J32*L32,0) -> 115929
A33: 31 | B33: {='Rennovation Measurement'!B293:B293} -> 5.22.6.A | C33: {='Rennovation Measurement'!C292:C292 & 'Rennovation Measurement'!C293:C293} -> Steel reinforcement for R.C.C. work including straightening, cutting, bending, placing in position and binding all complete above plinth level.Thermo-Mechanically Treated bars of grade Fe-500D or more. | J33: ='Rennovation Measurement'!K296 -> 65.1 | K33: kg | L33: 89.65 | M33: =ROUND(J33*L33,0) -> 5836
A34: 32 | B34: {='Rennovation Measurement'!B297:B297} -> 5.9.3 | C34: {='Rennovation Measurement'!C297:C297} -> Suspended floors, roofs, landings, balconies and access platform | J34: ='Rennovation Measurement'!K299 -> 7.5 | K34: Sqm | L34: ='Rennovation Measurement'!M299 -> 766.55 | M34: =ROUND(J34*L34,0) -> 5749
A35: 33 | B35: ='Rennovation Measurement'!B300 -> 5.3 | C35: {='Rennovation Measurement'!C300:C300} -> Reinforced cement concrete work in beams, suspended floors, roofs having slope up to 15° landings, balconies, shelves, chajjas, lintels, bands, plain window sills, staircases and spiral stair cases above plinth level up to floor five level, excluding the cost of centering, shuttering, finishing and reinforcement with 1:1.5:3 (1 cement : 1.5 coarse sand(zone-III) derived from natural sources : 3 graded stone aggregate 20 mm nominal size derived from natural sources). | J35: ='Rennovation Measurement'!K302 -> 0.75 | K35: cum | L35: ='Rennovation Measurement'!M302 -> 10719.3 | M35: =ROUND(J35*L35,0) -> 8039
A36: 34 | B36: 6.3 | C36: {='Rennovation Measurement'!C303:C303} -> Brick work with common burnt clay machine moulded perforated bricks of class designation 12.5 conforming to IS: 2222 in superstructure above plinth level up to floor five level in cement mortar 1:6 (1 cement : 6 coarse sand) : 6.3.1 With F.P.S.(non modular) bricks | J36: ='Rennovation Measurement'!K305 -> 3.45 | K36: cum | L36: 8030.6 | M36: =ROUND(J36*L36,0) -> 27706
A37: 35 | B37: ='Rennovation Measurement'!B306 -> 13.14 | C37: {='Rennovation Measurement'!C306:C306} -> 15 mm cement plaster 1:2 (1 cement : 2 stone dust) on the rough side of single or half brick wall.: | J37: ='Rennovation Measurement'!K308 -> 68.97 | K37: cum | L37: 376.65 | M37: =ROUND(J37*L37,0) -> 25978
A38: 36 | B38: ='Rennovation Measurement'!B309 -> 9.48 | C38: {='Rennovation Measurement'!C309:C309} -> Providing and fixing M.S. grills of required pattern in frames of windows etc. with M.S. flats, square or round bars etc. including priming coat with approved steel primer all complete. 9.48.2 Fixed to openings /wooden frames with rawl plugs screws etc. | J38: ='Rennovation Measurement'!K311 -> 975 | K38: cum | L38: 197.7 | M38: =ROUND(J38*L38,0) -> 192758
A39: TOTAL= | M39: =ROUND(SUM(M3:M35),0) -> 2357162
A40: SAY= | M40: =M39 -> 2357162
C41: =CU47 -> (Rupees twenty three lakh fifty seven thousand one hundred sixty two) only.
A47: =M40 -> 2357162 | B47: COPY CELLS=> | C47: 1 | D47: one | E47: 2 | F47: two | G47: 3 | H47: three | I47: 4 | J47: four | K47: 5 | L47: five | M47: 6 | N47: six | O47: 7 | P47: seven | Q47: 8 | R47: eight | S47: 9 | T47: nine | U47: 10 | V47: ten | W47: 11 | X47: eleven | Y47: 12 | Z47: twelve | AA47: 13 | AB47: thirteen | AC47: 14 | AD47: fourteen | AE47: 15 | AF47: fifteen | AG47: 16 | AH47: sixteen | AI47: 17 | AJ47: seventeen | AK47: 18 | AL47: eighteen | AM47: 19 | AN47: nineteen | AO47: <=COPY CELLS | AP47: WORDS-> | AQ47: CRORE | AR47: =IF(AX47="","",IF(AX47>=90,"ninety "&IF((AX47-ROUNDDOWN(AX47,-1))=C47,D47,"")&IF((AX47-ROUNDDOWN(AX47,-1))=E47,F47,"")&IF((AX47-ROUNDDOWN(AX47,-1))=G47,H47,"")&IF((AX47-ROUNDDOWN(AX47,-1))=I47,J47,"")&IF((AX47-ROUNDDOWN(AX47,-1))=K47,L47,"")&IF((AX47-ROUNDDOWN(AX47,-1))=M47,N47,"")&IF((AX47-ROUNDDOWN(AX47,-1))=O47,P47,"")&IF((AX47-ROUNDDOWN(AX47,-1))=Q47,R47,"")&IF((AX47-ROUNDDOWN(AX47,-1))=S47,T47,""),IF(AX47>=80,"eighty "&IF((AX47-ROUNDDOWN(AX47,-1))=1,D47,"")&IF((AX47-ROUNDDOWN(AX47,-1))=2,F47,"")&IF((AX47-ROUNDDOWN(AX47,-1))=G47,H47,"")&IF((AX47-ROUNDDOWN(AX47,-1))=I47,J47,"")&IF((AX47-ROUNDDOWN(AX47,-1))=K47,L47,"")&IF((AX47-ROUNDDOWN(AX47,-1))=M47,N47,"")&IF((AX47-ROUNDDOWN(AX47,-1))=O47,P47,"")&IF((AX47-ROUNDDOWN(AX47,-1))=Q47,R47,"")&IF((AX47-ROUNDDOWN(AX47,-1))=S47,T47,""),""))) | AS47: =IF(AX47="","",IF(AX47>79,"",IF(AX47>=70,"seventy "&IF((AX47-ROUNDDOWN(AX47,-1))=C47,D47,"")&IF((AX47-ROUNDDOWN(AX47,-1))=E47,F47,"")&IF((AX47-ROUNDDOWN(AX47,-1))=G47,H47,"")&IF((AX47-ROUNDDOWN(AX47,-1))=I47,J47,"")&IF((AX47-ROUNDDOWN(AX47,-1))=K47,L47,"")&IF((AX47-ROUNDDOWN(AX47,-1))=M47,N47,"")&IF((AX47-ROUNDDOWN(AX47,-1))=O47,P47,"")&IF((AX47-ROUNDDOWN(AX47,-1))=Q47,R47,"")&IF((AX47-ROUNDDOWN(AX47,-1))=S47,T47,""),IF(AX47>=60,"sixty "&IF((AX47-ROUNDDOWN(AX47,-1))=1,D47,"")&IF((AX47-ROUNDDOWN(AX47,-1))=2,F47,"")&IF((AX47-ROUNDDOWN(AX47,-1))=G47,H47,"")&IF((AX47-ROUNDDOWN(AX47,-1))=I47,J47,"")&IF((AX47-ROUNDDOWN(AX47,-1))=K47,L47,"")&IF((AX47-ROUNDDOWN(AX47,-1))=M47,N47,"")&IF((AX47-ROUNDDOWN(AX47,-1))=O47,P47,"")&IF((AX47-ROUNDDOWN(AX47,-1))=Q47,R47,"")&IF((AX47-ROUNDDOWN(AX47,-1))=S47,T47,""),"")))) | AT47: =IF(AX47="","",IF(AX47>59,"",IF(AX47>=50,"fifty "&IF((AX47-ROUNDDOWN(AX47,-1))=C47,D47,"")&IF((AX47-ROUNDDOWN(AX47,-1))=E47,F47,"")&IF((AX47-ROUNDDOWN(AX47,-1))=G47,H47,"")&IF((AX47-ROUNDDOWN(AX47,-1))=I47,J47,"")&IF((AX47-ROUNDDOWN(AX47,-1))=K47,L47,"")&IF((AX47-ROUNDDOWN(AX47,-1))=M47,N47,"")&IF((AX47-ROUNDDOWN(AX47,-1))=O47,P47,"")&IF((AX47-ROUNDDOWN(AX47,-1))=Q47,R47,"")&IF((AX47-ROUNDDOWN(AX47,-1))=S47,T47,""),IF(AX47>=40,"forty "&IF((AX47-ROUNDDOWN(AX47,-1))=1,D47,"")&IF((AX47-ROUNDDOWN(AX47,-1))=2,F47,"")&IF((AX47-ROUNDDOWN(AX47,-1))=G47,H47,"")&IF((AX47-ROUNDDOWN(AX47,-1))=I47,J47,"")&IF((AX47-ROUNDDOWN(AX47,-1))=K47,L47,"")&IF((AX47-ROUNDDOWN(AX47,-1))=M47,N47,"")&IF((AX47-ROUNDDOWN(AX47,-1))=O47,P47,"")&IF((AX47-ROUNDDOWN(AX47,-1))=Q47,R47,"")&IF((AX47-ROUNDDOWN(AX47,-1))=S47,T47,""),"")))) | AU47: =IF(AX47="","",IF(AX47>39,"",IF(AX47>=30,"thirty "&IF((AX47-ROUNDDOWN(AX47,-1))=C47,D47,"")&IF((AX47-ROUNDDOWN(AX47,-1))=E47,F47,"")&IF((AX47-ROUNDDOWN(AX47,-1))=G47,H47,"")&IF((AX47-ROUNDDOWN(AX47,-1))=I47,J47,"")&IF((AX47-ROUNDDOWN(AX47,-1))=K47,L47,"")&IF((AX47-ROUNDDOWN(AX47,-1))=M47,N47,"")&IF((AX47-ROUNDDOWN(AX47,-1))=O47,P47,"")&IF((AX47-ROUNDDOWN(AX47,-1))=Q47,R47,"")&IF((AX47-ROUNDDOWN(AX47,-1))=S47,T47,""),IF(AX47>=20,"twenty "&IF((AX47-ROUNDDOWN(AX47,-1))=1,D47,"")&IF((AX47-ROUNDDOWN(AX47,-1))=2,F47,"")&IF((AX47-ROUNDDOWN(AX47,-1))=G47,H47,"")&IF((AX47-ROUNDDOWN(AX47,-1))=I47,J47,"")&IF((AX47-ROUNDDOWN(AX47,-1))=K47,L47,"")&IF((AX47-ROUNDDOWN(AX47,-1))=M47,N47,"")&IF((AX47-ROUNDDOWN(AX47,-1))=O47,P47,"")&IF((AX47-ROUNDDOWN(AX47,-1))=Q47,R47,"")&IF((AX47-ROUNDDOWN(AX47,-1))=S47,T47,""),"")))) | AV47: =IF(AX47="","",IF(AX47=C47,D47,"")&IF(AX47=E47,F47,"")&IF(AX47=G47,H47,"")&IF(AX47=I47,J47,"")&IF(AX47=K47,L47,"")&IF(AX47=M47,N47,"")&IF(AX47=O47,P47,"")&IF(AX47=Q47,R47,"")&IF(AX47=S47,T47,"")&IF(AX47=U47,V47,"")&IF(AX47=W47,X47,"")&IF(AX47=Y47,Z47,"")&IF(AX47=AA47,AB47,"")&IF(AX47=AC47,AD47,"")&IF(AX47=AE47,AF47,"")&IF(AX47=AG47,AH47,"")&IF(AX47=AI47,AJ47,"")&IF(AX47=AK47,AL47,"")&IF(AX47=AM47,AN47,"")) | AX47: =IF(A47>=10000000,ROUNDDOWN(A47,-7)/10000000,"") | AY47: =IF(AR47="","",AR47)&IF(AS47="","",AS47)&IF(AT47="","",AT47)&IF(AU47="","",AU47)&IF(AV47="","",AV47) | AZ47: LAKH | BA47: =IF(BG47="","",IF(BG47>=90,"ninety "&IF((BG47-ROUNDDOWN(BG47,-1))=C47,D47,"")&IF((BG47-ROUNDDOWN(BG47,-1))=E47,F47,"")&IF((BG47-ROUNDDOWN(BG47,-1))=G47,H47,"")&IF((BG47-ROUNDDOWN(BG47,-1))=I47,J47,"")&IF((BG47-ROUNDDOWN(BG47,-1))=K47,L47,"")&IF((BG47-ROUNDDOWN(BG47,-1))=M47,N47,"")&IF((BG47-ROUNDDOWN(BG47,-1))=O47,P47,"")&IF((BG47-ROUNDDOWN(BG47,-1))=Q47,R47,"")&IF((BG47-ROUNDDOWN(BG47,-1))=S47,T47,""),IF(BG47>=80,"eighty "&IF((BG47-ROUNDDOWN(BG47,-1))=1,D47,"")&IF((BG47-ROUNDDOWN(BG47,-1))=2,F47,"")&IF((BG47-ROUNDDOWN(BG47,-1))=G47,H47,"")&IF((BG47-ROUNDDOWN(BG47,-1))=I47,J47,"")&IF((BG47-ROUNDDOWN(BG47,-1))=K47,L47,"")&IF((BG47-ROUNDDOWN(BG47,-1))=M47,N47,"")&IF((BG47-ROUNDDOWN(BG47,-1))=O47,P47,"")&IF((BG47-ROUNDDOWN(BG47,-1))=Q47,R47,"")&IF((BG47-ROUNDDOWN(BG47,-1))=S47,T47,""),""))) | BB47: =IF(BG47="","",IF(BG47>79,"",IF(BG47>=70,"seventy "&IF((BG47-ROUNDDOWN(BG47,-1))=C47,D47,"")&IF((BG47-ROUNDDOWN(BG47,-1))=E47,F47,"")&IF((BG47-ROUNDDOWN(BG47,-1))=G47,H47,"")&IF((BG47-ROUNDDOWN(BG47,-1))=I47,J47,"")&IF((BG47-ROUNDDOWN(BG47,-1))=K47,L47,"")&IF((BG47-ROUNDDOWN(BG47,-1))=M47,N47,"")&IF((BG47-ROUNDDOWN(BG47,-1))=O47,P47,"")&IF((BG47-ROUNDDOWN(BG47,-1))=Q47,R47,"")&IF((BG47-ROUNDDOWN(BG47,-1))=S47,T47,""),IF(BG47>=60,"sixty "&IF((BG47-ROUNDDOWN(BG47,-1))=1,D47,"")&IF((BG47-ROUNDDOWN(BG47,-1))=2,F47,"")&IF((BG47-ROUNDDOWN(BG47,-1))=G47,H47,"")&IF((BG47-ROUNDDOWN(BG47,-1))=I47,J47,"")&IF((BG47-ROUNDDOWN(BG47,-1))=K47,L47,"")&IF((BG47-ROUNDDOWN(BG47,-1))=M47,N47,"")&IF((BG47-ROUNDDOWN(BG47,-1))=O47,P47,"")&IF((BG47-ROUNDDOWN(BG47,-1))=Q47,R47,"")&IF((BG47-ROUNDDOWN(BG47,-1))=S47,T47,""),"")))) | BC47: =IF(BG47="","",IF(BG47>59,"",IF(BG47>=50,"fifty "&IF((BG47-ROUNDDOWN(BG47,-1))=C47,D47,"")&IF((BG47-ROUNDDOWN(BG47,-1))=E47,F47,"")&IF((BG47-ROUNDDOWN(BG47,-1))=G47,H47,"")&IF((BG47-ROUNDDOWN(BG47,-1))=I47,J47,"")&IF((BG47-ROUNDDOWN(BG47,-1))=K47,L47,"")&IF((BG47-ROUNDDOWN(BG47,-1))=M47,N47,"")&IF((BG47-ROUNDDOWN(BG47,-1))=O47,P47,"")&IF((BG47-ROUNDDOWN(BG47,-1))=Q47,R47,"")&IF((BG47-ROUNDDOWN(BG47,-1))=S47,T47,""),IF(BG47>=40,"forty "&IF((BG47-ROUNDDOWN(BG47,-1))=1,D47,"")&IF((BG47-ROUNDDOWN(BG47,-1))=2,F47,"")&IF((BG47-ROUNDDOWN(BG47,-1))=G47,H47,"")&IF((BG47-ROUNDDOWN(BG47,-1))=I47,J47,"")&IF((BG47-ROUNDDOWN(BG47,-1))=K47,L47,"")&IF((BG47-ROUNDDOWN(BG47,-1))=M47,N47,"")&IF((BG47-ROUNDDOWN(BG47,-1))=O47,P47,"")&IF((BG47-ROUNDDOWN(BG47,-1))=Q47,R47,"")&IF((BG47-ROUNDDOWN(BG47,-1))=S47,T47,""),"")))) | BD47: =IF(BG47="","",IF(BG47>39,"",IF(BG47>=30,"thirty "&IF((BG47-ROUNDDOWN(BG47,-1))=C47,D47,"")&IF((BG47-ROUNDDOWN(BG47,-1))=E47,F47,"")&IF((BG47-ROUNDDOWN(BG47,-1))=G47,H47,"")&IF((BG47-ROUNDDOWN(BG47,-1))=I47,J47,"")&IF((BG47-ROUNDDOWN(BG47,-1))=K47,L47,"")&IF((BG47-ROUNDDOWN(BG47,-1))=M47,N47,"")&IF((BG47-ROUNDDOWN(BG47,-1))=O47,P47,"")&IF((BG47-ROUNDDOWN(BG47,-1))=Q47,R47,"")&IF((BG47-ROUNDDOWN(BG47,-1))=S47,T47,""),IF(BG47>=20,"twenty "&IF((BG47-ROUNDDOWN(BG47,-1))=1,D47,"")&IF((BG47-ROUNDDOWN(BG47,-1))=2,F47,"")&IF((BG47-ROUNDDOWN(BG47,-1))=G47,H47,"")&IF((BG47-ROUNDDOWN(BG47,-1))=I47,J47,"")&IF((BG47-ROUNDDOWN(BG47,-1))=K47,L47,"")&IF((BG47-ROUNDDOWN(BG47,-1))=M47,N47,"")&IF((BG47-ROUNDDOWN(BG47,-1))=O47,P47,"")&IF((BG47-ROUNDDOWN(BG47,-1))=Q47,R47,"")&IF((BG47-ROUNDDOWN(BG47,-1))=S47,T47,""),"")))) -> twenty three | BE47: =IF(BG47="","",IF(BG47=C47,D47,"")&IF(BG47=E47,F47,"")&IF(BG47=G47,H47,"")&IF(BG47=I47,J47,"")&IF(BG47=K47,L47,"")&IF(BG47=M47,N47,"")&IF(BG47=O47,P47,"")&IF(BG47=Q47,R47,"")&IF(BG47=S47,T47,"")&IF(BG47=U47,V47,"")&IF(BG47=W47,X47,"")&IF(BG47=Y47,Z47,"")&IF(BG47=AA47,AB47,"")&IF(BG47=AC47,AD47,"")&IF(BG47=AE47,AF47,"")&IF(BG47=AG47,AH47,"")&IF(BG47=AI47,AJ47,"")&IF(BG47=AK47,AL47,"")&IF(BG47=AM47,AN47,"")) | BG47: =IF(A47>=100000,ROUNDDOWN((ROUND(A47,-4)-ROUNDDOWN(A47,-7))/100000,0),"") -> 23 | BH47: =IF(BA47="","",BA47)&IF(BB47="","",BB47)&IF(BC47="","",BC47)&IF(BD47="","",BD47)&IF(BE47="","",BE47) -> twenty three | BI47: THOUSAND | BJ47: =IF(BP47="","",IF(BP47>=90,"ninety "&IF((BP47-ROUNDDOWN(BP47,-1))=1,D47,"")&IF((BP47-ROUNDDOWN(BP47,-1))=2,F47,"")&IF((BP47-ROUNDDOWN(BP47,-1))=G47,H47,"")&IF((BP47-ROUNDDOWN(BP47,-1))=I47,J47,"")&IF((BP47-ROUNDDOWN(BP47,-1))=K47,L47,"")&IF((BP47-ROUNDDOWN(BP47,-1))=M47,N47,"")&IF((BP47-ROUNDDOWN(BP47,-1))=O47,P47,"")&IF((BP47-ROUNDDOWN(BP47,-1))=Q47,R47,"")&IF((BP47-ROUNDDOWN(BP47,-1))=S47,T47,""),IF(BP47>=80,"eighty "&IF((BP47-ROUNDDOWN(BP47,-1))=1,D47,"")&IF((BP47-ROUNDDOWN(BP47,-1))=2,F47,"")&IF((BP47-ROUNDDOWN(BP47,-1))=G47,H47,"")&IF((BP47-ROUNDDOWN(BP47,-1))=I47,J47,"")&IF((BP47-ROUNDDOWN(BP47,-1))=K47,L47,"")&IF((BP47-ROUNDDOWN(BP47,-1))=M47,N47,"")&IF((BP47-ROUNDDOWN(BP47,-1))=O47,P47,"")&IF((BP47-ROUNDDOWN(BP47,-1))=Q47,R47,"")&IF((BP47-ROUNDDOWN(BP47,-1))=S47,T47,""),""))) | BK47: =IF(BP47="","",IF(BP47>79,"",IF(BP47>=70,"seventy "&IF((BP47-ROUNDDOWN(BP47,-1))=1,D47,"")&IF((BP47-ROUNDDOWN(BP47,-1))=2,F47,"")&IF((BP47-ROUNDDOWN(BP47,-1))=G47,H47,"")&IF((BP47-ROUNDDOWN(BP47,-1))=I47,J47,"")&IF((BP47-ROUNDDOWN(BP47,-1))=K47,L47,"")&IF((BP47-ROUNDDOWN(BP47,-1))=M47,N47,"")&IF((BP47-ROUNDDOWN(BP47,-1))=O47,P47,"")&IF((BP47-ROUNDDOWN(BP47,-1))=Q47,R47,"")&IF((BP47-ROUNDDOWN(BP47,-1))=S47,T47,""),IF(BP47>=60,"sixty "&IF((BP47-ROUNDDOWN(BP47,-1))=1,D47,"")&IF((BP47-ROUNDDOWN(BP47,-1))=2,F47,"")&IF((BP47-ROUNDDOWN(BP47,-1))=G47,H47,"")&IF((BP47-ROUNDDOWN(BP47,-1))=I47,J47,"")&IF((BP47-ROUNDDOWN(BP47,-1))=K47,L47,"")&IF((BP47-ROUNDDOWN(BP47,-1))=M47,N47,"")&IF((BP47-ROUNDDOWN(BP47,-1))=O47,P47,"")&IF((BP47-ROUNDDOWN(BP47,-1))=Q47,R47,"")&IF((BP47-ROUNDDOWN(BP47,-1))=S47,T47,""),"")))) | BL47: =IF(BP47="","",IF(BP47>59,"",IF(BP47>=50,"fifty "&IF((BP47-ROUNDDOWN(BP47,-1))=1,D47,"")&IF((BP47-ROUNDDOWN(BP47,-1))=2,F47,"")&IF((BP47-ROUNDDOWN(BP47,-1))=G47,H47,"")&IF((BP47-ROUNDDOWN(BP47,-1))=I47,J47,"")&IF((BP47-ROUNDDOWN(BP47,-1))=K47,L47,"")&IF((BP47-ROUNDDOWN(BP47,-1))=M47,N47,"")&IF((BP47-ROUNDDOWN(BP47,-1))=O47,P47,"")&IF((BP47-ROUNDDOWN(BP47,-1))=Q47,R47,"")&IF((BP47-ROUNDDOWN(BP47,-1))=S47,T47,""),IF(BP47>=40,"forty "&IF((BP47-ROUNDDOWN(BP47,-1))=1,D47,"")&IF((BP47-ROUNDDOWN(BP47,-1))=2,F47,"")&IF((BP47-ROUNDDOWN(BP47,-1))=G47,H47,"")&IF((BP47-ROUNDDOWN(BP47,-1))=I47,J47,"")&IF((BP47-ROUNDDOWN(BP47,-1))=K47,L47,"")&IF((BP47-ROUNDDOWN(BP47,-1))=M47,N47,"")&IF((BP47-ROUNDDOWN(BP47,-1))=O47,P47,"")&IF((BP47-ROUNDDOWN(BP47,-1))=Q47,R47,"")&IF((BP47-ROUNDDOWN(BP47,-1))=S47,T47,""),"")))) -> fifty seven | BM47: =IF(BP47="","",IF(BP47>39,"",IF(BP47>=30,"thirty "&IF((BP47-ROUNDDOWN(BP47,-1))=1,D47,"")&IF((BP47-ROUNDDOWN(BP47,-1))=2,F47,"")&IF((BP47-ROUNDDOWN(BP47,-1))=G47,H47,"")&IF((BP47-ROUNDDOWN(BP47,-1))=I47,J47,"")&IF((BP47-ROUNDDOWN(BP47,-1))=K47,L47,"")&IF((BP47-ROUNDDOWN(BP47,-1))=M47,N47,"")&IF((BP47-ROUNDDOWN(BP47,-1))=O47,P47,"")&IF((BP47-ROUNDDOWN(BP47,-1))=Q47,R47,"")&IF((BP47-ROUNDDOWN(BP47,-1))=S47,T47,""),IF(BP47>=20,"twenty "&IF((BP47-ROUNDDOWN(BP47,-1))=1,D47,"")&IF((BP47-ROUNDDOWN(BP47,-1))=2,F47,"")&IF((BP47-ROUNDDOWN(BP47,-1))=G47,H47,"")&IF((BP47-ROUNDDOWN(BP47,-1))=I47,J47,"")&IF((BP47-ROUNDDOWN(BP47,-1))=K47,L47,"")&IF((BP47-ROUNDDOWN(BP47,-1))=M47,N47,"")&IF((BP47-ROUNDDOWN(BP47,-1))=O47,P47,"")&IF((BP47-ROUNDDOWN(BP47,-1))=Q47,R47,"")&IF((BP47-ROUNDDOWN(BP47,-1))=S47,T47,""),"")))) | BN47: =IF(BP47="","",IF(BP47=C47,D47,"")&IF(BP47=E47,F47,"")&IF(BP47=G47,H47,"")&IF(BP47=I47,J47,"")&IF(BP47=K47,L47,"")&IF(BP47=M47,N47,"")&IF(BP47=O47,P47,"")&IF(BP47=Q47,R47,"")&IF(BP47=S47,T47,"")&IF(BP47=U47,V47,"")&IF(BP47=W47,X47,"")&IF(BP47=Y47,Z47,"")&IF(BP47=AA47,AB47,"")&IF(BP47=AC47,AD47,"")&IF(BP47=AE47,AF47,"")&IF(BP47=AG47,AH47,"")&IF(BP47=AI47,AJ47,"")&IF(BP47=AK47,AL47,"")&IF(BP47=AM47,AN47,"")) | BP47: =IF(A47>=1000,ROUNDDOWN((A47-ROUNDDOWN(A47,-5))/1000,0),"") -> 57 | BQ47: =IF(BJ47="","",BJ47)&IF(BK47="","",BK47)&IF(BL47="","",BL47)&IF(BM47="","",BM47)&IF(BN47="","",BN47) -> fifty seven | BR47: HUNDRED | BS47: =IF(BY47="","",IF(BY47>=90,"ninety "&IF((BY47-ROUNDDOWN(BY47,-1))=1,D47,"")&IF((BY47-ROUNDDOWN(BY47,-1))=2,F47,"")&IF((BY47-ROUNDDOWN(BY47,-1))=G47,H47,"")&IF((BY47-ROUNDDOWN(BY47,-1))=I47,J47,"")&IF((BY47-ROUNDDOWN(BY47,-1))=K47,L47,"")&IF((BY47-ROUNDDOWN(BY47,-1))=M47,N47,"")&IF((BY47-ROUNDDOWN(BY47,-1))=O47,P47,"")&IF((BY47-ROUNDDOWN(BY47,-1))=Q47,R47,"")&IF((BY47-ROUNDDOWN(BY47,-1))=S47,T47,""),IF(BY47>=80,"eighty "&IF((BY47-ROUNDDOWN(BY47,-1))=1,D47,"")&IF((BY47-ROUNDDOWN(BY47,-1))=2,F47,"")&IF((BY47-ROUNDDOWN(BY47,-1))=G47,H47,"")&IF((BY47-ROUNDDOWN(BY47,-1))=I47,J47,"")&IF((BY47-ROUNDDOWN(BY47,-1))=K47,L47,"")&IF((BY47-ROUNDDOWN(BY47,-1))=M47,N47,"")&IF((BY47-ROUNDDOWN(BY47,-1))=O47,P47,"")&IF((BY47-ROUNDDOWN(BY47,-1))=Q47,R47,"")&IF((BY47-ROUNDDOWN(BY47,-1))=S47,T47,""),""))) | BT47: =IF(BY47="","",IF(BY47>79,"",IF(BY47>=70,"seventy "&IF((BY47-ROUNDDOWN(BY47,-1))=1,D47,"")&IF((BY47-ROUNDDOWN(BY47,-1))=2,F47,"")&IF((BY47-ROUNDDOWN(BY47,-1))=G47,H47,"")&IF((BY47-ROUNDDOWN(BY47,-1))=I47,J47,"")&IF((BY47-ROUNDDOWN(BY47,-1))=K47,L47,"")&IF((BY47-ROUNDDOWN(BY47,-1))=M47,N47,"")&IF((BY47-ROUNDDOWN(BY47,-1))=O47,P47,"")&IF((BY47-ROUNDDOWN(BY47,-1))=Q47,R47,"")&IF((BY47-ROUNDDOWN(BY47,-1))=S47,T47,""),IF(BY47>=60,"sixty "&IF((BY47-ROUNDDOWN(BY47,-1))=1,D47,"")&IF((BY47-ROUNDDOWN(BY47,-1))=2,F47,"")&IF((BY47-ROUNDDOWN(BY47,-1))=G47,H47,"")&IF((BY47-ROUNDDOWN(BY47,-1))=I47,J47,"")&IF((BY47-ROUNDDOWN(BY47,-1))=K47,L47,"")&IF((BY47-ROUNDDOWN(BY47,-1))=M47,N47,"")&IF((BY47-ROUNDDOWN(BY47,-1))=O47,P47,"")&IF((BY47-ROUNDDOWN(BY47,-1))=Q47,R47,"")&IF((BY47-ROUNDDOWN(BY47,-1))=S47,T47,""),"")))) | BU47: =IF(BY47="","",IF(BY47>59,"",IF(BY47>=50,"fifty "&IF((BY47-ROUNDDOWN(BY47,-1))=1,D47,"")&IF((BY47-ROUNDDOWN(BY47,-1))=2,F47,"")&IF((BY47-ROUNDDOWN(BY47,-1))=G47,H47,"")&IF((BY47-ROUNDDOWN(BY47,-1))=I47,J47,"")&IF((BY47-ROUNDDOWN(BY47,-1))=K47,L47,"")&IF((BY47-ROUNDDOWN(BY47,-1))=M47,N47,"")&IF((BY47-ROUNDDOWN(BY47,-1))=O47,P47,"")&IF((BY47-ROUNDDOWN(BY47,-1))=Q47,R47,"")&IF((BY47-ROUNDDOWN(BY47,-1))=S47,T47,""),IF(BY47>=40,"forty "&IF((BY47-ROUNDDOWN(BY47,-1))=1,D47,"")&IF((BY47-ROUNDDOWN(BY47,-1))=2,F47,"")&IF((BY47-ROUNDDOWN(BY47,-1))=G47,H47,"")&IF((BY47-ROUNDDOWN(BY47,-1))=I47,J47,"")&IF((BY47-ROUNDDOWN(BY47,-1))=K47,L47,"")&IF((BY47-ROUNDDOWN(BY47,-1))=M47,N47,"")&IF((BY47-ROUNDDOWN(BY47,-1))=O47,P47,"")&IF((BY47-ROUNDDOWN(BY47,-1))=Q47,R47,"")&IF((BY47-ROUNDDOWN(BY47,-1))=S47,T47,""),"")))) | BV47: =IF(BY47="","",IF(BY47>39,"",IF(BY47>=30,"thirty "&IF((BY47-ROUNDDOWN(BY47,-1))=1,D47,"")&IF((BY47-ROUNDDOWN(BY47,-1))=2,F47,"")&IF((BY47-ROUNDDOWN(BY47,-1))=G47,H47,"")&IF((BY47-ROUNDDOWN(BY47,-1))=I47,J47,"")&IF((BY47-ROUNDDOWN(BY47,-1))=K47,L47,"")&IF((BY47-ROUNDDOWN(BY47,-1))=M47,N47,"")&IF((BY47-ROUNDDOWN(BY47,-1))=O47,P47,"")&IF((BY47-ROUNDDOWN(BY47,-1))=Q47,R47,"")&IF((BY47-ROUNDDOWN(BY47,-1))=S47,T47,""),IF(BY47>=20,"twenty "&IF((BY47-ROUNDDOWN(BY47,-1))=1,D47,"")&IF((BY47-ROUNDDOWN(BY47,-1))=2,F47,"")&IF((BY47-ROUNDDOWN(BY47,-1))=G47,H47,"")&IF((BY47-ROUNDDOWN(BY47,-1))=I47,J47,"")&IF((BY47-ROUNDDOWN(BY47,-1))=K47,L47,"")&IF((BY47-ROUNDDOWN(BY47,-1))=M47,N47,"")&IF((BY47-ROUNDDOWN(BY47,-1))=O47,P47,"")&IF((BY47-ROUNDDOWN(BY47,-1))=Q47,R47,"")&IF((BY47-ROUNDDOWN(BY47,-1))=S47,T47,""),"")))) | BW47: =IF(BY47="","",IF(BY47=C47,D47,"")&IF(BY47=E47,F47,"")&IF(BY47=G47,H47,"")&IF(BY47=I47,J47,"")&IF(BY47=K47,L47,"")&IF(BY47=M47,N47,"")&IF(BY47=O47,P47,"")&IF(BY47=Q47,R47,"")&IF(BY47=S47,T47,"")&IF(BY47=U47,V47,"")&IF(BY47=W47,X47,"")&IF(BY47=Y47,Z47,"")&IF(BY47=AA47,AB47,"")&IF(BY47=AC47,AD47,"")&IF(BY47=AE47,AF47,"")&IF(BY47=AG47,AH47,"")&IF(BY47=AI47,AJ47,"")&IF(BY47=AK47,AL47,"")&IF(BY47=AM47,AN47,"")) -> one | BY47: =IF(A47>=100,ROUNDDOWN((A47-ROUNDDOWN(A47,-3))/100,0),"") -> 1 | BZ47: =IF(BS47="","",BS47)&IF(BT47="","",BT47)&IF(BU47="","",BU47)&IF(BV47="","",BV47)&IF(BW47="","",BW47) -> one | CA47: TENS | CB47: =IF(CH47="","",IF(CH47>=90,"ninety "&IF((CH47-ROUNDDOWN(CH47,-1))=1,D47,"")&IF((CH47-ROUNDDOWN(CH47,-1))=2,F47,"")&IF((CH47-ROUNDDOWN(CH47,-1))=G47,H47,"")&IF((CH47-ROUNDDOWN(CH47,-1))=I47,J47,"")&IF((CH47-ROUNDDOWN(CH47,-1))=K47,L47,"")&IF((CH47-ROUNDDOWN(CH47,-1))=M47,N47,"")&IF((CH47-ROUNDDOWN(CH47,-1))=O47,P47,"")&IF((CH47-ROUNDDOWN(CH47,-1))=Q47,R47,"")&IF((CH47-ROUNDDOWN(CH47,-1))=S47,T47,""),IF(CH47>=80,"eighty "&IF((CH47-ROUNDDOWN(CH47,-1))=1,D47,"")&IF((CH47-ROUNDDOWN(CH47,-1))=2,F47,"")&IF((CH47-ROUNDDOWN(CH47,-1))=G47,H47,"")&IF((CH47-ROUNDDOWN(CH47,-1))=I47,J47,"")&IF((CH47-ROUNDDOWN(CH47,-1))=K47,L47,"")&IF((CH47-ROUNDDOWN(CH47,-1))=M47,N47,"")&IF((CH47-ROUNDDOWN(CH47,-1))=O47,P47,"")&IF((CH47-ROUNDDOWN(CH47,-1))=Q47,R47,"")&IF((CH47-ROUNDDOWN(CH47,-1))=S47,T47,""),""))) | CC47: =IF(CH47="","",IF(CH47>79,"",IF(CH47>=70,"seventy "&IF((CH47-ROUNDDOWN(CH47,-1))=1,D47,"")&IF((CH47-ROUNDDOWN(CH47,-1))=2,F47,"")&IF((CH47-ROUNDDOWN(CH47,-1))=G47,H47,"")&IF((CH47-ROUNDDOWN(CH47,-1))=I47,J47,"")&IF((CH47-ROUNDDOWN(CH47,-1))=K47,L47,"")&IF((CH47-ROUNDDOWN(CH47,-1))=M47,N47,"")&IF((CH47-ROUNDDOWN(CH47,-1))=O47,P47,"")&IF((CH47-ROUNDDOWN(CH47,-1))=Q47,R47,"")&IF((CH47-ROUNDDOWN(CH47,-1))=S47,T47,""),IF(CH47>=60,"sixty "&IF((CH47-ROUNDDOWN(CH47,-1))=1,D47,"")&IF((CH47-ROUNDDOWN(CH47,-1))=2,F47,"")&IF((CH47-ROUNDDOWN(CH47,-1))=G47,H47,"")&IF((CH47-ROUNDDOWN(CH47,-1))=I47,J47,"")&IF((CH47-ROUNDDOWN(CH47,-1))=K47,L47,"")&IF((CH47-ROUNDDOWN(CH47,-1))=M47,N47,"")&IF((CH47-ROUNDDOWN(CH47,-1))=O47,P47,"")&IF((CH47-ROUNDDOWN(CH47,-1))=Q47,R47,"")&IF((CH47-ROUNDDOWN(CH47,-1))=S47,T47,""),"")))) -> sixty two | CD47: =IF(CH47="","",IF(CH47>59,"",IF(CH47>=50,"fifty "&IF((CH47-ROUNDDOWN(CH47,-1))=1,D47,"")&IF((CH47-ROUNDDOWN(CH47,-1))=2,F47,"")&IF((CH47-ROUNDDOWN(CH47,-1))=G47,H47,"")&IF((CH47-ROUNDDOWN(CH47,-1))=I47,J47,"")&IF((CH47-ROUNDDOWN(CH47,-1))=K47,L47,"")&IF((CH47-ROUNDDOWN(CH47,-1))=M47,N47,"")&IF((CH47-ROUNDDOWN(CH47,-1))=O47,P47,"")&IF((CH47-ROUNDDOWN(CH47,-1))=Q47,R47,"")&IF((CH47-ROUNDDOWN(CH47,-1))=S47,T47,""),IF(CH47>=40,"forty "&IF((CH47-ROUNDDOWN(CH47,-1))=1,D47,"")&IF((CH47-ROUNDDOWN(CH47,-1))=2,F47,"")&IF((CH47-ROUNDDOWN(CH47,-1))=G47,H47,"")&IF((CH47-ROUNDDOWN(CH47,-1))=I47,J47,"")&IF((CH47-ROUNDDOWN(CH47,-1))=K47,L47,"")&IF((CH47-ROUNDDOWN(CH47,-1))=M47,N47,"")&IF((CH47-ROUNDDOWN(CH47,-1))=O47,P47,"")&IF((CH47-ROUNDDOWN(CH47,-1))=Q47,R47,"")&IF((CH47-ROUNDDOWN(CH47,-1))=S47,T47,""),"")))) | CE47: =IF(CH47="","",IF(CH47>39,"",IF(CH47>=30,"thirty "&IF((CH47-ROUNDDOWN(CH47,-1))=1,D47,"")&IF((CH47-ROUNDDOWN(CH47,-1))=2,F47,"")&IF((CH47-ROUNDDOWN(CH47,-1))=G47,H47,"")&IF((CH47-ROUNDDOWN(CH47,-1))=I47,J47,"")&IF((CH47-ROUNDDOWN(CH47,-1))=K47,L47,"")&IF((CH47-ROUNDDOWN(CH47,-1))=M47,N47,"")&IF((CH47-ROUNDDOWN(CH47,-1))=O47,P47,"")&IF((CH47-ROUNDDOWN(CH47,-1))=Q47,R47,"")&IF((CH47-ROUNDDOWN(CH47,-1))=S47,T47,""),IF(CH47>=20,"twenty "&IF((CH47-ROUNDDOWN(CH47,-1))=1,D47,"")&IF((CH47-ROUNDDOWN(CH47,-1))=2,F47,"")&IF((CH47-ROUNDDOWN(CH47,-1))=G47,H47,"")&IF((CH47-ROUNDDOWN(CH47,-1))=I47,J47,"")&IF((CH47-ROUNDDOWN(CH47,-1))=K47,L47,"")&IF((CH47-ROUNDDOWN(CH47,-1))=M47,N47,"")&IF((CH47-ROUNDDOWN(CH47,-1))=O47,P47,"")&IF((CH47-ROUNDDOWN(CH47,-1))=Q47,R47,"")&IF((CH47-ROUNDDOWN(CH47,-1))=S47,T47,""),"")))) | CF47: =IF(CH47="","",IF(CH47=C47,D47,"")&IF(CH47=E47,F47,"")&IF(CH47=G47,H47,"")&IF(CH47=I47,J47,"")&IF(CH47=K47,L47,"")&IF(CH47=M47,N47,"")&IF(CH47=O47,P47,"")&IF(CH47=Q47,R47,"")&IF(CH47=S47,T47,"")&IF(CH47=U47,V47,"")&IF(CH47=W47,X47,"")&IF(CH47=Y47,Z47,"")&IF(CH47=AA47,AB47,"")&IF(CH47=AC47,AD47,"")&IF(CH47=AE47,AF47,"")&IF(CH47=AG47,AH47,"")&IF(CH47=AI47,AJ47,"")&IF(CH47=AK47,AL47,"")&IF(CH47=AM47,AN47,"")) | CH47: =IF(A47>=1,ROUNDDOWN(A47-ROUNDDOWN(A47,-2),0),"") -> 62 | CI47: =IF(CB47="","",CB47)&IF(CC47="","",CC47)&IF(CD47="","",CD47)&IF(CE47="","",CE47)&IF(CF47="","",CF47) -> sixty two | CJ47: PAISE | CK47: =IF(CQ47="","",IF(CQ47>=90,"ninety "&IF((CQ47-ROUNDDOWN(CQ47,-1))=1,D47,"")&IF((CQ47-ROUNDDOWN(CQ47,-1))=2,F47,"")&IF((CQ47-ROUNDDOWN(CQ47,-1))=G47,H47,"")&IF((CQ47-ROUNDDOWN(CQ47,-1))=I47,J47,"")&IF((CQ47-ROUNDDOWN(CQ47,-1))=K47,L47,"")&IF((CQ47-ROUNDDOWN(CQ47,-1))=M47,N47,"")&IF((CQ47-ROUNDDOWN(CQ47,-1))=O47,P47,"")&IF((CQ47-ROUNDDOWN(CQ47,-1))=Q47,R47,"")&IF((CQ47-ROUNDDOWN(CQ47,-1))=S47,T47,""),IF(CQ47>=80,"eighty "&IF((CQ47-ROUNDDOWN(CQ47,-1))=1,D47,"")&IF((CQ47-ROUNDDOWN(CQ47,-1))=2,F47,"")&IF((CQ47-ROUNDDOWN(CQ47,-1))=G47,H47,"")&IF((CQ47-ROUNDDOWN(CQ47,-1))=I47,J47,"")&IF((CQ47-ROUNDDOWN(CQ47,-1))=K47,L47,"")&IF((CQ47-ROUNDDOWN(CQ47,-1))=M47,N47,"")&IF((CQ47-ROUNDDOWN(CQ47,-1))=O47,P47,"")&IF((CQ47-ROUNDDOWN(CQ47,-1))=Q47,R47,"")&IF((CQ47-ROUNDDOWN(CQ47,-1))=S47,T47,""),""))) | CL47: =IF(CQ47="","",IF(CQ47>79,"",IF(CQ47>=70,"seventy "&IF((CQ47-ROUNDDOWN(CQ47,-1))=1,D47,"")&IF((CQ47-ROUNDDOWN(CQ47,-1))=2,F47,"")&IF((CQ47-ROUNDDOWN(CQ47,-1))=G47,H47,"")&IF((CQ47-ROUNDDOWN(CQ47,-1))=I47,J47,"")&IF((CQ47-ROUNDDOWN(CQ47,-1))=K47,L47,"")&IF((CQ47-ROUNDDOWN(CQ47,-1))=M47,N47,"")&IF((CQ47-ROUNDDOWN(CQ47,-1))=O47,P47,"")&IF((CQ47-ROUNDDOWN(CQ47,-1))=Q47,R47,"")&IF((CQ47-ROUNDDOWN(CQ47,-1))=S47,T47,""),IF(CQ47>=60,"sixty "&IF((CQ47-ROUNDDOWN(CQ47,-1))=1,D47,"")&IF((CQ47-ROUNDDOWN(CQ47,-1))=2,F47,"")&IF((CQ47-ROUNDDOWN(CQ47,-1))=G47,H47,"")&IF((CQ47-ROUNDDOWN(CQ47,-1))=I47,J47,"")&IF((CQ47-ROUNDDOWN(CQ47,-1))=K47,L47,"")&IF((CQ47-ROUNDDOWN(CQ47,-1))=M47,N47,"")&IF((CQ47-ROUNDDOWN(CQ47,-1))=O47,P47,"")&IF((CQ47-ROUNDDOWN(CQ47,-1))=Q47,R47,"")&IF((CQ47-ROUNDDOWN(CQ47,-1))=S47,T47,""),"")))) | CM47: =IF(CQ47="","",IF(CQ47>59,"",IF(CQ47>=50,"fifty "&IF((CQ47-ROUNDDOWN(CQ47,-1))=1,D47,"")&IF((CQ47-ROUNDDOWN(CQ47,-1))=2,F47,"")&IF((CQ47-ROUNDDOWN(CQ47,-1))=G47,H47,"")&IF((CQ47-ROUNDDOWN(CQ47,-1))=I47,J47,"")&IF((CQ47-ROUNDDOWN(CQ47,-1))=K47,L47,"")&IF((CQ47-ROUNDDOWN(CQ47,-1))=M47,N47,"")&IF((CQ47-ROUNDDOWN(CQ47,-1))=O47,P47,"")&IF((CQ47-ROUNDDOWN(CQ47,-1))=Q47,R47,"")&IF((CQ47-ROUNDDOWN(CQ47,-1))=S47,T47,""),IF(CQ47>=40,"forty "&IF((CQ47-ROUNDDOWN(CQ47,-1))=1,D47,"")&IF((CQ47-ROUNDDOWN(CQ47,-1))=2,F47,"")&IF((CQ47-ROUNDDOWN(CQ47,-1))=G47,H47,"")&IF((CQ47-ROUNDDOWN(CQ47,-1))=I47,J47,"")&IF((CQ47-ROUNDDOWN(CQ47,-1))=K47,L47,"")&IF((CQ47-ROUNDDOWN(CQ47,-1))=M47,N47,"")&IF((CQ47-ROUNDDOWN(CQ47,-1))=O47,P47,"")&IF((CQ47-ROUNDDOWN(CQ47,-1))=Q47,R47,"")&IF((CQ47-ROUNDDOWN(CQ47,-1))=S47,T47,""),"")))) | CN47: =IF(CQ47="","",IF(CQ47>39,"",IF(CQ47>=30,"thirty "&IF((CQ47-ROUNDDOWN(CQ47,-1))=1,D47,"")&IF((CQ47-ROUNDDOWN(CQ47,-1))=2,F47,"")&IF((CQ47-ROUNDDOWN(CQ47,-1))=G47,H47,"")&IF((CQ47-ROUNDDOWN(CQ47,-1))=I47,J47,"")&IF((CQ47-ROUNDDOWN(CQ47,-1))=K47,L47,"")&IF((CQ47-ROUNDDOWN(CQ47,-1))=M47,N47,"")&IF((CQ47-ROUNDDOWN(CQ47,-1))=O47,P47,"")&IF((CQ47-ROUNDDOWN(CQ47,-1))=Q47,R47,"")&IF((CQ47-ROUNDDOWN(CQ47,-1))=S47,T47,""),IF(CQ47>=20,"twenty "&IF((CQ47-ROUNDDOWN(CQ47,-1))=1,D47,"")&IF((CQ47-ROUNDDOWN(CQ47,-1))=2,F47,"")&IF((CQ47-ROUNDDOWN(CQ47,-1))=G47,H47,"")&IF((CQ47-ROUNDDOWN(CQ47,-1))=I47,J47,"")&IF((CQ47-ROUNDDOWN(CQ47,-1))=K47,L47,"")&IF((CQ47-ROUNDDOWN(CQ47,-1))=M47,N47,"")&IF((CQ47-ROUNDDOWN(CQ47,-1))=O47,P47,"")&IF((CQ47-ROUNDDOWN(CQ47,-1))=Q47,R47,"")&IF((CQ47-ROUNDDOWN(CQ47,-1))=S47,T47,""),"")))) | CO47: =IF(CQ47="","",IF(CQ47=C47,D47,"")&IF(CQ47=E47,F47,"")&IF(CQ47=G47,H47,"")&IF(CQ47=I47,J47,"")&IF(CQ47=K47,L47,"")&IF(CQ47=M47,N47,"")&IF(CQ47=O47,P47,"")&IF(CQ47=Q47,R47,"")&IF(CQ47=S47,T47,"")&IF(CQ47=U47,V47,"")&IF(CQ47=W47,X47,"")&IF(CQ47=Y47,Z47,"")&IF(CQ47=AA47,AB47,"")&IF(CQ47=AC47,AD47,"")&IF(CQ47=AE47,AF47,"")&IF(CQ47=AG47,AH47,"")&IF(CQ47=AI47,AJ47,"")&IF(CQ47=AK47,AL47,"")&IF(CQ47=AM47,AN47,"")) | CQ47: =IF((A47-ROUNDDOWN(A47,0))>0,ROUND((A47-ROUNDDOWN(A47,0))*100,0),"") | CR47: =IF(CK47="","",CK47)&IF(CL47="","",CL47)&IF(CM47="","",CM47)&IF(CN47="","",CN47)&IF(CO47="","",CO47) | CS47: <= IN WORDS | CU47: =IF(A47="","","(Rupees "&IF(AY47="","",AY47&" crore ")&IF(BH47="","",BH47&" lakh ")&IF(BQ47="","",BQ47&" thousand ")&IF(BZ47="","",BZ47&" hundred ")&IF(CI47="","",CI47)&IF(CR47="",""," and paise "&CR47)&") only.") -> (Rupees twenty three lakh fifty seven thousand one hundred sixty two) only.

Sheet AType Cottage
A1: Name of Work :- Repairing and Renovation of Circuit House at Bokakhat Co District under Golaghat District
A2: (Rates are quoted from DSR (civil) of 2021)
A3: DETAIL ESTIMATE
A4: SL. No. | B4: CODE NO | C4: PARTICULARS | K4: QTY | L4: Unit | M4: RATE | N4: AMOUNT
A6: 1 | B6: 9.1 | C6: Providing wood work in frames of doors, windows, clerestory windows and other frames, wrought framed and fixed in position with hold fast lugs or with dash fasteners of required dia & length (hold fast lugs or dash fastener shall be paid for separately). 9.1.3 Kiln seasoned and chemically treated hollock wood
C7: Quantity
C8: Door, D1 | D8: 1 | E8: x | F8: =2.1+2.1+1.2 -> 5.4 | G8: x | H8: 0.075 | I8: x | J8: 0.1 | K8: =D8*F8*H8*J8 -> 0.041 | L8: cum
C9: W1 | D9: 4 | F9: =1.8*2+1.5*2 -> 6.6 | G9: x | H9: 0.08 | I9: x | J9: 0.1 | K9: =D9*F9*H9*J9 -> 0.211 | L9: cum
C10: V | D10: 5 | F10: =0.9*2+0.45*2 -> 2.7 | G10: x | H10: 0.08 | I10: x | J10: 0.1 | K10: =D10*F10*H10*J10 -> 0.108 | L10: cum
C11: Total | K11: =SUM(K8:K10) -> 0.36 | L11: cum | M11: 74199.7 | N11: =K11*M11 -> 26711.89
A12: 2 | B12: 9.5 | C12: Providing and fixing panelled or panelled and glazed shutters for doors, windows and clerestory windows, fixing with butt hinges of required size with necessary screws, excluding panelling which will be paid for separately, all complete as per direction of Engineer-in-charge. (Note:- Butt hinges and necessary screws shall be paid separately) 9.5.2 Kiln seasoned and chemically treated hollock wood 9.5.2.1 35 mm thick shutters | O12: =M12*N12 -> 0
C13: Quantity | O13: -5
C14: Door, D1 | D14: 1 | E14: x | F14: 1.2 | I14: x | J14: 2.1 | K14: =D14*F14*J14 -> 2.52 | L14: sqm | O14: -3
C15: W1 | D15: 4 | E15: x | F15: 1.5 | I15: x | J15: 1.8 | K15: =D15*F15*J15 -> 10.8 | L15: sqm
C16: V | D16: 5 | E16: x | F16: 1.5 | I16: x | J16: 0.45 | K16: =D16*F16*J16 -> 3.38 | L16: sqm
C17: Total | K17: =SUM(K14:K16) -> 16.7 | L17: sqm | M17: 2511.95 | N17: =K17*M17 -> 41949.57 | O17: =SUM(O6:O14) -> -8
A18: 3 | B18: 11.41 | C18: Providing and laying vitrified floor tiles in different sizes (thickness to be specified by the manufacturer) with water absorption less than 0.08% and conforming to IS: 15622, of approved make, in all colours and shades, laid on 20mm thick cement mortar 1:4 (1 cement : 4 coarse sand), jointing with grey cement slurry @ 3.3 kg/ sqm including grouting the joints with white cement and matching pigments etc., complete. 11.41.2 Size of Tile 600x600 mm.
D19: 1 | E19: x | F19: 5 | I19: x | J19: 7.5 | K19: =D19*F19*J19 -> 37.5 | L19: sqm | O19: -3
D20: 1 | E20: x | F20: 2.2 | I20: x | J20: 2.5 | K20: =D20*F20*J20 -> 5.5 | L20: sqm
C21: Total | K21: =SUM(K19:K20) -> 43 | L21: sqm | M21: 1416.65 | N21: =K21*M21 -> 60915.95 | O21: =SUM(O10:O19) -> -19
A22: 4 | B22: 8.31 | C22: Providing and fixing Ist quality ceramic glazed wall tiles conforming to IS: 15622 (thickness to be specified by the manufacturer), of approved make, in all colours, shades except burgundy, bottle green, black of any size as approved by Engineer-in-Charge, in skirting, risers of steps and dados, over 12 mm thick bed of cement mortar 1:3 (1 cement : 3 coarse sand) and jointing with grey cement slurry @ 3.3kg per sqm, including pointing in white cement mixed with pigment of matching shade complete.
D23: 2 | E23: x | F23: 2.1 | I23: x | J23: 1.5 | K23: =D23*F23*J23 -> 6.3 | L23: sqm | O23: -3
D24: 2 | E24: x | F24: 2.5 | I24: x | J24: 1.5 | K24: =D24*F24*J24 -> 7.5 | L24: sqm
C25: Deduct , Door | D25: -1 | E25: x | F25: 1.2 | I25: x | J25: 1.5 | K25: =D25*F25*J25 -> -1.8 | L25: sqm
C26: Total | K26: =SUM(K23:K25) -> 12 | L26: sqm | M26: 1063.45 | N26: =K26*M26 -> 12761.4 | O26: =SUM(O16:O23) -> -33
A27: 5 | B27: 15.12 | C27: Dismantling doors, windows and clerestory windows (steel or wood) shutter including chowkhats, architrave, holdfasts etc. complete and stacking within 50 metres lead : 15.12.1Of area 3 sq. metres and below | P27: =SQRT(((R27)^2)+((S27)^2)) -> 3.982 | Q27: =(5.2+0.5+0.5)/2 -> 3.1 | R27: 2.5 | S27: =Q27 -> 3.1
C28: Door | D28: 2 | K28: =D28 -> 2 | L28: each
C29: Window | D29: 4 | K29: =D29 -> 4 | L29: each
C30: Ventilators | D30: 5 | K30: =D30 -> 5 | L30: each
C31: TOTAL= | K31: =SUM(K28:K30) -> 11 | L31: each | M31: 302.7 | N31: =ROUND(K31*M31,2) -> 3329.7
A32: 6 | B32: 15.23 | C32: Dismantling tile work in floors and roofs laid in cement mortar including stacking material within 50 metres lead. 15.23.1 For thickness of tiles 10 mm to 25 mm | P32: =SQRT(((R32)^2)+((S32)^2)) -> 3.982 | Q32: =(5.2+0.5+0.5)/2 -> 3.1 | R32: 2.5 | S32: =Q32 -> 3.1
D33: 1 | E33: x | F33: 5 | I33: x | J33: 7.5 | K33: =D33*F33*J33 -> 37.5 | L33: sqm
D34: 1 | E34: x | F34: 2.2 | I34: x | J34: 2.5 | K34: =D34*F34*J34 -> 5.5 | L34: sqm
C35: TOTAL= | K35: =SUM(K33:K34) -> 43 | L35: each | M35: 60.5 | N35: =ROUND(K35*M35,2) -> 2601.5
A36: TOTAL OF CIVIL WORKS (A) = | N36: =SUM(N6:N35) -> 148270.01
A37: TOTAL= | N37: =ROUND(N36,0) -> 148270
C38: =CU44 -> (Rupees one lakh forty eight thousand two hundred seventy ) only.
Q40: 15.23 Dismantling tile work in floors and roofs laid in cement mortar including
Q41: stacking material within 50 metres lead.
Q42: 15.23.1 For thickness of tiles 10 mm to 25 mm
A44: =N37 -> 148270 | B44: COPY CELLS=> | C44: 1 | D44: one | E44: 2 | F44: two | G44: 3 | H44: three | I44: 4 | J44: four | K44: 5 | L44: five | M44: 6 | N44: six | O44: 7 | P44: seven | Q44: 8 | R44: eight | S44: 9 | T44: nine | U44: 10 | V44: ten | W44: 11 | X44: eleven | Y44: 12 | Z44: twelve | AA44: 13 | AB44: thirteen | AC44: 14 | AD44: fourteen | AE44: 15 | AF44: fifteen | AG44: 16 | AH44: sixteen | AI44: 17 | AJ44: seventeen | AK44: 18 | AL44: eighteen | AM44: 19 | AN44: nineteen | AO44: <=COPY CELLS | AP44: WORDS-> | AQ44: CRORE | AR44: =IF(AX44="","",IF(AX44>=90,"ninety "&IF((AX44-ROUNDDOWN(AX44,-1))=C44,D44,"")&IF((AX44-ROUNDDOWN(AX44,-1))=E44,F44,"")&IF((AX44-ROUNDDOWN(AX44,-1))=G44,H44,"")&IF((AX44-ROUNDDOWN(AX44,-1))=I44,J44,"")&IF((AX44-ROUNDDOWN(AX44,-1))=K44,L44,"")&IF((AX44-ROUNDDOWN(AX44,-1))=M44,N44,"")&IF((AX44-ROUNDDOWN(AX44,-1))=O44,P44,"")&IF((AX44-ROUNDDOWN(AX44,-1))=Q44,R44,"")&IF((AX44-ROUNDDOWN(AX44,-1))=S44,T44,""),IF(AX44>=80,"eighty "&IF((AX44-ROUNDDOWN(AX44,-1))=1,D44,"")&IF((AX44-ROUNDDOWN(AX44,-1))=2,F44,"")&IF((AX44-ROUNDDOWN(AX44,-1))=G44,H44,"")&IF((AX44-ROUNDDOWN(AX44,-1))=I44,J44,"")&IF((AX44-ROUNDDOWN(AX44,-1))=K44,L44,"")&IF((AX44-ROUNDDOWN(AX44,-1))=M44,N44,"")&IF((AX44-ROUNDDOWN(AX44,-1))=O44,P44,"")&IF((AX44-ROUNDDOWN(AX44,-1))=Q44,R44,"")&IF((AX44-ROUNDDOWN(AX44,-1))=S44,T44,""),""))) | AS44: =IF(AX44="","",IF(AX44>79,"",IF(AX44>=70,"seventy "&IF((AX44-ROUNDDOWN(AX44,-1))=C44,D44,"")&IF((AX44-ROUNDDOWN(AX44,-1))=E44,F44,"")&IF((AX44-ROUNDDOWN(AX44,-1))=G44,H44,"")&IF((AX44-ROUNDDOWN(AX44,-1))=I44,J44,"")&IF((AX44-ROUNDDOWN(AX44,-1))=K44,L44,"")&IF((AX44-ROUNDDOWN(AX44,-1))=M44,N44,"")&IF((AX44-ROUNDDOWN(AX44,-1))=O44,P44,"")&IF((AX44-ROUNDDOWN(AX44,-1))=Q44,R44,"")&IF((AX44-ROUNDDOWN(AX44,-1))=S44,T44,""),IF(AX44>=60,"sixty "&IF((AX44-ROUNDDOWN(AX44,-1))=1,D44,"")&IF((AX44-ROUNDDOWN(AX44,-1))=2,F44,"")&IF((AX44-ROUNDDOWN(AX44,-1))=G44,H44,"")&IF((AX44-ROUNDDOWN(AX44,-1))=I44,J44,"")&IF((AX44-ROUNDDOWN(AX44,-1))=K44,L44,"")&IF((AX44-ROUNDDOWN(AX44,-1))=M44,N44,"")&IF((AX44-ROUNDDOWN(AX44,-1))=O44,P44,"")&IF((AX44-ROUNDDOWN(AX44,-1))=Q44,R44,"")&IF((AX44-ROUNDDOWN(AX44,-1))=S44,T44,""),"")))) | AT44: =IF(AX44="","",IF(AX44>59,"",IF(AX44>=50,"fifty "&IF((AX44-ROUNDDOWN(AX44,-1))=C44,D44,"")&IF((AX44-ROUNDDOWN(AX44,-1))=E44,F44,"")&IF((AX44-ROUNDDOWN(AX44,-1))=G44,H44,"")&IF((AX44-ROUNDDOWN(AX44,-1))=I44,J44,"")&IF((AX44-ROUNDDOWN(AX44,-1))=K44,L44,"")&IF((AX44-ROUNDDOWN(AX44,-1))=M44,N44,"")&IF((AX44-ROUNDDOWN(AX44,-1))=O44,P44,"")&IF((AX44-ROUNDDOWN(AX44,-1))=Q44,R44,"")&IF((AX44-ROUNDDOWN(AX44,-1))=S44,T44,""),IF(AX44>=40,"forty "&IF((AX44-ROUNDDOWN(AX44,-1))=1,D44,"")&IF((AX44-ROUNDDOWN(AX44,-1))=2,F44,"")&IF((AX44-ROUNDDOWN(AX44,-1))=G44,H44,"")&IF((AX44-ROUNDDOWN(AX44,-1))=I44,J44,"")&IF((AX44-ROUNDDOWN(AX44,-1))=K44,L44,"")&IF((AX44-ROUNDDOWN(AX44,-1))=M44,N44,"")&IF((AX44-ROUNDDOWN(AX44,-1))=O44,P44,"")&IF((AX44-ROUNDDOWN(AX44,-1))=Q44,R44,"")&IF((AX44-ROUNDDOWN(AX44,-1))=S44,T44,""),"")))) | AU44: =IF(AX44="","",IF(AX44>39,"",IF(AX44>=30,"thirty "&IF((AX44-ROUNDDOWN(AX44,-1))=C44,D44,"")&IF((AX44-ROUNDDOWN(AX44,-1))=E44,F44,"")&IF((AX44-ROUNDDOWN(AX44,-1))=G44,H44,"")&IF((AX44-ROUNDDOWN(AX44,-1))=I44,J44,"")&IF((AX44-ROUNDDOWN(AX44,-1))=K44,L44,"")&IF((AX44-ROUNDDOWN(AX44,-1))=M44,N44,"")&IF((AX44-ROUNDDOWN(AX44,-1))=O44,P44,"")&IF((AX44-ROUNDDOWN(AX44,-1))=Q44,R44,"")&IF((AX44-ROUNDDOWN(AX44,-1))=S44,T44,""),IF(AX44>=20,"twenty "&IF((AX44-ROUNDDOWN(AX44,-1))=1,D44,"")&IF((AX44-ROUNDDOWN(AX44,-1))=2,F44,"")&IF((AX44-ROUNDDOWN(AX44,-1))=G44,H44,"")&IF((AX44-ROUNDDOWN(AX44,-1))=I44,J44,"")&IF((AX44-ROUNDDOWN(AX44,-1))=K44,L44,"")&IF((AX44-ROUNDDOWN(AX44,-1))=M44,N44,"")&IF((AX44-ROUNDDOWN(AX44,-1))=O44,P44,"")&IF((AX44-ROUNDDOWN(AX44,-1))=Q44,R44,"")&IF((AX44-ROUNDDOWN(AX44,-1))=S44,T44,""),"")))) | AV44: =IF(AX44="","",IF(AX44=C44,D44,"")&IF(AX44=E44,F44,"")&IF(AX44=G44,H44,"")&IF(AX44=I44,J44,"")&IF(AX44=K44,L44,"")&IF(AX44=M44,N44,"")&IF(AX44=O44,P44,"")&IF(AX44=Q44,R44,"")&IF(AX44=S44,T44,"")&IF(AX44=U44,V44,"")&IF(AX44=W44,X44,"")&IF(AX44=Y44,Z44,"")&IF(AX44=AA44,AB44,"")&IF(AX44=AC44,AD44,"")&IF(AX44=AE44,AF44,"")&IF(AX44=AG44,AH44,"")&IF(AX44=AI44,AJ44,"")&IF(AX44=AK44,AL44,"")&IF(AX44=AM44,AN44,"")) | AX44: =IF(A44>=10000000,ROUNDDOWN(A44,-7)/10000000,"") | AY44: =IF(AR44="","",AR44)&IF(AS44="","",AS44)&IF(AT44="","",AT44)&IF(AU44="","",AU44)&IF(AV44="","",AV44) | AZ44: LAKH | BA44: =IF(BG44="","",IF(BG44>=90,"ninety "&IF((BG44-ROUNDDOWN(BG44,-1))=C44,D44,"")&IF((BG44-ROUNDDOWN(BG44,-1))=E44,F44,"")&IF((BG44-ROUNDDOWN(BG44,-1))=G44,H44,"")&IF((BG44-ROUNDDOWN(BG44,-1))=I44,J44,"")&IF((BG44-ROUNDDOWN(BG44,-1))=K44,L44,"")&IF((BG44-ROUNDDOWN(BG44,-1))=M44,N44,"")&IF((BG44-ROUNDDOWN(BG44,-1))=O44,P44,"")&IF((BG44-ROUNDDOWN(BG44,-1))=Q44,R44,"")&IF((BG44-ROUNDDOWN(BG44,-1))=S44,T44,""),IF(BG44>=80,"eighty "&IF((BG44-ROUNDDOWN(BG44,-1))=1,D44,"")&IF((BG44-ROUNDDOWN(BG44,-1))=2,F44,"")&IF((BG44-ROUNDDOWN(BG44,-1))=G44,H44,"")&IF((BG44-ROUNDDOWN(BG44,-1))=I44,J44,"")&IF((BG44-ROUNDDOWN(BG44,-1))=K44,L44,"")&IF((BG44-ROUNDDOWN(BG44,-1))=M44,N44,"")&IF((BG44-ROUNDDOWN(BG44,-1))=O44,P44,"")&IF((BG44-ROUNDDOWN(BG44,-1))=Q44,R44,"")&IF((BG44-ROUNDDOWN(BG44,-1))=S44,T44,""),""))) | BB44: =IF(BG44="","",IF(BG44>79,"",IF(BG44>=70,"seventy "&IF((BG44-ROUNDDOWN(BG44,-1))=C44,D44,"")&IF((BG44-ROUNDDOWN(BG44,-1))=E44,F44,"")&IF((BG44-ROUNDDOWN(BG44,-1))=G44,H44,"")&IF((BG44-ROUNDDOWN(BG44,-1))=I44,J44,"")&IF((BG44-ROUNDDOWN(BG44,-1))=K44,L44,"")&IF((BG44-ROUNDDOWN(BG44,-1))=M44,N44,"")&IF((BG44-ROUNDDOWN(BG44,-1))=O44,P44,"")&IF((BG44-ROUNDDOWN(BG44,-1))=Q44,R44,"")&IF((BG44-ROUNDDOWN(BG44,-1))=S44,T44,""),IF(BG44>=60,"sixty "&IF((BG44-ROUNDDOWN(BG44,-1))=1,D44,"")&IF((BG44-ROUNDDOWN(BG44,-1))=2,F44,"")&IF((BG44-ROUNDDOWN(BG44,-1))=G44,H44,"")&IF((BG44-ROUNDDOWN(BG44,-1))=I44,J44,"")&IF((BG44-ROUNDDOWN(BG44,-1))=K44,L44,"")&IF((BG44-ROUNDDOWN(BG44,-1))=M44,N44,"")&IF((BG44-ROUNDDOWN(BG44,-1))=O44,P44,"")&IF((BG44-ROUNDDOWN(BG44,-1))=Q44,R44,"")&IF((BG44-ROUNDDOWN(BG44,-1))=S44,T44,""),"")))) | BC44: =IF(BG44="","",IF(BG44>59,"",IF(BG44>=50,"fifty "&IF((BG44-ROUNDDOWN(BG44,-1))=C44,D44,"")&IF((BG44-ROUNDDOWN(BG44,-1))=E44,F44,"")&IF((BG44-ROUNDDOWN(BG44,-1))=G44,H44,"")&IF((BG44-ROUNDDOWN(BG44,-1))=I44,J44,"")&IF((BG44-ROUNDDOWN(BG44,-1))=K44,L44,"")&IF((BG44-ROUNDDOWN(BG44,-1))=M44,N44,"")&IF((BG44-ROUNDDOWN(BG44,-1))=O44,P44,"")&IF((BG44-ROUNDDOWN(BG44,-1))=Q44,R44,"")&IF((BG44-ROUNDDOWN(BG44,-1))=S44,T44,""),IF(BG44>=40,"forty "&IF((BG44-ROUNDDOWN(BG44,-1))=1,D44,"")&IF((BG44-ROUNDDOWN(BG44,-1))=2,F44,"")&IF((BG44-ROUNDDOWN(BG44,-1))=G44,H44,"")&IF((BG44-ROUNDDOWN(BG44,-1))=I44,J44,"")&IF((BG44-ROUNDDOWN(BG44,-1))=K44,L44,"")&IF((BG44-ROUNDDOWN(BG44,-1))=M44,N44,"")&IF((BG44-ROUNDDOWN(BG44,-1))=O44,P44,"")&IF((BG44-ROUNDDOWN(BG44,-1))=Q44,R44,"")&IF((BG44-ROUNDDOWN(BG44,-1))=S44,T44,""),"")))) | BD44: =IF(BG44="","",IF(BG44>39,"",IF(BG44>=30,"thirty "&IF((BG44-ROUNDDOWN(BG44,-1))=C44,D44,"")&IF((BG44-ROUNDDOWN(BG44,-1))=E44,F44,"")&IF((BG44-ROUNDDOWN(BG44,-1))=G44,H44,"")&IF((BG44-ROUNDDOWN(BG44,-1))=I44,J44,"")&IF((BG44-ROUNDDOWN(BG44,-1))=K44,L44,"")&IF((BG44-ROUNDDOWN(BG44,-1))=M44,N44,"")&IF((BG44-ROUNDDOWN(BG44,-1))=O44,P44,"")&IF((BG44-ROUNDDOWN(BG44,-1))=Q44,R44,"")&IF((BG44-ROUNDDOWN(BG44,-1))=S44,T44,""),IF(BG44>=20,"twenty "&IF((BG44-ROUNDDOWN(BG44,-1))=1,D44,"")&IF((BG44-ROUNDDOWN(BG44,-1))=2,F44,"")&IF((BG44-ROUNDDOWN(BG44,-1))=G44,H44,"")&IF((BG44-ROUNDDOWN(BG44,-1))=I44,J44,"")&IF((BG44-ROUNDDOWN(BG44,-1))=K44,L44,"")&IF((BG44-ROUNDDOWN(BG44,-1))=M44,N44,"")&IF((BG44-ROUNDDOWN(BG44,-1))=O44,P44,"")&IF((BG44-ROUNDDOWN(BG44,-1))=Q44,R44,"")&IF((BG44-ROUNDDOWN(BG44,-1))=S44,T44,""),"")))) | BE44: =IF(BG44="","",IF(BG44=C44,D44,"")&IF(BG44=E44,F44,"")&IF(BG44=G44,H44,"")&IF(BG44=I44,J44,"")&IF(BG44=K44,L44,"")&IF(BG44=M44,N44,"")&IF(BG44=O44,P44,"")&IF(BG44=Q44,R44,"")&IF(BG44=S44,T44,"")&IF(BG44=U44,V44,"")&IF(BG44=W44,X44,"")&IF(BG44=Y44,Z44,"")&IF(BG44=AA44,AB44,"")&IF(BG44=AC44,AD44,"")&IF(BG44=AE44,AF44,"")&IF(BG44=AG44,AH44,"")&IF(BG44=AI44,AJ44,"")&IF(BG44=AK44,AL44,"")&IF(BG44=AM44,AN44,"")) -> one | BG44: =IF(A44>=100000,ROUNDDOWN((ROUND(A44,-4)-ROUNDDOWN(A44,-7))/100000,0),"") -> 1 | BH44: =IF(BA44="","",BA44)&IF(BB44="","",BB44)&IF(BC44="","",BC44)&IF(BD44="","",BD44)&IF(BE44="","",BE44) -> one | BI44: THOUSAND | BJ44: =IF(BP44="","",IF(BP44>=90,"ninety "&IF((BP44-ROUNDDOWN(BP44,-1))=1,D44,"")&IF((BP44-ROUNDDOWN(BP44,-1))=2,F44,"")&IF((BP44-ROUNDDOWN(BP44,-1))=G44,H44,"")&IF((BP44-ROUNDDOWN(BP44,-1))=I44,J44,"")&IF((BP44-ROUNDDOWN(BP44,-1))=K44,L44,"")&IF((BP44-ROUNDDOWN(BP44,-1))=M44,N44,"")&IF((BP44-ROUNDDOWN(BP44,-1))=O44,P44,"")&IF((BP44-ROUNDDOWN(BP44,-1))=Q44,R44,"")&IF((BP44-ROUNDDOWN(BP44,-1))=S44,T44,""),IF(BP44>=80,"eighty "&IF((BP44-ROUNDDOWN(BP44,-1))=1,D44,"")&IF((BP44-ROUNDDOWN(BP44,-1))=2,F44,"")&IF((BP44-ROUNDDOWN(BP44,-1))=G44,H44,"")&IF((BP44-ROUNDDOWN(BP44,-1))=I44,J44,"")&IF((BP44-ROUNDDOWN(BP44,-1))=K44,L44,"")&IF((BP44-ROUNDDOWN(BP44,-1))=M44,N44,"")&IF((BP44-ROUNDDOWN(BP44,-1))=O44,P44,"")&IF((BP44-ROUNDDOWN(BP44,-1))=Q44,R44,"")&IF((BP44-ROUNDDOWN(BP44,-1))=S44,T44,""),""))) | BK44: =IF(BP44="","",IF(BP44>79,"",IF(BP44>=70,"seventy "&IF((BP44-ROUNDDOWN(BP44,-1))=1,D44,"")&IF((BP44-ROUNDDOWN(BP44,-1))=2,F44,"")&IF((BP44-ROUNDDOWN(BP44,-1))=G44,H44,"")&IF((BP44-ROUNDDOWN(BP44,-1))=I44,J44,"")&IF((BP44-ROUNDDOWN(BP44,-1))=K44,L44,"")&IF((BP44-ROUNDDOWN(BP44,-1))=M44,N44,"")&IF((BP44-ROUNDDOWN(BP44,-1))=O44,P44,"")&IF((BP44-ROUNDDOWN(BP44,-1))=Q44,R44,"")&IF((BP44-ROUNDDOWN(BP44,-1))=S44,T44,""),IF(BP44>=60,"sixty "&IF((BP44-ROUNDDOWN(BP44,-1))=1,D44,"")&IF((BP44-ROUNDDOWN(BP44,-1))=2,F44,"")&IF((BP44-ROUNDDOWN(BP44,-1))=G44,H44,"")&IF((BP44-ROUNDDOWN(BP44,-1))=I44,J44,"")&IF((BP44-ROUNDDOWN(BP44,-1))=K44,L44,"")&IF((BP44-ROUNDDOWN(BP44,-1))=M44,N44,"")&IF((BP44-ROUNDDOWN(BP44,-1))=O44,P44,"")&IF((BP44-ROUNDDOWN(BP44,-1))=Q44,R44,"")&IF((BP44-ROUNDDOWN(BP44,-1))=S44,T44,""),"")))) | BL44: =IF(BP44="","",IF(BP44>59,"",IF(BP44>=50,"fifty "&IF((BP44-ROUNDDOWN(BP44,-1))=1,D44,"")&IF((BP44-ROUNDDOWN(BP44,-1))=2,F44,"")&IF((BP44-ROUNDDOWN(BP44,-1))=G44,H44,"")&IF((BP44-ROUNDDOWN(BP44,-1))=I44,J44,"")&IF((BP44-ROUNDDOWN(BP44,-1))=K44,L44,"")&IF((BP44-ROUNDDOWN(BP44,-1))=M44,N44,"")&IF((BP44-ROUNDDOWN(BP44,-1))=O44,P44,"")&IF((BP44-ROUNDDOWN(BP44,-1))=Q44,R44,"")&IF((BP44-ROUNDDOWN(BP44,-1))=S44,T44,""),IF(BP44>=40,"forty "&IF((BP44-ROUNDDOWN(BP44,-1))=1,D44,"")&IF((BP44-ROUNDDOWN(BP44,-1))=2,F44,"")&IF((BP44-ROUNDDOWN(BP44,-1))=G44,H44,"")&IF((BP44-ROUNDDOWN(BP44,-1))=I44,J44,"")&IF((BP44-ROUNDDOWN(BP44,-1))=K44,L44,"")&IF((BP44-ROUNDDOWN(BP44,-1))=M44,N44,"")&IF((BP44-ROUNDDOWN(BP44,-1))=O44,P44,"")&IF((BP44-ROUNDDOWN(BP44,-1))=Q44,R44,"")&IF((BP44-ROUNDDOWN(BP44,-1))=S44,T44,""),"")))) -> forty eight | BM44: =IF(BP44="","",IF(BP44>39,"",IF(BP44>=30,"thirty "&IF((BP44-ROUNDDOWN(BP44,-1))=1,D44,"")&IF((BP44-ROUNDDOWN(BP44,-1))=2,F44,"")&IF((BP44-ROUNDDOWN(BP44,-1))=G44,H44,"")&IF((BP44-ROUNDDOWN(BP44,-1))=I44,J44,"")&IF((BP44-ROUNDDOWN(BP44,-1))=K44,L44,"")&IF((BP44-ROUNDDOWN(BP44,-1))=M44,N44,"")&IF((BP44-ROUNDDOWN(BP44,-1))=O44,P44,"")&IF((BP44-ROUNDDOWN(BP44,-1))=Q44,R44,"")&IF((BP44-ROUNDDOWN(BP44,-1))=S44,T44,""),IF(BP44>=20,"twenty "&IF((BP44-ROUNDDOWN(BP44,-1))=1,D44,"")&IF((BP44-ROUNDDOWN(BP44,-1))=2,F44,"")&IF((BP44-ROUNDDOWN(BP44,-1))=G44,H44,"")&IF((BP44-ROUNDDOWN(BP44,-1))=I44,J44,"")&IF((BP44-ROUNDDOWN(BP44,-1))=K44,L44,"")&IF((BP44-ROUNDDOWN(BP44,-1))=M44,N44,"")&IF((BP44-ROUNDDOWN(BP44,-1))=O44,P44,"")&IF((BP44-ROUNDDOWN(BP44,-1))=Q44,R44,"")&IF((BP44-ROUNDDOWN(BP44,-1))=S44,T44,""),"")))) | BN44: =IF(BP44="","",IF(BP44=C44,D44,"")&IF(BP44=E44,F44,"")&IF(BP44=G44,H44,"")&IF(BP44=I44,J44,"")&IF(BP44=K44,L44,"")&IF(BP44=M44,N44,"")&IF(BP44=O44,P44,"")&IF(BP44=Q44,R44,"")&IF(BP44=S44,T44,"")&IF(BP44=U44,V44,"")&IF(BP44=W44,X44,"")&IF(BP44=Y44,Z44,"")&IF(BP44=AA44,AB44,"")&IF(BP44=AC44,AD44,"")&IF(BP44=AE44,AF44,"")&IF(BP44=AG44,AH44,"")&IF(BP44=AI44,AJ44,"")&IF(BP44=AK44,AL44,"")&IF(BP44=AM44,AN44,"")) | BP44: =IF(A44>=1000,ROUNDDOWN((A44-ROUNDDOWN(A44,-5))/1000,0),"") -> 48 | BQ44: =IF(BJ44="","",BJ44)&IF(BK44="","",BK44)&IF(BL44="","",BL44)&IF(BM44="","",BM44)&IF(BN44="","",BN44) -> forty eight | BR44: HUNDRED | BS44: =IF(BY44="","",IF(BY44>=90,"ninety "&IF((BY44-ROUNDDOWN(BY44,-1))=1,D44,"")&IF((BY44-ROUNDDOWN(BY44,-1))=2,F44,"")&IF((BY44-ROUNDDOWN(BY44,-1))=G44,H44,"")&IF((BY44-ROUNDDOWN(BY44,-1))=I44,J44,"")&IF((BY44-ROUNDDOWN(BY44,-1))=K44,L44,"")&IF((BY44-ROUNDDOWN(BY44,-1))=M44,N44,"")&IF((BY44-ROUNDDOWN(BY44,-1))=O44,P44,"")&IF((BY44-ROUNDDOWN(BY44,-1))=Q44,R44,"")&IF((BY44-ROUNDDOWN(BY44,-1))=S44,T44,""),IF(BY44>=80,"eighty "&IF((BY44-ROUNDDOWN(BY44,-1))=1,D44,"")&IF((BY44-ROUNDDOWN(BY44,-1))=2,F44,"")&IF((BY44-ROUNDDOWN(BY44,-1))=G44,H44,"")&IF((BY44-ROUNDDOWN(BY44,-1))=I44,J44,"")&IF((BY44-ROUNDDOWN(BY44,-1))=K44,L44,"")&IF((BY44-ROUNDDOWN(BY44,-1))=M44,N44,"")&IF((BY44-ROUNDDOWN(BY44,-1))=O44,P44,"")&IF((BY44-ROUNDDOWN(BY44,-1))=Q44,R44,"")&IF((BY44-ROUNDDOWN(BY44,-1))=S44,T44,""),""))) | BT44: =IF(BY44="","",IF(BY44>79,"",IF(BY44>=70,"seventy "&IF((BY44-ROUNDDOWN(BY44,-1))=1,D44,"")&IF((BY44-ROUNDDOWN(BY44,-1))=2,F44,"")&IF((BY44-ROUNDDOWN(BY44,-1))=G44,H44,"")&IF((BY44-ROUNDDOWN(BY44,-1))=I44,J44,"")&IF((BY44-ROUNDDOWN(BY44,-1))=K44,L44,"")&IF((BY44-ROUNDDOWN(BY44,-1))=M44,N44,"")&IF((BY44-ROUNDDOWN(BY44,-1))=O44,P44,"")&IF((BY44-ROUNDDOWN(BY44,-1))=Q44,R44,"")&IF((BY44-ROUNDDOWN(BY44,-1))=S44,T44,""),IF(BY44>=60,"sixty "&IF((BY44-ROUNDDOWN(BY44,-1))=1,D44,"")&IF((BY44-ROUNDDOWN(BY44,-1))=2,F44,"")&IF((BY44-ROUNDDOWN(BY44,-1))=G44,H44,"")&IF((BY44-ROUNDDOWN(BY44,-1))=I44,J44,"")&IF((BY44-ROUNDDOWN(BY44,-1))=K44,L44,"")&IF((BY44-ROUNDDOWN(BY44,-1))=M44,N44,"")&IF((BY44-ROUNDDOWN(BY44,-1))=O44,P44,"")&IF((BY44-ROUNDDOWN(BY44,-1))=Q44,R44,"")&IF((BY44-ROUNDDOWN(BY44,-1))=S44,T44,""),"")))) | BU44: =IF(BY44="","",IF(BY44>59,"",IF(BY44>=50,"fifty "&IF((BY44-ROUNDDOWN(BY44,-1))=1,D44,"")&IF((BY44-ROUNDDOWN(BY44,-1))=2,F44,"")&IF((BY44-ROUNDDOWN(BY44,-1))=G44,H44,"")&IF((BY44-ROUNDDOWN(BY44,-1))=I44,J44,"")&IF((BY44-ROUNDDOWN(BY44,-1))=K44,L44,"")&IF((BY44-ROUNDDOWN(BY44,-1))=M44,N44,"")&IF((BY44-ROUNDDOWN(BY44,-1))=O44,P44,"")&IF((BY44-ROUNDDOWN(BY44,-1))=Q44,R44,"")&IF((BY44-ROUNDDOWN(BY44,-1))=S44,T44,""),IF(BY44>=40,"forty "&IF((BY44-ROUNDDOWN(BY44,-1))=1,D44,"")&IF((BY44-ROUNDDOWN(BY44,-1))=2,F44,"")&IF((BY44-ROUNDDOWN(BY44,-1))=G44,H44,"")&IF((BY44-ROUNDDOWN(BY44,-1))=I44,J44,"")&IF((BY44-ROUNDDOWN(BY44,-1))=K44,L44,"")&IF((BY44-ROUNDDOWN(BY44,-1))=M44,N44,"")&IF((BY44-ROUNDDOWN(BY44,-1))=O44,P44,"")&IF((BY44-ROUNDDOWN(BY44,-1))=Q44,R44,"")&IF((BY44-ROUNDDOWN(BY44,-1))=S44,T44,""),"")))) | BV44: =IF(BY44="","",IF(BY44>39,"",IF(BY44>=30,"thirty "&IF((BY44-ROUNDDOWN(BY44,-1))=1,D44,"")&IF((BY44-ROUNDDOWN(BY44,-1))=2,F44,"")&IF((BY44-ROUNDDOWN(BY44,-1))=G44,H44,"")&IF((BY44-ROUNDDOWN(BY44,-1))=I44,J44,"")&IF((BY44-ROUNDDOWN(BY44,-1))=K44,L44,"")&IF((BY44-ROUNDDOWN(BY44,-1))=M44,N44,"")&IF((BY44-ROUNDDOWN(BY44,-1))=O44,P44,"")&IF((BY44-ROUNDDOWN(BY44,-1))=Q44,R44,"")&IF((BY44-ROUNDDOWN(BY44,-1))=S44,T44,""),IF(BY44>=20,"twenty "&IF((BY44-ROUNDDOWN(BY44,-1))=1,D44,"")&IF((BY44-ROUNDDOWN(BY44,-1))=2,F44,"")&IF((BY44-ROUNDDOWN(BY44,-1))=G44,H44,"")&IF((BY44-ROUNDDOWN(BY44,-1))=I44,J44,"")&IF((BY44-ROUNDDOWN(BY44,-1))=K44,L44,"")&IF((BY44-ROUNDDOWN(BY44,-1))=M44,N44,"")&IF((BY44-ROUNDDOWN(BY44,-1))=O44,P44,"")&IF((BY44-ROUNDDOWN(BY44,-1))=Q44,R44,"")&IF((BY44-ROUNDDOWN(BY44,-1))=S44,T44,""),"")))) | BW44: =IF(BY44="","",IF(BY44=C44,D44,"")&IF(BY44=E44,F44,"")&IF(BY44=G44,H44,"")&IF(BY44=I44,J44,"")&IF(BY44=K44,L44,"")&IF(BY44=M44,N44,"")&IF(BY44=O44,P44,"")&IF(BY44=Q44,R44,"")&IF(BY44=S44,T44,"")&IF(BY44=U44,V44,"")&IF(BY44=W44,X44,"")&IF(BY44=Y44,Z44,"")&IF(BY44=AA44,AB44,"")&IF(BY44=AC44,AD44,"")&IF(BY44=AE44,AF44,"")&IF(BY44=AG44,AH44,"")&IF(BY44=AI44,AJ44,"")&IF(BY44=AK44,AL44,"")&IF(BY44=AM44,AN44,"")) -> two | BY44: =IF(A44>=100,ROUNDDOWN((A44-ROUNDDOWN(A44,-3))/100,0),"") -> 2 | BZ44: =IF(BS44="","",BS44)&IF(BT44="","",BT44)&IF(BU44="","",BU44)&IF(BV44="","",BV44)&IF(BW44="","",BW44) -> two | CA44: TENS | CB44: =IF(CH44="","",IF(CH44>=90,"ninety "&IF((CH44-ROUNDDOWN(CH44,-1))=1,D44,"")&IF((CH44-ROUNDDOWN(CH44,-1))=2,F44,"")&IF((CH44-ROUNDDOWN(CH44,-1))=G44,H44,"")&IF((CH44-ROUNDDOWN(CH44,-1))=I44,J44,"")&IF((CH44-ROUNDDOWN(CH44,-1))=K44,L44,"")&IF((CH44-ROUNDDOWN(CH44,-1))=M44,N44,"")&IF((CH44-ROUNDDOWN(CH44,-1))=O44,P44,"")&IF((CH44-ROUNDDOWN(CH44,-1))=Q44,R44,"")&IF((CH44-ROUNDDOWN(CH44,-1))=S44,T44,""),IF(CH44>=80,"eighty "&IF((CH44-ROUNDDOWN(CH44,-1))=1,D44,"")&IF((CH44-ROUNDDOWN(CH44,-1))=2,F44,"")&IF((CH44-ROUNDDOWN(CH44,-1))=G44,H44,"")&IF((CH44-ROUNDDOWN(CH44,-1))=I44,J44,"")&IF((CH44-ROUNDDOWN(CH44,-1))=K44,L44,"")&IF((CH44-ROUNDDOWN(CH44,-1))=M44,N44,"")&IF((CH44-ROUNDDOWN(CH44,-1))=O44,P44,"")&IF((CH44-ROUNDDOWN(CH44,-1))=Q44,R44,"")&IF((CH44-ROUNDDOWN(CH44,-1))=S44,T44,""),""))) | CC44: =IF(CH44="","",IF(CH44>79,"",IF(CH44>=70,"seventy "&IF((CH44-ROUNDDOWN(CH44,-1))=1,D44,"")&IF((CH44-ROUNDDOWN(CH44,-1))=2,F44,"")&IF((CH44-ROUNDDOWN(CH44,-1))=G44,H44,"")&IF((CH44-ROUNDDOWN(CH44,-1))=I44,J44,"")&IF((CH44-ROUNDDOWN(CH44,-1))=K44,L44,"")&IF((CH44-ROUNDDOWN(CH44,-1))=M44,N44,"")&IF((CH44-ROUNDDOWN(CH44,-1))=O44,P44,"")&IF((CH44-ROUNDDOWN(CH44,-1))=Q44,R44,"")&IF((CH44-ROUNDDOWN(CH44,-1))=S44,T44,""),IF(CH44>=60,"sixty "&IF((CH44-ROUNDDOWN(CH44,-1))=1,D44,"")&IF((CH44-ROUNDDOWN(CH44,-1))=2,F44,"")&IF((CH44-ROUNDDOWN(CH44,-1))=G44,H44,"")&IF((CH44-ROUNDDOWN(CH44,-1))=I44,J44,"")&IF((CH44-ROUNDDOWN(CH44,-1))=K44,L44,"")&IF((CH44-ROUNDDOWN(CH44,-1))=M44,N44,"")&IF((CH44-ROUNDDOWN(CH44,-1))=O44,P44,"")&IF((CH44-ROUNDDOWN(CH44,-1))=Q44,R44,"")&IF((CH44-ROUNDDOWN(CH44,-1))=S44,T44,""),"")))) -> seventy | CD44: =IF(CH44="","",IF(CH44>59,"",IF(CH44>=50,"fifty "&IF((CH44-ROUNDDOWN(CH44,-1))=1,D44,"")&IF((CH44-ROUNDDOWN(CH44,-1))=2,F44,"")&IF((CH44-ROUNDDOWN(CH44,-1))=G44,H44,"")&IF((CH44-ROUNDDOWN(CH44,-1))=I44,J44,"")&IF((CH44-ROUNDDOWN(CH44,-1))=K44,L44,"")&IF((CH44-ROUNDDOWN(CH44,-1))=M44,N44,"")&IF((CH44-ROUNDDOWN(CH44,-1))=O44,P44,"")&IF((CH44-ROUNDDOWN(CH44,-1))=Q44,R44,"")&IF((CH44-ROUNDDOWN(CH44,-1))=S44,T44,""),IF(CH44>=40,"forty "&IF((CH44-ROUNDDOWN(CH44,-1))=1,D44,"")&IF((CH44-ROUNDDOWN(CH44,-1))=2,F44,"")&IF((CH44-ROUNDDOWN(CH44,-1))=G44,H44,"")&IF((CH44-ROUNDDOWN(CH44,-1))=I44,J44,"")&IF((CH44-ROUNDDOWN(CH44,-1))=K44,L44,"")&IF((CH44-ROUNDDOWN(CH44,-1))=M44,N44,"")&IF((CH44-ROUNDDOWN(CH44,-1))=O44,P44,"")&IF((CH44-ROUNDDOWN(CH44,-1))=Q44,R44,"")&IF((CH44-ROUNDDOWN(CH44,-1))=S44,T44,""),"")))) | CE44: =IF(CH44="","",IF(CH44>39,"",IF(CH44>=30,"thirty "&IF((CH44-ROUNDDOWN(CH44,-1))=1,D44,"")&IF((CH44-ROUNDDOWN(CH44,-1))=2,F44,"")&IF((CH44-ROUNDDOWN(CH44,-1))=G44,H44,"")&IF((CH44-ROUNDDOWN(CH44,-1))=I44,J44,"")&IF((CH44-ROUNDDOWN(CH44,-1))=K44,L44,"")&IF((CH44-ROUNDDOWN(CH44,-1))=M44,N44,"")&IF((CH44-ROUNDDOWN(CH44,-1))=O44,P44,"")&IF((CH44-ROUNDDOWN(CH44,-1))=Q44,R44,"")&IF((CH44-ROUNDDOWN(CH44,-1))=S44,T44,""),IF(CH44>=20,"twenty "&IF((CH44-ROUNDDOWN(CH44,-1))=1,D44,"")&IF((CH44-ROUNDDOWN(CH44,-1))=2,F44,"")&IF((CH44-ROUNDDOWN(CH44,-1))=G44,H44,"")&IF((CH44-ROUNDDOWN(CH44,-1))=I44,J44,"")&IF((CH44-ROUNDDOWN(CH44,-1))=K44,L44,"")&IF((CH44-ROUNDDOWN(CH44,-1))=M44,N44,"")&IF((CH44-ROUNDDOWN(CH44,-1))=O44,P44,"")&IF((CH44-ROUNDDOWN(CH44,-1))=Q44,R44,"")&IF((CH44-ROUNDDOWN(CH44,-1))=S44,T44,""),"")))) | CF44: =IF(CH44="","",IF(CH44=C44,D44,"")&IF(CH44=E44,F44,"")&IF(CH44=G44,H44,"")&IF(CH44=I44,J44,"")&IF(CH44=K44,L44,"")&IF(CH44=M44,N44,"")&IF(CH44=O44,P44,"")&IF(CH44=Q44,R44,"")&IF(CH44=S44,T44,"")&IF(CH44=U44,V44,"")&IF(CH44=W44,X44,"")&IF(CH44=Y44,Z44,"")&IF(CH44=AA44,AB44,"")&IF(CH44=AC44,AD44,"")&IF(CH44=AE44,AF44,"")&IF(CH44=AG44,AH44,"")&IF(CH44=AI44,AJ44,"")&IF(CH44=AK44,AL44,"")&IF(CH44=AM44,AN44,"")) | CH44: =IF(A44>=1,ROUNDDOWN(A44-ROUNDDOWN(A44,-2),0),"") -> 70 | CI44: =IF(CB44="","",CB44)&IF(CC44="","",CC44)&IF(CD44="","",CD44)&IF(CE44="","",CE44)&IF(CF44="","",CF44) -> seventy | CJ44: PAISE | CK44: =IF(CQ44="","",IF(CQ44>=90,"ninety "&IF((CQ44-ROUNDDOWN(CQ44,-1))=1,D44,"")&IF((CQ44-ROUNDDOWN(CQ44,-1))=2,F44,"")&IF((CQ44-ROUNDDOWN(CQ44,-1))=G44,H44,"")&IF((CQ44-ROUNDDOWN(CQ44,-1))=I44,J44,"")&IF((CQ44-ROUNDDOWN(CQ44,-1))=K44,L44,"")&IF((CQ44-ROUNDDOWN(CQ44,-1))=M44,N44,"")&IF((CQ44-ROUNDDOWN(CQ44,-1))=O44,P44,"")&IF((CQ44-ROUNDDOWN(CQ44,-1))=Q44,R44,"")&IF((CQ44-ROUNDDOWN(CQ44,-1))=S44,T44,""),IF(CQ44>=80,"eighty "&IF((CQ44-ROUNDDOWN(CQ44,-1))=1,D44,"")&IF((CQ44-ROUNDDOWN(CQ44,-1))=2,F44,"")&IF((CQ44-ROUNDDOWN(CQ44,-1))=G44,H44,"")&IF((CQ44-ROUNDDOWN(CQ44,-1))=I44,J44,"")&IF((CQ44-ROUNDDOWN(CQ44,-1))=K44,L44,"")&IF((CQ44-ROUNDDOWN(CQ44,-1))=M44,N44,"")&IF((CQ44-ROUNDDOWN(CQ44,-1))=O44,P44,"")&IF((CQ44-ROUNDDOWN(CQ44,-1))=Q44,R44,"")&IF((CQ44-ROUNDDOWN(CQ44,-1))=S44,T44,""),""))) | CL44: =IF(CQ44="","",IF(CQ44>79,"",IF(CQ44>=70,"seventy "&IF((CQ44-ROUNDDOWN(CQ44,-1))=1,D44,"")&IF((CQ44-ROUNDDOWN(CQ44,-1))=2,F44,"")&IF((CQ44-ROUNDDOWN(CQ44,-1))=G44,H44,"")&IF((CQ44-ROUNDDOWN(CQ44,-1))=I44,J44,"")&IF((CQ44-ROUNDDOWN(CQ44,-1))=K44,L44,"")&IF((CQ44-ROUNDDOWN(CQ44,-1))=M44,N44,"")&IF((CQ44-ROUNDDOWN(CQ44,-1))=O44,P44,"")&IF((CQ44-ROUNDDOWN(CQ44,-1))=Q44,R44,"")&IF((CQ44-ROUNDDOWN(CQ44,-1))=S44,T44,""),IF(CQ44>=60,"sixty "&IF((CQ44-ROUNDDOWN(CQ44,-1))=1,D44,"")&IF((CQ44-ROUNDDOWN(CQ44,-1))=2,F44,"")&IF((CQ44-ROUNDDOWN(CQ44,-1))=G44,H44,"")&IF((CQ44-ROUNDDOWN(CQ44,-1))=I44,J44,"")&IF((CQ44-ROUNDDOWN(CQ44,-1))=K44,L44,"")&IF((CQ44-ROUNDDOWN(CQ44,-1))=M44,N44,"")&IF((CQ44-ROUNDDOWN(CQ44,-1))=O44,P44,"")&IF((CQ44-ROUNDDOWN(CQ44,-1))=Q44,R44,"")&IF((CQ44-ROUNDDOWN(CQ44,-1))=S44,T44,""),"")))) | CM44: =IF(CQ44="","",IF(CQ44>59,"",IF(CQ44>=50,"fifty "&IF((CQ44-ROUNDDOWN(CQ44,-1))=1,D44,"")&IF((CQ44-ROUNDDOWN(CQ44,-1))=2,F44,"")&IF((CQ44-ROUNDDOWN(CQ44,-1))=G44,H44,"")&IF((CQ44-ROUNDDOWN(CQ44,-1))=I44,J44,"")&IF((CQ44-ROUNDDOWN(CQ44,-1))=K44,L44,"")&IF((CQ44-ROUNDDOWN(CQ44,-1))=M44,N44,"")&IF((CQ44-ROUNDDOWN(CQ44,-1))=O44,P44,"")&IF((CQ44-ROUNDDOWN(CQ44,-1))=Q44,R44,"")&IF((CQ44-ROUNDDOWN(CQ44,-1))=S44,T44,""),IF(CQ44>=40,"forty "&IF((CQ44-ROUNDDOWN(CQ44,-1))=1,D44,"")&IF((CQ44-ROUNDDOWN(CQ44,-1))=2,F44,"")&IF((CQ44-ROUNDDOWN(CQ44,-1))=G44,H44,"")&IF((CQ44-ROUNDDOWN(CQ44,-1))=I44,J44,"")&IF((CQ44-ROUNDDOWN(CQ44,-1))=K44,L44,"")&IF((CQ44-ROUNDDOWN(CQ44,-1))=M44,N44,"")&IF((CQ44-ROUNDDOWN(CQ44,-1))=O44,P44,"")&IF((CQ44-ROUNDDOWN(CQ44,-1))=Q44,R44,"")&IF((CQ44-ROUNDDOWN(CQ44,-1))=S44,T44,""),"")))) | CN44: =IF(CQ44="","",IF(CQ44>39,"",IF(CQ44>=30,"thirty "&IF((CQ44-ROUNDDOWN(CQ44,-1))=1,D44,"")&IF((CQ44-ROUNDDOWN(CQ44,-1))=2,F44,"")&IF((CQ44-ROUNDDOWN(CQ44,-1))=G44,H44,"")&IF((CQ44-ROUNDDOWN(CQ44,-1))=I44,J44,"")&IF((CQ44-ROUNDDOWN(CQ44,-1))=K44,L44,"")&IF((CQ44-ROUNDDOWN(CQ44,-1))=M44,N44,"")&IF((CQ44-ROUNDDOWN(CQ44,-1))=O44,P44,"")&IF((CQ44-ROUNDDOWN(CQ44,-1))=Q44,R44,"")&IF((CQ44-ROUNDDOWN(CQ44,-1))=S44,T44,""),IF(CQ44>=20,"twenty "&IF((CQ44-ROUNDDOWN(CQ44,-1))=1,D44,"")&IF((CQ44-ROUNDDOWN(CQ44,-1))=2,F44,"")&IF((CQ44-ROUNDDOWN(CQ44,-1))=G44,H44,"")&IF((CQ44-ROUNDDOWN(CQ44,-1))=I44,J44,"")&IF((CQ44-ROUNDDOWN(CQ44,-1))=K44,L44,"")&IF((CQ44-ROUNDDOWN(CQ44,-1))=M44,N44,"")&IF((CQ44-ROUNDDOWN(CQ44,-1))=O44,P44,"")&IF((CQ44-ROUNDDOWN(CQ44,-1))=Q44,R44,"")&IF((CQ44-ROUNDDOWN(CQ44,-1))=S44,T44,""),"")))) | CO44: =IF(CQ44="","",IF(CQ44=C44,D44,"")&IF(CQ44=E44,F44,"")&IF(CQ44=G44,H44,"")&IF(CQ44=I44,J44,"")&IF(CQ44=K44,L44,"")&IF(CQ44=M44,N44,"")&IF(CQ44=O44,P44,"")&IF(CQ44=Q44,R44,"")&IF(CQ44=S44,T44,"")&IF(CQ44=U44,V44,"")&IF(CQ44=W44,X44,"")&IF(CQ44=Y44,Z44,"")&IF(CQ44=AA44,AB44,"")&IF(CQ44=AC44,AD44,"")&IF(CQ44=AE44,AF44,"")&IF(CQ44=AG44,AH44,"")&IF(CQ44=AI44,AJ44,"")&IF(CQ44=AK44,AL44,"")&IF(CQ44=AM44,AN44,"")) | CQ44: =IF((A44-ROUNDDOWN(A44,0))>0,ROUND((A44-ROUNDDOWN(A44,0))*100,0),"") | CR44: =IF(CK44="","",CK44)&IF(CL44="","",CL44)&IF(CM44="","",CM44)&IF(CN44="","",CN44)&IF(CO44="","",CO44) | CS44: <= IN WORDS | CU44: =IF(A44="","","(Rupees "&IF(AY44="","",AY44&" crore ")&IF(BH44="","",BH44&" lakh ")&IF(BQ44="","",BQ44&" thousand ")&IF(BZ44="","",BZ44&" hundred ")&IF(CI44="","",CI44)&IF(CR44="",""," and paise "&CR44)&") only.") -> (Rupees one lakh forty eight thousand two hundred seventy ) only.

Sheet furniture
A1: {='Rennovation BOQ'!A1:A1} -> Name of Work :- Repairing and Renovation of Circuit House at Bokakhat Co District under Golaghat District
A2: FURNITURE WORK
A4: SL NO | B4: ITEM NAME | C4: QTY | D4: UNIT | E4: UNIT PRICE(RS) | F4: TOTAL PRICE
A5: F1 | B5: **Supply, Fitting & Fixing of SINGLE WOODEN BED WITHOUT STORAGE** of following specification: Overall size approximately 1800–1850 mm (L) × 900–1050 mm (W) × 550–600 mm (H), with bed frame made of good quality engineered wood/particle board of approved make and finish, including headboard and footboard, suitable mattress support arrangement, necessary screws, fasteners, connectors, brackets, joining hardware and other accessories required for proper assembly and fixing, all exposed surfaces having smooth, durable and aesthetically appealing factory finish, complete in all respects as per approved sample, manufacturer's specifications and as directed by the Engineer-in-Charge. | C5: 15 | D5: each | E5: ='Furniture analysis'!H18 -> 9359.37 | F5: =C5*E5 -> 140390.55
A6: F2 | B6: Supply, Fitting & Fixing of SINGLE BED MATTRESS of following specification: Overall size 1900 mm (L) × 900 mm (W) × 75–125 mm thickness, conforming to IS 13489 (V3), Type-2 bed mattress with pocket-spring construction, cushioning/core layer of flexible polyurethane foam sheet, single core layer, quilted multi-layer foam mattress case with top quilting of Jacquard weave fabric of minimum 130 GSM, in red colour, including all necessary materials, workmanship, finishing and accessories, complete in all respects as per approved sample and manufacturer's specifications and as directed by the Engineer-in-Charge. Make: KURL-ON or approved equivalent. | C6: 15 | D6: each | E6: ='Furniture analysis'!H36 -> 6638.04 | F6: =C6*E6 -> 99570.6
A7: F3 | B7: Supply, Fitting & Fixing of HANDCRAFTED DINING TABLE SET of following specification: Rectangular dining table of overall size approximately 1.83 m (L) × 0.91 m (D) × 0.76 m (H), with table top and base made of Sheesham wood, brown colour finish, whole unit handcrafted, non-foldable, without storage and wheels, including 6 Nos. of matching dining chairs, complete assembly at consignee's premises/site at no extra cost, including all necessary fittings, hardware, accessories and workmanship, complete in all respects as per approved sample, manufacturer's specifications and as directed by the Engineer-in-Charge. | C7: 2 | D7: each | E7: ='Furniture analysis'!H54 -> 70278.18 | F7: =C7*E7 -> 140556.36
A8: F4 | B8: bombay dyeing Bedsheet - Size 255 centimeter x 230 centimeter | C8: =2*C5 -> 30 | D8: each | E8: ='Furniture analysis'!H69 -> 621.99 | F8: =C8*E8 -> 18659.7
A9: F5 | B9: PUREREST Cotton Pillow 33 cm x 56 cm | C9: =2*C6 -> 30 | D9: each | E9: ='Furniture analysis'!H87 -> 604.21 | F9: =C9*E9 -> 18126.3
A10: F6 | B10: BANDHARA Cotton Oxford Pillow Covers-Hand icraft, Size Single | C10: =C9 -> 30 | D10: each | E10: ='Furniture analysis'!H105 -> 264.2 | F10: =C10*E10 -> 7926
A11: F7 | B11: Borosil Ceramic Dinner Set Borosil (LARAH 3N BIRTHDAY SET) | C11: 10 | D11: each | E11: ='Furniture analysis'!H125 -> 354.21 | F11: =C11*E11 -> 3542.1
A12: Total = | F12: =ROUND(SUM(F5:F11),0) -> 428772
A13: SAY= | F13: =F12 -> 428772
B14: =CU20 -> (Rupees four lakh twenty eight thousand seven hundred seventy two) only.
A20: =F13 -> 428772 | B20: COPY CELLS=> | C20: 1 | D20: one | E20: 2 | F20: two | G20: 3 | H20: three | I20: 4 | J20: four | K20: 5 | L20: five | M20: 6 | N20: six | O20: 7 | P20: seven | Q20: 8 | R20: eight | S20: 9 | T20: nine | U20: 10 | V20: ten | W20: 11 | X20: eleven | Y20: 12 | Z20: twelve | AA20: 13 | AB20: thirteen | AC20: 14 | AD20: fourteen | AE20: 15 | AF20: fifteen | AG20: 16 | AH20: sixteen | AI20: 17 | AJ20: seventeen | AK20: 18 | AL20: eighteen | AM20: 19 | AN20: nineteen | AO20: <=COPY CELLS | AP20: WORDS-> | AQ20: CRORE | AR20: =IF(AX20="","",IF(AX20>=90,"ninety "&IF((AX20-ROUNDDOWN(AX20,-1))=C20,D20,"")&IF((AX20-ROUNDDOWN(AX20,-1))=E20,F20,"")&IF((AX20-ROUNDDOWN(AX20,-1))=G20,H20,"")&IF((AX20-ROUNDDOWN(AX20,-1))=I20,J20,"")&IF((AX20-ROUNDDOWN(AX20,-1))=K20,L20,"")&IF((AX20-ROUNDDOWN(AX20,-1))=M20,N20,"")&IF((AX20-ROUNDDOWN(AX20,-1))=O20,P20,"")&IF((AX20-ROUNDDOWN(AX20,-1))=Q20,R20,"")&IF((AX20-ROUNDDOWN(AX20,-1))=S20,T20,""),IF(AX20>=80,"eighty "&IF((AX20-ROUNDDOWN(AX20,-1))=1,D20,"")&IF((AX20-ROUNDDOWN(AX20,-1))=2,F20,"")&IF((AX20-ROUNDDOWN(AX20,-1))=G20,H20,"")&IF((AX20-ROUNDDOWN(AX20,-1))=I20,J20,"")&IF((AX20-ROUNDDOWN(AX20,-1))=K20,L20,"")&IF((AX20-ROUNDDOWN(AX20,-1))=M20,N20,"")&IF((AX20-ROUNDDOWN(AX20,-1))=O20,P20,"")&IF((AX20-ROUNDDOWN(AX20,-1))=Q20,R20,"")&IF((AX20-ROUNDDOWN(AX20,-1))=S20,T20,""),""))) | AS20: =IF(AX20="","",IF(AX20>79,"",IF(AX20>=70,"seventy "&IF((AX20-ROUNDDOWN(AX20,-1))=C20,D20,"")&IF((AX20-ROUNDDOWN(AX20,-1))=E20,F20,"")&IF((AX20-ROUNDDOWN(AX20,-1))=G20,H20,"")&IF((AX20-ROUNDDOWN(AX20,-1))=I20,J20,"")&IF((AX20-ROUNDDOWN(AX20,-1))=K20,L20,"")&IF((AX20-ROUNDDOWN(AX20,-1))=M20,N20,"")&IF((AX20-ROUNDDOWN(AX20,-1))=O20,P20,"")&IF((AX20-ROUNDDOWN(AX20,-1))=Q20,R20,"")&IF((AX20-ROUNDDOWN(AX20,-1))=S20,T20,""),IF(AX20>=60,"sixty "&IF((AX20-ROUNDDOWN(AX20,-1))=1,D20,"")&IF((AX20-ROUNDDOWN(AX20,-1))=2,F20,"")&IF((AX20-ROUNDDOWN(AX20,-1))=G20,H20,"")&IF((AX20-ROUNDDOWN(AX20,-1))=I20,J20,"")&IF((AX20-ROUNDDOWN(AX20,-1))=K20,L20,"")&IF((AX20-ROUNDDOWN(AX20,-1))=M20,N20,"")&IF((AX20-ROUNDDOWN(AX20,-1))=O20,P20,"")&IF((AX20-ROUNDDOWN(AX20,-1))=Q20,R20,"")&IF((AX20-ROUNDDOWN(AX20,-1))=S20,T20,""),"")))) | AT20: =IF(AX20="","",IF(AX20>59,"",IF(AX20>=50,"fifty "&IF((AX20-ROUNDDOWN(AX20,-1))=C20,D20,"")&IF((AX20-ROUNDDOWN(AX20,-1))=E20,F20,"")&IF((AX20-ROUNDDOWN(AX20,-1))=G20,H20,"")&IF((AX20-ROUNDDOWN(AX20,-1))=I20,J20,"")&IF((AX20-ROUNDDOWN(AX20,-1))=K20,L20,"")&IF((AX20-ROUNDDOWN(AX20,-1))=M20,N20,"")&IF((AX20-ROUNDDOWN(AX20,-1))=O20,P20,"")&IF((AX20-ROUNDDOWN(AX20,-1))=Q20,R20,"")&IF((AX20-ROUNDDOWN(AX20,-1))=S20,T20,""),IF(AX20>=40,"forty "&IF((AX20-ROUNDDOWN(AX20,-1))=1,D20,"")&IF((AX20-ROUNDDOWN(AX20,-1))=2,F20,"")&IF((AX20-ROUNDDOWN(AX20,-1))=G20,H20,"")&IF((AX20-ROUNDDOWN(AX20,-1))=I20,J20,"")&IF((AX20-ROUNDDOWN(AX20,-1))=K20,L20,"")&IF((AX20-ROUNDDOWN(AX20,-1))=M20,N20,"")&IF((AX20-ROUNDDOWN(AX20,-1))=O20,P20,"")&IF((AX20-ROUNDDOWN(AX20,-1))=Q20,R20,"")&IF((AX20-ROUNDDOWN(AX20,-1))=S20,T20,""),"")))) | AU20: =IF(AX20="","",IF(AX20>39,"",IF(AX20>=30,"thirty "&IF((AX20-ROUNDDOWN(AX20,-1))=C20,D20,"")&IF((AX20-ROUNDDOWN(AX20,-1))=E20,F20,"")&IF((AX20-ROUNDDOWN(AX20,-1))=G20,H20,"")&IF((AX20-ROUNDDOWN(AX20,-1))=I20,J20,"")&IF((AX20-ROUNDDOWN(AX20,-1))=K20,L20,"")&IF((AX20-ROUNDDOWN(AX20,-1))=M20,N20,"")&IF((AX20-ROUNDDOWN(AX20,-1))=O20,P20,"")&IF((AX20-ROUNDDOWN(AX20,-1))=Q20,R20,"")&IF((AX20-ROUNDDOWN(AX20,-1))=S20,T20,""),IF(AX20>=20,"twenty "&IF((AX20-ROUNDDOWN(AX20,-1))=1,D20,"")&IF((AX20-ROUNDDOWN(AX20,-1))=2,F20,"")&IF((AX20-ROUNDDOWN(AX20,-1))=G20,H20,"")&IF((AX20-ROUNDDOWN(AX20,-1))=I20,J20,"")&IF((AX20-ROUNDDOWN(AX20,-1))=K20,L20,"")&IF((AX20-ROUNDDOWN(AX20,-1))=M20,N20,"")&IF((AX20-ROUNDDOWN(AX20,-1))=O20,P20,"")&IF((AX20-ROUNDDOWN(AX20,-1))=Q20,R20,"")&IF((AX20-ROUNDDOWN(AX20,-1))=S20,T20,""),"")))) | AV20: =IF(AX20="","",IF(AX20=C20,D20,"")&IF(AX20=E20,F20,"")&IF(AX20=G20,H20,"")&IF(AX20=I20,J20,"")&IF(AX20=K20,L20,"")&IF(AX20=M20,N20,"")&IF(AX20=O20,P20,"")&IF(AX20=Q20,R20,"")&IF(AX20=S20,T20,"")&IF(AX20=U20,V20,"")&IF(AX20=W20,X20,"")&IF(AX20=Y20,Z20,"")&IF(AX20=AA20,AB20,"")&IF(AX20=AC20,AD20,"")&IF(AX20=AE20,AF20,"")&IF(AX20=AG20,AH20,"")&IF(AX20=AI20,AJ20,"")&IF(AX20=AK20,AL20,"")&IF(AX20=AM20,AN20,"")) | AX20: =IF(A20>=10000000,ROUNDDOWN(A20,-7)/10000000,"") | AY20: =IF(AR20="","",AR20)&IF(AS20="","",AS20)&IF(AT20="","",AT20)&IF(AU20="","",AU20)&IF(AV20="","",AV20) | AZ20: LAKH | BA20: =IF(BG20="","",IF(BG20>=90,"ninety "&IF((BG20-ROUNDDOWN(BG20,-1))=C20,D20,"")&IF((BG20-ROUNDDOWN(BG20,-1))=E20,F20,"")&IF((BG20-ROUNDDOWN(BG20,-1))=G20,H20,"")&IF((BG20-ROUNDDOWN(BG20,-1))=I20,J20,"")&IF((BG20-ROUNDDOWN(BG20,-1))=K20,L20,"")&IF((BG20-ROUNDDOWN(BG20,-1))=M20,N20,"")&IF((BG20-ROUNDDOWN(BG20,-1))=O20,P20,"")&IF((BG20-ROUNDDOWN(BG20,-1))=Q20,R20,"")&IF((BG20-ROUNDDOWN(BG20,-1))=S20,T20,""),IF(BG20>=80,"eighty "&IF((BG20-ROUNDDOWN(BG20,-1))=1,D20,"")&IF((BG20-ROUNDDOWN(BG20,-1))=2,F20,"")&IF((BG20-ROUNDDOWN(BG20,-1))=G20,H20,"")&IF((BG20-ROUNDDOWN(BG20,-1))=I20,J20,"")&IF((BG20-ROUNDDOWN(BG20,-1))=K20,L20,"")&IF((BG20-ROUNDDOWN(BG20,-1))=M20,N20,"")&IF((BG20-ROUNDDOWN(BG20,-1))=O20,P20,"")&IF((BG20-ROUNDDOWN(BG20,-1))=Q20,R20,"")&IF((BG20-ROUNDDOWN(BG20,-1))=S20,T20,""),""))) | BB20: =IF(BG20="","",IF(BG20>79,"",IF(BG20>=70,"seventy "&IF((BG20-ROUNDDOWN(BG20,-1))=C20,D20,"")&IF((BG20-ROUNDDOWN(BG20,-1))=E20,F20,"")&IF((BG20-ROUNDDOWN(BG20,-1))=G20,H20,"")&IF((BG20-ROUNDDOWN(BG20,-1))=I20,J20,"")&IF((BG20-ROUNDDOWN(BG20,-1))=K20,L20,"")&IF((BG20-ROUNDDOWN(BG20,-1))=M20,N20,"")&IF((BG20-ROUNDDOWN(BG20,-1))=O20,P20,"")&IF((BG20-ROUNDDOWN(BG20,-1))=Q20,R20,"")&IF((BG20-ROUNDDOWN(BG20,-1))=S20,T20,""),IF(BG20>=60,"sixty "&IF((BG20-ROUNDDOWN(BG20,-1))=1,D20,"")&IF((BG20-ROUNDDOWN(BG20,-1))=2,F20,"")&IF((BG20-ROUNDDOWN(BG20,-1))=G20,H20,"")&IF((BG20-ROUNDDOWN(BG20,-1))=I20,J20,"")&IF((BG20-ROUNDDOWN(BG20,-1))=K20,L20,"")&IF((BG20-ROUNDDOWN(BG20,-1))=M20,N20,"")&IF((BG20-ROUNDDOWN(BG20,-1))=O20,P20,"")&IF((BG20-ROUNDDOWN(BG20,-1))=Q20,R20,"")&IF((BG20-ROUNDDOWN(BG20,-1))=S20,T20,""),"")))) | BC20: =IF(BG20="","",IF(BG20>59,"",IF(BG20>=50,"fifty "&IF((BG20-ROUNDDOWN(BG20,-1))=C20,D20,"")&IF((BG20-ROUNDDOWN(BG20,-1))=E20,F20,"")&IF((BG20-ROUNDDOWN(BG20,-1))=G20,H20,"")&IF((BG20-ROUNDDOWN(BG20,-1))=I20,J20,"")&IF((BG20-ROUNDDOWN(BG20,-1))=K20,L20,"")&IF((BG20-ROUNDDOWN(BG20,-1))=M20,N20,"")&IF((BG20-ROUNDDOWN(BG20,-1))=O20,P20,"")&IF((BG20-ROUNDDOWN(BG20,-1))=Q20,R20,"")&IF((BG20-ROUNDDOWN(BG20,-1))=S20,T20,""),IF(BG20>=40,"forty "&IF((BG20-ROUNDDOWN(BG20,-1))=1,D20,"")&IF((BG20-ROUNDDOWN(BG20,-1))=2,F20,"")&IF((BG20-ROUNDDOWN(BG20,-1))=G20,H20,"")&IF((BG20-ROUNDDOWN(BG20,-1))=I20,J20,"")&IF((BG20-ROUNDDOWN(BG20,-1))=K20,L20,"")&IF((BG20-ROUNDDOWN(BG20,-1))=M20,N20,"")&IF((BG20-ROUNDDOWN(BG20,-1))=O20,P20,"")&IF((BG20-ROUNDDOWN(BG20,-1))=Q20,R20,"")&IF((BG20-ROUNDDOWN(BG20,-1))=S20,T20,""),"")))) | BD20: =IF(BG20="","",IF(BG20>39,"",IF(BG20>=30,"thirty "&IF((BG20-ROUNDDOWN(BG20,-1))=C20,D20,"")&IF((BG20-ROUNDDOWN(BG20,-1))=E20,F20,"")&IF((BG20-ROUNDDOWN(BG20,-1))=G20,H20,"")&IF((BG20-ROUNDDOWN(BG20,-1))=I20,J20,"")&IF((BG20-ROUNDDOWN(BG20,-1))=K20,L20,"")&IF((BG20-ROUNDDOWN(BG20,-1))=M20,N20,"")&IF((BG20-ROUNDDOWN(BG20,-1))=O20,P20,"")&IF((BG20-ROUNDDOWN(BG20,-1))=Q20,R20,"")&IF((BG20-ROUNDDOWN(BG20,-1))=S20,T20,""),IF(BG20>=20,"twenty "&IF((BG20-ROUNDDOWN(BG20,-1))=1,D20,"")&IF((BG20-ROUNDDOWN(BG20,-1))=2,F20,"")&IF((BG20-ROUNDDOWN(BG20,-1))=G20,H20,"")&IF((BG20-ROUNDDOWN(BG20,-1))=I20,J20,"")&IF((BG20-ROUNDDOWN(BG20,-1))=K20,L20,"")&IF((BG20-ROUNDDOWN(BG20,-1))=M20,N20,"")&IF((BG20-ROUNDDOWN(BG20,-1))=O20,P20,"")&IF((BG20-ROUNDDOWN(BG20,-1))=Q20,R20,"")&IF((BG20-ROUNDDOWN(BG20,-1))=S20,T20,""),"")))) | BE20: =IF(BG20="","",IF(BG20=C20,D20,"")&IF(BG20=E20,F20,"")&IF(BG20=G20,H20,"")&IF(BG20=I20,J20,"")&IF(BG20=K20,L20,"")&IF(BG20=M20,N20,"")&IF(BG20=O20,P20,"")&IF(BG20=Q20,R20,"")&IF(BG20=S20,T20,"")&IF(BG20=U20,V20,"")&IF(BG20=W20,X20,"")&IF(BG20=Y20,Z20,"")&IF(BG20=AA20,AB20,"")&IF(BG20=AC20,AD20,"")&IF(BG20=AE20,AF20,"")&IF(BG20=AG20,AH20,"")&IF(BG20=AI20,AJ20,"")&IF(BG20=AK20,AL20,"")&IF(BG20=AM20,AN20,"")) -> four | BG20: =IF(A20>=100000,ROUNDDOWN((ROUND(A20,-4)-ROUNDDOWN(A20,-7))/100000,0),"") -> 4 | BH20: =IF(BA20="","",BA20)&IF(BB20="","",BB20)&IF(BC20="","",BC20)&IF(BD20="","",BD20)&IF(BE20="","",BE20) -> four | BI20: THOUSAND | BJ20: =IF(BP20="","",IF(BP20>=90,"ninety "&IF((BP20-ROUNDDOWN(BP20,-1))=1,D20,"")&IF((BP20-ROUNDDOWN(BP20,-1))=2,F20,"")&IF((BP20-ROUNDDOWN(BP20,-1))=G20,H20,"")&IF((BP20-ROUNDDOWN(BP20,-1))=I20,J20,"")&IF((BP20-ROUNDDOWN(BP20,-1))=K20,L20,"")&IF((BP20-ROUNDDOWN(BP20,-1))=M20,N20,"")&IF((BP20-ROUNDDOWN(BP20,-1))=O20,P20,"")&IF((BP20-ROUNDDOWN(BP20,-1))=Q20,R20,"")&IF((BP20-ROUNDDOWN(BP20,-1))=S20,T20,""),IF(BP20>=80,"eighty "&IF((BP20-ROUNDDOWN(BP20,-1))=1,D20,"")&IF((BP20-ROUNDDOWN(BP20,-1))=2,F20,"")&IF((BP20-ROUNDDOWN(BP20,-1))=G20,H20,"")&IF((BP20-ROUNDDOWN(BP20,-1))=I20,J20,"")&IF((BP20-ROUNDDOWN(BP20,-1))=K20,L20,"")&IF((BP20-ROUNDDOWN(BP20,-1))=M20,N20,"")&IF((BP20-ROUNDDOWN(BP20,-1))=O20,P20,"")&IF((BP20-ROUNDDOWN(BP20,-1))=Q20,R20,"")&IF((BP20-ROUNDDOWN(BP20,-1))=S20,T20,""),""))) | BK20: =IF(BP20="","",IF(BP20>79,"",IF(BP20>=70,"seventy "&IF((BP20-ROUNDDOWN(BP20,-1))=1,D20,"")&IF((BP20-ROUNDDOWN(BP20,-1))=2,F20,"")&IF((BP20-ROUNDDOWN(BP20,-1))=G20,H20,"")&IF((BP20-ROUNDDOWN(BP20,-1))=I20,J20,"")&IF((BP20-ROUNDDOWN(BP20,-1))=K20,L20,"")&IF((BP20-ROUNDDOWN(BP20,-1))=M20,N20,"")&IF((BP20-ROUNDDOWN(BP20,-1))=O20,P20,"")&IF((BP20-ROUNDDOWN(BP20,-1))=Q20,R20,"")&IF((BP20-ROUNDDOWN(BP20,-1))=S20,T20,""),IF(BP20>=60,"sixty "&IF((BP20-ROUNDDOWN(BP20,-1))=1,D20,"")&IF((BP20-ROUNDDOWN(BP20,-1))=2,F20,"")&IF((BP20-ROUNDDOWN(BP20,-1))=G20,H20,"")&IF((BP20-ROUNDDOWN(BP20,-1))=I20,J20,"")&IF((BP20-ROUNDDOWN(BP20,-1))=K20,L20,"")&IF((BP20-ROUNDDOWN(BP20,-1))=M20,N20,"")&IF((BP20-ROUNDDOWN(BP20,-1))=O20,P20,"")&IF((BP20-ROUNDDOWN(BP20,-1))=Q20,R20,"")&IF((BP20-ROUNDDOWN(BP20,-1))=S20,T20,""),"")))) | BL20: =IF(BP20="","",IF(BP20>59,"",IF(BP20>=50,"fifty "&IF((BP20-ROUNDDOWN(BP20,-1))=1,D20,"")&IF((BP20-ROUNDDOWN(BP20,-1))=2,F20,"")&IF((BP20-ROUNDDOWN(BP20,-1))=G20,H20,"")&IF((BP20-ROUNDDOWN(BP20,-1))=I20,J20,"")&IF((BP20-ROUNDDOWN(BP20,-1))=K20,L20,"")&IF((BP20-ROUNDDOWN(BP20,-1))=M20,N20,"")&IF((BP20-ROUNDDOWN(BP20,-1))=O20,P20,"")&IF((BP20-ROUNDDOWN(BP20,-1))=Q20,R20,"")&IF((BP20-ROUNDDOWN(BP20,-1))=S20,T20,""),IF(BP20>=40,"forty "&IF((BP20-ROUNDDOWN(BP20,-1))=1,D20,"")&IF((BP20-ROUNDDOWN(BP20,-1))=2,F20,"")&IF((BP20-ROUNDDOWN(BP20,-1))=G20,H20,"")&IF((BP20-ROUNDDOWN(BP20,-1))=I20,J20,"")&IF((BP20-ROUNDDOWN(BP20,-1))=K20,L20,"")&IF((BP20-ROUNDDOWN(BP20,-1))=M20,N20,"")&IF((BP20-ROUNDDOWN(BP20,-1))=O20,P20,"")&IF((BP20-ROUNDDOWN(BP20,-1))=Q20,R20,"")&IF((BP20-ROUNDDOWN(BP20,-1))=S20,T20,""),"")))) | BM20: =IF(BP20="","",IF(BP20>39,"",IF(BP20>=30,"thirty "&IF((BP20-ROUNDDOWN(BP20,-1))=1,D20,"")&IF((BP20-ROUNDDOWN(BP20,-1))=2,F20,"")&IF((BP20-ROUNDDOWN(BP20,-1))=G20,H20,"")&IF((BP20-ROUNDDOWN(BP20,-1))=I20,J20,"")&IF((BP20-ROUNDDOWN(BP20,-1))=K20,L20,"")&IF((BP20-ROUNDDOWN(BP20,-1))=M20,N20,"")&IF((BP20-ROUNDDOWN(BP20,-1))=O20,P20,"")&IF((BP20-ROUNDDOWN(BP20,-1))=Q20,R20,"")&IF((BP20-ROUNDDOWN(BP20,-1))=S20,T20,""),IF(BP20>=20,"twenty "&IF((BP20-ROUNDDOWN(BP20,-1))=1,D20,"")&IF((BP20-ROUNDDOWN(BP20,-1))=2,F20,"")&IF((BP20-ROUNDDOWN(BP20,-1))=G20,H20,"")&IF((BP20-ROUNDDOWN(BP20,-1))=I20,J20,"")&IF((BP20-ROUNDDOWN(BP20,-1))=K20,L20,"")&IF((BP20-ROUNDDOWN(BP20,-1))=M20,N20,"")&IF((BP20-ROUNDDOWN(BP20,-1))=O20,P20,"")&IF((BP20-ROUNDDOWN(BP20,-1))=Q20,R20,"")&IF((BP20-ROUNDDOWN(BP20,-1))=S20,T20,""),"")))) -> twenty eight | BN20: =IF(BP20="","",IF(BP20=C20,D20,"")&IF(BP20=E20,F20,"")&IF(BP20=G20,H20,"")&IF(BP20=I20,J20,"")&IF(BP20=K20,L20,"")&IF(BP20=M20,N20,"")&IF(BP20=O20,P20,"")&IF(BP20=Q20,R20,"")&IF(BP20=S20,T20,"")&IF(BP20=U20,V20,"")&IF(BP20=W20,X20,"")&IF(BP20=Y20,Z20,"")&IF(BP20=AA20,AB20,"")&IF(BP20=AC20,AD20,"")&IF(BP20=AE20,AF20,"")&IF(BP20=AG20,AH20,"")&IF(BP20=AI20,AJ20,"")&IF(BP20=AK20,AL20,"")&IF(BP20=AM20,AN20,"")) | BP20: =IF(A20>=1000,ROUNDDOWN((A20-ROUNDDOWN(A20,-5))/1000,0),"") -> 28 | BQ20: =IF(BJ20="","",BJ20)&IF(BK20="","",BK20)&IF(BL20="","",BL20)&IF(BM20="","",BM20)&IF(BN20="","",BN20) -> twenty eight | BR20: HUNDRED | BS20: =IF(BY20="","",IF(BY20>=90,"ninety "&IF((BY20-ROUNDDOWN(BY20,-1))=1,D20,"")&IF((BY20-ROUNDDOWN(BY20,-1))=2,F20,"")&IF((BY20-ROUNDDOWN(BY20,-1))=G20,H20,"")&IF((BY20-ROUNDDOWN(BY20,-1))=I20,J20,"")&IF((BY20-ROUNDDOWN(BY20,-1))=K20,L20,"")&IF((BY20-ROUNDDOWN(BY20,-1))=M20,N20,"")&IF((BY20-ROUNDDOWN(BY20,-1))=O20,P20,"")&IF((BY20-ROUNDDOWN(BY20,-1))=Q20,R20,"")&IF((BY20-ROUNDDOWN(BY20,-1))=S20,T20,""),IF(BY20>=80,"eighty "&IF((BY20-ROUNDDOWN(BY20,-1))=1,D20,"")&IF((BY20-ROUNDDOWN(BY20,-1))=2,F20,"")&IF((BY20-ROUNDDOWN(BY20,-1))=G20,H20,"")&IF((BY20-ROUNDDOWN(BY20,-1))=I20,J20,"")&IF((BY20-ROUNDDOWN(BY20,-1))=K20,L20,"")&IF((BY20-ROUNDDOWN(BY20,-1))=M20,N20,"")&IF((BY20-ROUNDDOWN(BY20,-1))=O20,P20,"")&IF((BY20-ROUNDDOWN(BY20,-1))=Q20,R20,"")&IF((BY20-ROUNDDOWN(BY20,-1))=S20,T20,""),""))) | BT20: =IF(BY20="","",IF(BY20>79,"",IF(BY20>=70,"seventy "&IF((BY20-ROUNDDOWN(BY20,-1))=1,D20,"")&IF((BY20-ROUNDDOWN(BY20,-1))=2,F20,"")&IF((BY20-ROUNDDOWN(BY20,-1))=G20,H20,"")&IF((BY20-ROUNDDOWN(BY20,-1))=I20,J20,"")&IF((BY20-ROUNDDOWN(BY20,-1))=K20,L20,"")&IF((BY20-ROUNDDOWN(BY20,-1))=M20,N20,"")&IF((BY20-ROUNDDOWN(BY20,-1))=O20,P20,"")&IF((BY20-ROUNDDOWN(BY20,-1))=Q20,R20,"")&IF((BY20-ROUNDDOWN(BY20,-1))=S20,T20,""),IF(BY20>=60,"sixty "&IF((BY20-ROUNDDOWN(BY20,-1))=1,D20,"")&IF((BY20-ROUNDDOWN(BY20,-1))=2,F20,"")&IF((BY20-ROUNDDOWN(BY20,-1))=G20,H20,"")&IF((BY20-ROUNDDOWN(BY20,-1))=I20,J20,"")&IF((BY20-ROUNDDOWN(BY20,-1))=K20,L20,"")&IF((BY20-ROUNDDOWN(BY20,-1))=M20,N20,"")&IF((BY20-ROUNDDOWN(BY20,-1))=O20,P20,"")&IF((BY20-ROUNDDOWN(BY20,-1))=Q20,R20,"")&IF((BY20-ROUNDDOWN(BY20,-1))=S20,T20,""),"")))) | BU20: =IF(BY20="","",IF(BY20>59,"",IF(BY20>=50,"fifty "&IF((BY20-ROUNDDOWN(BY20,-1))=1,D20,"")&IF((BY20-ROUNDDOWN(BY20,-1))=2,F20,"")&IF((BY20-ROUNDDOWN(BY20,-1))=G20,H20,"")&IF((BY20-ROUNDDOWN(BY20,-1))=I20,J20,"")&IF((BY20-ROUNDDOWN(BY20,-1))=K20,L20,"")&IF((BY20-ROUNDDOWN(BY20,-1))=M20,N20,"")&IF((BY20-ROUNDDOWN(BY20,-1))=O20,P20,"")&IF((BY20-ROUNDDOWN(BY20,-1))=Q20,R20,"")&IF((BY20-ROUNDDOWN(BY20,-1))=S20,T20,""),IF(BY20>=40,"forty "&IF((BY20-ROUNDDOWN(BY20,-1))=1,D20,"")&IF((BY20-ROUNDDOWN(BY20,-1))=2,F20,"")&IF((BY20-ROUNDDOWN(BY20,-1))=G20,H20,"")&IF((BY20-ROUNDDOWN(BY20,-1))=I20,J20,"")&IF((BY20-ROUNDDOWN(BY20,-1))=K20,L20,"")&IF((BY20-ROUNDDOWN(BY20,-1))=M20,N20,"")&IF((BY20-ROUNDDOWN(BY20,-1))=O20,P20,"")&IF((BY20-ROUNDDOWN(BY20,-1))=Q20,R20,"")&IF((BY20-ROUNDDOWN(BY20,-1))=S20,T20,""),"")))) | BV20: =IF(BY20="","",IF(BY20>39,"",IF(BY20>=30,"thirty "&IF((BY20-ROUNDDOWN(BY20,-1))=1,D20,"")&IF((BY20-ROUNDDOWN(BY20,-1))=2,F20,"")&IF((BY20-ROUNDDOWN(BY20,-1))=G20,H20,"")&IF((BY20-ROUNDDOWN(BY20,-1))=I20,J20,"")&IF((BY20-ROUNDDOWN(BY20,-1))=K20,L20,"")&IF((BY20-ROUNDDOWN(BY20,-1))=M20,N20,"")&IF((BY20-ROUNDDOWN(BY20,-1))=O20,P20,"")&IF((BY20-ROUNDDOWN(BY20,-1))=Q20,R20,"")&IF((BY20-ROUNDDOWN(BY20,-1))=S20,T20,""),IF(BY20>=20,"twenty "&IF((BY20-ROUNDDOWN(BY20,-1))=1,D20,"")&IF((BY20-ROUNDDOWN(BY20,-1))=2,F20,"")&IF((BY20-ROUNDDOWN(BY20,-1))=G20,H20,"")&IF((BY20-ROUNDDOWN(BY20,-1))=I20,J20,"")&IF((BY20-ROUNDDOWN(BY20,-1))=K20,L20,"")&IF((BY20-ROUNDDOWN(BY20,-1))=M20,N20,"")&IF((BY20-ROUNDDOWN(BY20,-1))=O20,P20,"")&IF((BY20-ROUNDDOWN(BY20,-1))=Q20,R20,"")&IF((BY20-ROUNDDOWN(BY20,-1))=S20,T20,""),"")))) | BW20: =IF(BY20="","",IF(BY20=C20,D20,"")&IF(BY20=E20,F20,"")&IF(BY20=G20,H20,"")&IF(BY20=I20,J20,"")&IF(BY20=K20,L20,"")&IF(BY20=M20,N20,"")&IF(BY20=O20,P20,"")&IF(BY20=Q20,R20,"")&IF(BY20=S20,T20,"")&IF(BY20=U20,V20,"")&IF(BY20=W20,X20,"")&IF(BY20=Y20,Z20,"")&IF(BY20=AA20,AB20,"")&IF(BY20=AC20,AD20,"")&IF(BY20=AE20,AF20,"")&IF(BY20=AG20,AH20,"")&IF(BY20=AI20,AJ20,"")&IF(BY20=AK20,AL20,"")&IF(BY20=AM20,AN20,"")) -> seven | BY20: =IF(A20>=100,ROUNDDOWN((A20-ROUNDDOWN(A20,-3))/100,0),"") -> 7 | BZ20: =IF(BS20="","",BS20)&IF(BT20="","",BT20)&IF(BU20="","",BU20)&IF(BV20="","",BV20)&IF(BW20="","",BW20) -> seven | CA20: TENS | CB20: =IF(CH20="","",IF(CH20>=90,"ninety "&IF((CH20-ROUNDDOWN(CH20,-1))=1,D20,"")&IF((CH20-ROUNDDOWN(CH20,-1))=2,F20,"")&IF((CH20-ROUNDDOWN(CH20,-1))=G20,H20,"")&IF((CH20-ROUNDDOWN(CH20,-1))=I20,J20,"")&IF((CH20-ROUNDDOWN(CH20,-1))=K20,L20,"")&IF((CH20-ROUNDDOWN(CH20,-1))=M20,N20,"")&IF((CH20-ROUNDDOWN(CH20,-1))=O20,P20,"")&IF((CH20-ROUNDDOWN(CH20,-1))=Q20,R20,"")&IF((CH20-ROUNDDOWN(CH20,-1))=S20,T20,""),IF(CH20>=80,"eighty "&IF((CH20-ROUNDDOWN(CH20,-1))=1,D20,"")&IF((CH20-ROUNDDOWN(CH20,-1))=2,F20,"")&IF((CH20-ROUNDDOWN(CH20,-1))=G20,H20,"")&IF((CH20-ROUNDDOWN(CH20,-1))=I20,J20,"")&IF((CH20-ROUNDDOWN(CH20,-1))=K20,L20,"")&IF((CH20-ROUNDDOWN(CH20,-1))=M20,N20,"")&IF((CH20-ROUNDDOWN(CH20,-1))=O20,P20,"")&IF((CH20-ROUNDDOWN(CH20,-1))=Q20,R20,"")&IF((CH20-ROUNDDOWN(CH20,-1))=S20,T20,""),""))) | CC20: =IF(CH20="","",IF(CH20>79,"",IF(CH20>=70,"seventy "&IF((CH20-ROUNDDOWN(CH20,-1))=1,D20,"")&IF((CH20-ROUNDDOWN(CH20,-1))=2,F20,"")&IF((CH20-ROUNDDOWN(CH20,-1))=G20,H20,"")&IF((CH20-ROUNDDOWN(CH20,-1))=I20,J20,"")&IF((CH20-ROUNDDOWN(CH20,-1))=K20,L20,"")&IF((CH20-ROUNDDOWN(CH20,-1))=M20,N20,"")&IF((CH20-ROUNDDOWN(CH20,-1))=O20,P20,"")&IF((CH20-ROUNDDOWN(CH20,-1))=Q20,R20,"")&IF((CH20-ROUNDDOWN(CH20,-1))=S20,T20,""),IF(CH20>=60,"sixty "&IF((CH20-ROUNDDOWN(CH20,-1))=1,D20,"")&IF((CH20-ROUNDDOWN(CH20,-1))=2,F20,"")&IF((CH20-ROUNDDOWN(CH20,-1))=G20,H20,"")&IF((CH20-ROUNDDOWN(CH20,-1))=I20,J20,"")&IF((CH20-ROUNDDOWN(CH20,-1))=K20,L20,"")&IF((CH20-ROUNDDOWN(CH20,-1))=M20,N20,"")&IF((CH20-ROUNDDOWN(CH20,-1))=O20,P20,"")&IF((CH20-ROUNDDOWN(CH20,-1))=Q20,R20,"")&IF((CH20-ROUNDDOWN(CH20,-1))=S20,T20,""),"")))) -> seventy two | CD20: =IF(CH20="","",IF(CH20>59,"",IF(CH20>=50,"fifty "&IF((CH20-ROUNDDOWN(CH20,-1))=1,D20,"")&IF((CH20-ROUNDDOWN(CH20,-1))=2,F20,"")&IF((CH20-ROUNDDOWN(CH20,-1))=G20,H20,"")&IF((CH20-ROUNDDOWN(CH20,-1))=I20,J20,"")&IF((CH20-ROUNDDOWN(CH20,-1))=K20,L20,"")&IF((CH20-ROUNDDOWN(CH20,-1))=M20,N20,"")&IF((CH20-ROUNDDOWN(CH20,-1))=O20,P20,"")&IF((CH20-ROUNDDOWN(CH20,-1))=Q20,R20,"")&IF((CH20-ROUNDDOWN(CH20,-1))=S20,T20,""),IF(CH20>=40,"forty "&IF((CH20-ROUNDDOWN(CH20,-1))=1,D20,"")&IF((CH20-ROUNDDOWN(CH20,-1))=2,F20,"")&IF((CH20-ROUNDDOWN(CH20,-1))=G20,H20,"")&IF((CH20-ROUNDDOWN(CH20,-1))=I20,J20,"")&IF((CH20-ROUNDDOWN(CH20,-1))=K20,L20,"")&IF((CH20-ROUNDDOWN(CH20,-1))=M20,N20,"")&IF((CH20-ROUNDDOWN(CH20,-1))=O20,P20,"")&IF((CH20-ROUNDDOWN(CH20,-1))=Q20,R20,"")&IF((CH20-ROUNDDOWN(CH20,-1))=S20,T20,""),"")))) | CE20: =IF(CH20="","",IF(CH20>39,"",IF(CH20>=30,"thirty "&IF((CH20-ROUNDDOWN(CH20,-1))=1,D20,"")&IF((CH20-ROUNDDOWN(CH20,-1))=2,F20,"")&IF((CH20-ROUNDDOWN(CH20,-1))=G20,H20,"")&IF((CH20-ROUNDDOWN(CH20,-1))=I20,J20,"")&IF((CH20-ROUNDDOWN(CH20,-1))=K20,L20,"")&IF((CH20-ROUNDDOWN(CH20,-1))=M20,N20,"")&IF((CH20-ROUNDDOWN(CH20,-1))=O20,P20,"")&IF((CH20-ROUNDDOWN(CH20,-1))=Q20,R20,"")&IF((CH20-ROUNDDOWN(CH20,-1))=S20,T20,""),IF(CH20>=20,"twenty "&IF((CH20-ROUNDDOWN(CH20,-1))=1,D20,"")&IF((CH20-ROUNDDOWN(CH20,-1))=2,F20,"")&IF((CH20-ROUNDDOWN(CH20,-1))=G20,H20,"")&IF((CH20-ROUNDDOWN(CH20,-1))=I20,J20,"")&IF((CH20-ROUNDDOWN(CH20,-1))=K20,L20,"")&IF((CH20-ROUNDDOWN(CH20,-1))=M20,N20,"")&IF((CH20-ROUNDDOWN(CH20,-1))=O20,P20,"")&IF((CH20-ROUNDDOWN(CH20,-1))=Q20,R20,"")&IF((CH20-ROUNDDOWN(CH20,-1))=S20,T20,""),"")))) | CF20: =IF(CH20="","",IF(CH20=C20,D20,"")&IF(CH20=E20,F20,"")&IF(CH20=G20,H20,"")&IF(CH20=I20,J20,"")&IF(CH20=K20,L20,"")&IF(CH20=M20,N20,"")&IF(CH20=O20,P20,"")&IF(CH20=Q20,R20,"")&IF(CH20=S20,T20,"")&IF(CH20=U20,V20,"")&IF(CH20=W20,X20,"")&IF(CH20=Y20,Z20,"")&IF(CH20=AA20,AB20,"")&IF(CH20=AC20,AD20,"")&IF(CH20=AE20,AF20,"")&IF(CH20=AG20,AH20,"")&IF(CH20=AI20,AJ20,"")&IF(CH20=AK20,AL20,"")&IF(CH20=AM20,AN20,"")) | CH20: =IF(A20>=1,ROUNDDOWN(A20-ROUNDDOWN(A20,-2),0),"") -> 72 | CI20: =IF(CB20="","",CB20)&IF(CC20="","",CC20)&IF(CD20="","",CD20)&IF(CE20="","",CE20)&IF(CF20="","",CF20) -> seventy two | CJ20: PAISE | CK20: =IF(CQ20="","",IF(CQ20>=90,"ninety "&IF((CQ20-ROUNDDOWN(CQ20,-1))=1,D20,"")&IF((CQ20-ROUNDDOWN(CQ20,-1))=2,F20,"")&IF((CQ20-ROUNDDOWN(CQ20,-1))=G20,H20,"")&IF((CQ20-ROUNDDOWN(CQ20,-1))=I20,J20,"")&IF((CQ20-ROUNDDOWN(CQ20,-1))=K20,L20,"")&IF((CQ20-ROUNDDOWN(CQ20,-1))=M20,N20,"")&IF((CQ20-ROUNDDOWN(CQ20,-1))=O20,P20,"")&IF((CQ20-ROUNDDOWN(CQ20,-1))=Q20,R20,"")&IF((CQ20-ROUNDDOWN(CQ20,-1))=S20,T20,""),IF(CQ20>=80,"eighty "&IF((CQ20-ROUNDDOWN(CQ20,-1))=1,D20,"")&IF((CQ20-ROUNDDOWN(CQ20,-1))=2,F20,"")&IF((CQ20-ROUNDDOWN(CQ20,-1))=G20,H20,"")&IF((CQ20-ROUNDDOWN(CQ20,-1))=I20,J20,"")&IF((CQ20-ROUNDDOWN(CQ20,-1))=K20,L20,"")&IF((CQ20-ROUNDDOWN(CQ20,-1))=M20,N20,"")&IF((CQ20-ROUNDDOWN(CQ20,-1))=O20,P20,"")&IF((CQ20-ROUNDDOWN(CQ20,-1))=Q20,R20,"")&IF((CQ20-ROUNDDOWN(CQ20,-1))=S20,T20,""),""))) | CL20: =IF(CQ20="","",IF(CQ20>79,"",IF(CQ20>=70,"seventy "&IF((CQ20-ROUNDDOWN(CQ20,-1))=1,D20,"")&IF((CQ20-ROUNDDOWN(CQ20,-1))=2,F20,"")&IF((CQ20-ROUNDDOWN(CQ20,-1))=G20,H20,"")&IF((CQ20-ROUNDDOWN(CQ20,-1))=I20,J20,"")&IF((CQ20-ROUNDDOWN(CQ20,-1))=K20,L20,"")&IF((CQ20-ROUNDDOWN(CQ20,-1))=M20,N20,"")&IF((CQ20-ROUNDDOWN(CQ20,-1))=O20,P20,"")&IF((CQ20-ROUNDDOWN(CQ20,-1))=Q20,R20,"")&IF((CQ20-ROUNDDOWN(CQ20,-1))=S20,T20,""),IF(CQ20>=60,"sixty "&IF((CQ20-ROUNDDOWN(CQ20,-1))=1,D20,"")&IF((CQ20-ROUNDDOWN(CQ20,-1))=2,F20,"")&IF((CQ20-ROUNDDOWN(CQ20,-1))=G20,H20,"")&IF((CQ20-ROUNDDOWN(CQ20,-1))=I20,J20,"")&IF((CQ20-ROUNDDOWN(CQ20,-1))=K20,L20,"")&IF((CQ20-ROUNDDOWN(CQ20,-1))=M20,N20,"")&IF((CQ20-ROUNDDOWN(CQ20,-1))=O20,P20,"")&IF((CQ20-ROUNDDOWN(CQ20,-1))=Q20,R20,"")&IF((CQ20-ROUNDDOWN(CQ20,-1))=S20,T20,""),"")))) | CM20: =IF(CQ20="","",IF(CQ20>59,"",IF(CQ20>=50,"fifty "&IF((CQ20-ROUNDDOWN(CQ20,-1))=1,D20,"")&IF((CQ20-ROUNDDOWN(CQ20,-1))=2,F20,"")&IF((CQ20-ROUNDDOWN(CQ20,-1))=G20,H20,"")&IF((CQ20-ROUNDDOWN(CQ20,-1))=I20,J20,"")&IF((CQ20-ROUNDDOWN(CQ20,-1))=K20,L20,"")&IF((CQ20-ROUNDDOWN(CQ20,-1))=M20,N20,"")&IF((CQ20-ROUNDDOWN(CQ20,-1))=O20,P20,"")&IF((CQ20-ROUNDDOWN(CQ20,-1))=Q20,R20,"")&IF((CQ20-ROUNDDOWN(CQ20,-1))=S20,T20,""),IF(CQ20>=40,"forty "&IF((CQ20-ROUNDDOWN(CQ20,-1))=1,D20,"")&IF((CQ20-ROUNDDOWN(CQ20,-1))=2,F20,"")&IF((CQ20-ROUNDDOWN(CQ20,-1))=G20,H20,"")&IF((CQ20-ROUNDDOWN(CQ20,-1))=I20,J20,"")&IF((CQ20-ROUNDDOWN(CQ20,-1))=K20,L20,"")&IF((CQ20-ROUNDDOWN(CQ20,-1))=M20,N20,"")&IF((CQ20-ROUNDDOWN(CQ20,-1))=O20,P20,"")&IF((CQ20-ROUNDDOWN(CQ20,-1))=Q20,R20,"")&IF((CQ20-ROUNDDOWN(CQ20,-1))=S20,T20,""),"")))) | CN20: =IF(CQ20="","",IF(CQ20>39,"",IF(CQ20>=30,"thirty "&IF((CQ20-ROUNDDOWN(CQ20,-1))=1,D20,"")&IF((CQ20-ROUNDDOWN(CQ20,-1))=2,F20,"")&IF((CQ20-ROUNDDOWN(CQ20,-1))=G20,H20,"")&IF((CQ20-ROUNDDOWN(CQ20,-1))=I20,J20,"")&IF((CQ20-ROUNDDOWN(CQ20,-1))=K20,L20,"")&IF((CQ20-ROUNDDOWN(CQ20,-1))=M20,N20,"")&IF((CQ20-ROUNDDOWN(CQ20,-1))=O20,P20,"")&IF((CQ20-ROUNDDOWN(CQ20,-1))=Q20,R20,"")&IF((CQ20-ROUNDDOWN(CQ20,-1))=S20,T20,""),IF(CQ20>=20,"twenty "&IF((CQ20-ROUNDDOWN(CQ20,-1))=1,D20,"")&IF((CQ20-ROUNDDOWN(CQ20,-1))=2,F20,"")&IF((CQ20-ROUNDDOWN(CQ20,-1))=G20,H20,"")&IF((CQ20-ROUNDDOWN(CQ20,-1))=I20,J20,"")&IF((CQ20-ROUNDDOWN(CQ20,-1))=K20,L20,"")&IF((CQ20-ROUNDDOWN(CQ20,-1))=M20,N20,"")&IF((CQ20-ROUNDDOWN(CQ20,-1))=O20,P20,"")&IF((CQ20-ROUNDDOWN(CQ20,-1))=Q20,R20,"")&IF((CQ20-ROUNDDOWN(CQ20,-1))=S20,T20,""),"")))) | CO20: =IF(CQ20="","",IF(CQ20=C20,D20,"")&IF(CQ20=E20,F20,"")&IF(CQ20=G20,H20,"")&IF(CQ20=I20,J20,"")&IF(CQ20=K20,L20,"")&IF(CQ20=M20,N20,"")&IF(CQ20=O20,P20,"")&IF(CQ20=Q20,R20,"")&IF(CQ20=S20,T20,"")&IF(CQ20=U20,V20,"")&IF(CQ20=W20,X20,"")&IF(CQ20=Y20,Z20,"")&IF(CQ20=AA20,AB20,"")&IF(CQ20=AC20,AD20,"")&IF(CQ20=AE20,AF20,"")&IF(CQ20=AG20,AH20,"")&IF(CQ20=AI20,AJ20,"")&IF(CQ20=AK20,AL20,"")&IF(CQ20=AM20,AN20,"")) | CQ20: =IF((A20-ROUNDDOWN(A20,0))>0,ROUND((A20-ROUNDDOWN(A20,0))*100,0),"") | CR20: =IF(CK20="","",CK20)&IF(CL20="","",CL20)&IF(CM20="","",CM20)&IF(CN20="","",CN20)&IF(CO20="","",CO20) | CS20: <= IN WORDS | CU20: =IF(A20="","","(Rupees "&IF(AY20="","",AY20&" crore ")&IF(BH20="","",BH20&" lakh ")&IF(BQ20="","",BQ20&" thousand ")&IF(BZ20="","",BZ20&" hundred ")&IF(CI20="","",CI20)&IF(CR20="",""," and paise "&CR20)&") only.") -> (Rupees four lakh twenty eight thousand seven hundred seventy two) only.

Sheet Furniture analysis
A1: =Abstract!B3 -> Name of Work :- Repairing and Renovation of Circuit House at Bokakhat Co District under Golaghat District
A3: RATE ANALYSIS FURNITURE WORKS
B4: BOQ ITEM NO = F1
A6: SL.NO. | B6: Description | E6: Unit | F6: Quantity | G6: Rate (Rs) | H6: Amount (Rs) | I6: Remarks
B7: Details of Cost of One
A8: 1 | B8: MATERIAL :
B9: Ruddhania Flexible Furnitures Single Wooden Bed with Headboard and Footboard Ruddhania Flexible Furnitures (RUDDHANIA SINGLE WOODEN BED 09) | E9: Each | F9: 1 | G9: 7900 | H9: =G9*F9 -> 7900
B10: Add Carring Charge | E10: L.S. | G10: =G9*2% -> 158 | H10: =G10 -> 158
A11: 2 | B11: TOTAL | H11: =SUM(H9:H10) -> 8058
A13: 3 | B13: TOTAL | H13: =SUM(H11:H12) -> 8058 | I13: Y
B14: Add COPH | C14: 0.15 | D14: on "Y" | H14: =H13*C14 -> 1208.7
A15: 4 | B15: TOTAL | H15: =SUM(H13:H14) -> 9266.7 | I15: Z
B16: Add Cess @ | C16: 0.01 | D16: on "Z" | H16: =H15*C16 -> 92.67
A18: 5 | B18: COST OF ONE | C18: 1 | E18: EACH | H18: =SUM(H15:H17) -> 9359.37
B22: BOQ ITEM NO = F2
A24: SL.NO. | B24: Description | E24: Unit | F24: Quantity | G24: Rate (Rs) | H24: Amount (Rs) | I24: Remarks
B25: Details of Cost of One
A26: 1 | B26: MATERIAL :
B27: KURL-ON 900 mm / 2.95 ft (Single Bed | E27: Each | F27: 1 | G27: 5603 | H27: =G27*F27 -> 5603
B28: Add Carring Charge | E28: L.S. | G28: =G27*2% -> 112.06 | H28: =G28 -> 112.06
A29: 2 | B29: TOTAL | H29: =SUM(H27:H28) -> 5715.06
A31: 3 | B31: TOTAL | H31: =SUM(H29:H30) -> 5715.06 | I31: Y
B32: Add COPH | C32: 0.15 | D32: on "Y" | H32: =H31*C32 -> 857.26
A33: 4 | B33: TOTAL | H33: =SUM(H31:H32) -> 6572.32 | I33: Z
B34: Add Cess @ | C34: 0.01 | D34: on "Z" | H34: =H33*C34 -> 65.72
A36: 5 | B36: COST OF ONE | C36: 1 | E36: EACH | H36: =SUM(H33:H35) -> 6638.04
B41: BOQ ITEM NO = F3
A42: SL.NO. | B42: Description | E42: Unit | F42: Quantity | G42: Rate (Rs) | H42: Amount (Rs) | I42: Remarks
B43: Details of Cost of One
A44: 1 | B44: MATERIAL :
B45: CHANDRA SHEKHAR EXPORTS Handcrafted Dining Table CHANDRA SHEKHAR EXPORTSR (CSE-TH71) | E45: Each | F45: 1 | G45: 59320 | H45: =G45*F45 -> 59320
B46: Add Carring Charge | E46: L.S. | G46: =G45*2% -> 1186.4 | H46: =G46 -> 1186.4
A47: 2 | B47: TOTAL | H47: =SUM(H45:H46) -> 60506.4
A49: 3 | B49: TOTAL | H49: =SUM(H47:H48) -> 60506.4 | I49: Y
B50: Add COPH | C50: 0.15 | D50: on "Y" | H50: =H49*C50 -> 9075.96
A51: 4 | B51: TOTAL | H51: =SUM(H49:H50) -> 69582.36 | I51: Z
B52: Add Cess @ | C52: 0.01 | D52: on "Z" | H52: =H51*C52 -> 695.82
A54: 5 | B54: COST OF ONE | C54: 1 | E54: EACH | H54: =SUM(H51:H53) -> 70278.18
B56: BOQ ITEM NO = F4
A57: SL.NO. | B57: Description | E57: Unit | F57: Quantity | G57: Rate (Rs) | H57: Amount (Rs) | I57: Remarks
B58: Details of Cost of One
A59: 1 | B59: MATERIAL :
B60: bombay dyeing Bedsheet - Size 255 centimeter x 230 centimeter | E60: Each | F60: 1 | G60: 525 | H60: =G60*F60 -> 525
B61: Add Carring Charge | E61: L.S. | G61: =G60*2% -> 10.5 | H61: =G61 -> 10.5
A62: 2 | B62: TOTAL | H62: =SUM(H60:H61) -> 535.5
A64: 3 | B64: TOTAL | H64: =SUM(H62:H63) -> 535.5 | I64: Y
B65: Add COPH | C65: 0.15 | D65: on "Y" | H65: =H64*C65 -> 80.33
A66: 4 | B66: TOTAL | H66: =SUM(H64:H65) -> 615.83 | I66: Z
B67: Add Cess @ | C67: 0.01 | D67: on "Z" | H67: =H66*C67 -> 6.16
A69: 5 | B69: COST OF ONE | C69: 1 | E69: EACH | H69: =SUM(H66:H68) -> 621.99
B74: BOQ ITEM NO = F5
A75: SL.NO. | B75: Description | E75: Unit | F75: Quantity | G75: Rate (Rs) | H75: Amount (Rs) | I75: Remarks
B76: Details of Cost of One
A77: 1 | B77: MATERIAL :
B78: PUREREST Cotton Pillow 33 cm x 56 cm | E78: Each | F78: 1 | G78: 510 | H78: =G78*F78 -> 510
B79: Add Carring Charge | E79: L.S. | G79: =G78*2% -> 10.2 | H79: =G79 -> 10.2
A80: 2 | B80: TOTAL | H80: =SUM(H78:H79) -> 520.2
A82: 3 | B82: TOTAL | H82: =SUM(H80:H81) -> 520.2 | I82: Y
B83: Add COPH | C83: 0.15 | D83: on "Y" | H83: =H82*C83 -> 78.03
A84: 4 | B84: TOTAL | H84: =SUM(H82:H83) -> 598.23 | I84: Z
B85: Add Cess @ | C85: 0.01 | D85: on "Z" | H85: =H84*C85 -> 5.98
A87: 5 | B87: COST OF ONE | C87: 1 | E87: EACH | H87: =SUM(H84:H86) -> 604.21
B92: BOQ ITEM NO = F6
A93: SL.NO. | B93: Description | E93: Unit | F93: Quantity | G93: Rate (Rs) | H93: Amount (Rs) | I93: Remarks
B94: Details of Cost of One
A95: 1 | B95: MATERIAL :
B96: BANDHARA Cotton Oxford Pillow Covers-Hand icraft, Size Single | E96: Each | F96: 1 | G96: 223 | H96: =G96*F96 -> 223
B97: Add Carring Charge | E97: L.S. | G97: =G96*2% -> 4.46 | H97: =G97 -> 4.46
A98: 2 | B98: TOTAL | H98: =SUM(H96:H97) -> 227.46
A100: 3 | B100: TOTAL | H100: =SUM(H98:H99) -> 227.46 | I100: Y
B101: Add COPH | C101: 0.15 | D101: on "Y" | H101: =H100*C101 -> 34.12
A102: 4 | B102: TOTAL | H102: =SUM(H100:H101) -> 261.58 | I102: Z
B103: Add Cess @ | C103: 0.01 | D103: on "Z" | H103: =H102*C103 -> 2.62
A105: 5 | B105: COST OF ONE | C105: 1 | E105: EACH | H105: =SUM(H102:H104) -> 264.2
B112: BOQ ITEM NO = F7
A113: SL.NO. | B113: Description | E113: Unit | F113: Quantity | G113: Rate (Rs) | H113: Amount (Rs) | I113: Remarks
B114: Details of Cost of One
A115: 1 | B115: MATERIAL :
B116: Borosil Ceramic Dinner Set Borosil (LARAH 3N BIRTHDAY SET) | E116: Each | F116: 1 | G116: 298.98 | H116: =G116*F116 -> 298.98
B117: Add Carring Charge | E117: L.S. | G117: =G116*2% -> 5.98 | H117: =G117 -> 5.98
A118: 2 | B118: TOTAL | H118: =SUM(H116:H117) -> 304.96
A120: 3 | B120: TOTAL | H120: =SUM(H118:H119) -> 304.96 | I120: Y
B121: Add COPH | C121: 0.15 | D121: on "Y" | H121: =H120*C121 -> 45.74
A122: 4 | B122: TOTAL | H122: =SUM(H120:H121) -> 350.7 | I122: Z
B123: Add Cess @ | C123: 0.01 | D123: on "Z" | H123: =H122*C123 -> 3.51
A125: 5 | B125: COST OF ONE | C125: 1 | E125: EACH | H125: =SUM(H122:H124) -> 354.21

Sheet NDC 
A2: NON DUPLICITY CERTIFICATE
A8: Sl No | C8: Name of Work | H8: Estimated Amount
A10: 1 | C10: =Report!D3 -> Repairing and Renovation of Circuit House at Bokakhat Co District under Golaghat District | H10: ="Rs. " & TEXT(Report!D7,"##,##0.00") & Report!D8 -> Rs. 46,23,500.00(Rupees forty eight lakh twenty three thousand five hundred ) only.
A14: Certify that the above work/project has not been taken up under any others scheme. This estimate is need rational and as per site condition at the time of framing with an extravagant .

Sheet CS
A1: COMPARATIVE STATEMENT (MODULAR KITCHEN)
A2: ='AType Cottage'!A1 -> Name of Work :- Repairing and Renovation of Circuit House at Bokakhat Co District under Golaghat District
A3: Sl No. | C3: 1 | G3: 2 | K3: 3 | O3: Remarks
A4: Name of the quotation holder with address | C4: Royal Traders, Bokakhat | G4: Om Narayani hardware, Bokakhat | K4: Antique Orient Home decor, Guwahati
A5: Sl No. | B5: Description of items | C5: Qnty. | D5: Base Amount (in Rs.) | E5: Amount with 18% GST (in Rs,) | F5: Total Amount | G5: Qnty. | H5: Base Amount (in Rs.) | I5: Amount with 18% GST (in Rs,) | J5: Total Amount | K5: Qnty. | L5: Base Amount (in Rs.) | M5: Amount with 18% GST (in Rs,) | N5: Total Amount
A6: 1 | B6: Modular kitchen | C6: 1 | D6: 474534 | E6: =D6*0.18 -> 85416.12 | F6: =ROUND(E6+D6,0) -> 559950 | G6: 1 | H6: 503814 | I6: =H6*0.18 -> 90686.52 | J6: =ROUND(I6+H6,-2) -> 594500 | K6: 1 | L6: 693898 | M6: =L6*0.18 -> 124901.64 | N6: =ROUND(M6+L6,-2) -> 818800 | O6: Lowest Rate is indicate by (L1)
B7: Total | F7: =F6 -> 559950 | J7: =J6 -> 594500 | N7: =N6 -> 818800
A8: Position | F8: L1 | J8: L2 | N8: L3
B13: Junior Engineer, PW (B&NH)D | G13: Asstt. Executive Engineer, PW (B&NH)D
B14: Bokakhat & Dergaon Territorial | G14: Bokakhat & Dergaon Territorial
B15: Building Sub- Division, Bokakhat | G15: Building Sub- Division, Bokakhat

Sheet Cer 1
A2: CERTIFICATE
A8: =" The estimate for the work "" "& Report!D3&" "& """ has been thoroughly checked and the estimate has been prepared as per rates of CPWD Schedule of Rates 2021 including contingency as per norms and is found correct as per norms/guidelines of CVC ." -> The estimate for the work " Repairing and Renovation of Circuit House at Bokakhat Co District under Golaghat District " has been thoroughly checked and the estimate has been prepared as per rates of CPWD Schedule of Rates 2021 including contingency as per norms and is found correct as per norms/guidelines of CVC .

Sheet Cer 2
A2: CERTIFICATE
A8: This is to certify that the amount Rs. 48,98,500.00(Rupees forty eight lakh ninety eight thousand five hundred ) only for the work" Repairing and Renovation of of Circuit House at Bokakhat Co District under Golaghat District". This estimate is prepared as per requirement of the concerning authority and condition observing all pertaining rules, procedures, formalities and government norms current in the state .
B14: I take full responsibility for any discrepancy/ irregularity and violation of any laws/rules.

Sheet Check list
A1: Draft Checklist for PWD files
A2: A. For accordance of AA-related files
A3: Sl. No. | B3: Particulars | C3: Notes of the Administrative Department
A4: 1 | B4: Name of the project | C4: =Report!D3 -> Repairing and Renovation of Circuit House at Bokakhat Co District under Golaghat District
A5: 2 | B5: Location of the project | C5: =Report!B17 -> Circuit House, Bokakhat.
A6: 3 | B6: Estimated amount | C6: ="Rs. " & TEXT(Report!D7,"#,##0.00") & " " & Report!D8 -> Rs. 46,23,500.00 (Rupees forty eight lakh twenty three thousand five hundred ) only.
A7: 4 | B7: Indicate the percentage of scheduled and non-scheduled items incorporated in the plan and estimate
A8: 5 | B8: For building works: I. Cost per sqm
B9: II. Comparison of these rates with other similar projects
B10: III. Details such as plinth area, number of stories, etc.
A11: 6 | B11: For road works: I. Cost per km
B12: II. Comparison of these rates with other similar projects
B13: III. Type of road- Earth/ Gravel/ Black top/ Concrete/ others
A14: 7 | B14: Reason of the project being taken up: I. Name and designation of VIP/ Dignitary who recommended the project
B15: II. Announced by HCM during the visit
B16: III. Announced/ approved by Cabinet
B17: IV. Suggested by department in public interest
A18: 8 | B18: Whether all items including windows, doors, electrical items, bathroom fittings etc. are included in the estimate? (Y/N) | C18: Yes
A19: 9 | B19: Mention the scope/ components/ special features of the project (4-5 points)
A20: 10 | B20: Whether the views of Value Engineering cell on the estimate have been incorporated in the estimate? (Y/N)
A21: 11 | B21: Whether there is sufficient budget provision in the appropriate budget head? (Y/N)
A22: 12 | B22: In case of revised AA, what is the subsequent increase in value of each revised AA compared to the original estimate?
A23: 13 | B23: In case of revised AA, what is the physical and financial progress of the ongoing works?
A24: 14 | B24: In case of revised AA, what is the reason for increase in amount: I. Change in scope of the project
B25: II. Inclusion of items in BOQ, without change in scope of the project
B26: III. Increase in quantity of items in BOQ, without change in scope of the project

Sheet Sanitart Works
A1: ='AType Cottage'!A1 -> Name of Work :- Repairing and Renovation of Circuit House at Bokakhat Co District under Golaghat District
A2: Detail Measurement of Sanitary & Water Supply Work
A3: The estimate is prepared on the basis of DSR 2021 (CPWD)
A4: Sl. No. | B4: DSR No. | C4: Description of Item | K4: Unit | L4: Quantity | M4: Rate | N4: Amount in Rs.
C5: PART C-Sanitary Work
A6: 1 | B6: 14.81 | C6: Cutting holes of required size in brick masonry wall for fixing of exhaust fan including providing and fixing 300 mm dia PVC pipe conforming BIS -12818 and making good the same etc. complete as per direction of Engineer-in-charge. | K6: each | L6: 14 | M6: 243.1 | N6: =ROUND(L6*M6,2) -> 3403.4
A7: 2 | B7: 17.3 | C7: Providing and fixing white vitreous china pedestal type water closet (European type) with seat and lid, 10 litre low level white vitreous china flushing cistern & C.P. flush bend with fittings & C.I. brackets, 40 mm flush bend, overflow arrangement with specials of standard make and mosquito proof coupling of approved municipal design complete, including painting of fittings and brackets, cutting and making good the walls and floors wherever required :
B8: 17.3.1 | C8: W.C. pan with ISI marked white solid plastic seat and lid | K8: each | L8: 14 | M8: 6941.3 | N8: =ROUND(L8*M8,2) -> 97178.2
A9: 3 | B9: 17.7 | C9: Providing and fixing wash basin with C.I. brackets, 15 mm C.P. brass pillar taps, 32 mm C.P. brass waste of standard pattern, including painting of fittings and brackets, cutting and making good the walls wherever require:
B10: 17.7.1 | C10: White Vitreous China Wash basin size 630x450 mm with a pair of 15 mm C.P. brass pillar taps | K10: each | L10: 14 | M10: 2275 | N10: =ROUND(L10*M10,2) -> 31850 | O10: 2275 | P10: =N10/O10 -> 14
B11: 17.8 | C11: Providing and fixing white vitreous china pedestal for wash basin completely recessed at the back for the reception of pipes and fittings. | K11: each | L11: 14 | M11: 1500.05 | N11: =ROUND(L11*M11,2) -> 21000.7 | O11: 2275 | P11: =N11/O11 -> 9.23
A12: 4 | B12: 17.16A | C12: Providing and fixing 8 mm dia C.P. / S.S. Jet with flexible tube upto 1 metre long with S.S. triangular plate to Eureopean type W.C. of quality and make as approved by Engineer - in - charge. | K12: each | L12: 14 | M12: 299.35 | N12: =ROUND(L12*M12,2) -> 4190.9
A13: 5 | B13: 17.22B | C13: Providing and fixing CP Brass Single lever telephonic wall mixer of quality & make as approved by Engineer in charge. (a) 15 mm nominal dia | K13: each | L13: 14 | M13: 6119.15 | N13: =ROUND(L13*M13,2) -> 85668.1
A14: 6 | B14: 17.35 | C14: Providing and fixing soil, waste and vent pipes :
B15: 17.35.1 | C15: 100 mm dia
B16: 17.35.1.1 | C16: Sand cast iron S&S pipe as per IS: 1729 | K16: m | L16: 50 | M16: 1018.05 | N16: =ROUND(L16*M16,2) -> 50902.5
A17: 7 | B17: 17.36 | C17: Providing and filling the joints with spun yarn, cement slurry and cement mortar 1:2 (1 cement : 2 fine sand) in S.C.I./ C.I. Pipes :
B18: 17.36.2 | C18: 100 mm dia pipe | K18: each | L18: 25 | M18: 163.45 | N18: =ROUND(L18*M18,2) -> 4086.25
A19: 8 | B19: 17.37 | C19: Providing and fixing M.S. holder-bat clamps of approved design to Sand Cast iron/cast iron (spun) pipe embedded in and including cement concrete blocks 10x10x10 cm of 1:2:4 mix (1 cement : 2 coarse sand : 4 graded stone aggregate 20 mm nominal size), including cost of cutting holes and making good the walls etc.:
B20: 17.37.1 | C20: For 100 mm dia pipe | K20: each | L20: 25 | M20: 308.45 | N20: =ROUND(L20*M20,2) -> 7711.25
A21: 9 | B21: 17.38 | C21: Providing and fixing bend of required degree with access door, insertion rubber washer 3 mm thick, bolts and nuts complete.
B22: 17.38.1 | C22: 100 mm dia
B23: 17.38.1.1 | C23: Sand cast iron S&S as per IS - 1729 | K23: each | L23: 20 | M23: 530.7 | N23: =ROUND(L23*M23,2) -> 10614
A24: 10 | B24: 17.43 | C24: Providing and fixing single equal plain junction of required degree with access door, insertion rubber washer 3 mm thick, bolts and nuts complete.
B25: 17.43.1 | C25: 100x100x100 mm
B26: 17.43.1.1 | C26: Sand cast iron S&S as per IS - 1729 | K26: each | L26: 15 | M26: 671.2 | N26: =ROUND(L26*M26,2) -> 10068
A27: 11 | B27: 17.72 | C27: Providing and fixing PTMT liquid soap container 109 mm wide, 125 mm high and 112 mm distance from wall of standard shape with bracket of the same materials with snap fittings of approved quality and colour, weighing not less than 105 gms | K27: each | L27: 14 | M27: 146.3 | N27: =ROUND(L27*M27,2) -> 2048.2
A28: 12 | B28: 17.72 | C28: Providing and fixing PTMT towel ring trapezoidal shape 215 mm long, 200 mm wide with minimum distances of 37 mm from wall face with concealed fittings arrangement of approved quality and colour, weighing not less than 88 gms. | K28: each | L28: 14 | M28: 204.7 | N28: =ROUND(L28*M28,2) -> 2865.8
C29: Water Supply Work | N29: -
A30: 12 | B30: 18.7 | C30: Providing and fixing Chlorinated Polyvinyl Chloride (CPVC) pipes, having thermal stability for hot & cold water supply, including all CPVC plain & brass threaded fittings, including fixing the pipe with clamps at 1.00 m spacing. This includes jointing of pipes & fittings with one step CPVC solvent cement and testing of joints complete as per direction of Engineer in Charge.
B31: 18.7.2 | C31: 20 mm nominal dia Pipes | K31: mtr | L31: 150 | M31: 325.1 | N31: =ROUND(L31*M31,2) -> 48765
A32: 13 | B32: 18.9 | C32: Providing and fixing Chlorinated Polyvinyl Chloride (CPVC) pipes, having thermal stability for hot & cold water supply including all CPVC plain & brass threaded fittings This includes jointing of pipes & fittings with one step CPVC solvent cement, trenching, refilling & testing of joints complete as per direction of Engineer in Charge. External work
B33: 18.9.3 | C33: 25 mm nominal dia Pipes | K33: mtr | L33: 178 | M33: 370.65 | N33: =ROUND(L33*M33,2) -> 65975.7
A34: 14 | B34: 18.5 | C34: Providing and fixing C.P. brass long nose bib cock of approved quality conforming to IS standards and weighing not less than 810 gms.
B35: 18.50.1 | C35: 15 mm nominal bore | K35: each | L35: 35 | M35: 715.04 | N35: =ROUND(L35*M35,2) -> 25026.4
A36: 15 | B36: 18.49 | C36: Providing and fixing C.P. brass stop cock (concealed) of standard design and of approved make conforming to IS:8931.
B37: 18.49.1 | C37: 15 mm nominal bore | K37: each | L37: 45 | M37: 594.75 | N37: =ROUND(L37*M37,2) -> 26763.75
A39: TOTAL= | N39: =SUM(N6:N37) -> 498118.15
A40: SAY= | N40: =ROUND(N39,0) -> 498118 | O40: 398332 | P40: =O40-N40 -> -99786

Sheet Electrical Works
A1: {='Sanitart Works'!A1:A1} -> Name of Work :- Repairing and Renovation of Circuit House at Bokakhat Co District under Golaghat District
A2: SL NO. | B2: ITEM. | C2: Description of materials | D2: UNIT | E2: RATE | F2: QNTY. | G2: AMOUNT
A3: 1 | B3: 1.10 | C3: Wiring for light point/ fan point/ exhaust fan point/ call bell point with 1.5 sq.mm FRLS PVC insulated copper conductor single core cable in surface / recessed medium class PVC conduit, with modular switch, modular plate, suitable GI box and earthing the point with 1.5 sq.mm. FRLS PVC insulated copper conductor single core cable etc as required.
B4: 1.10.1 | C4: Group A | D4: Point | E4: 1015 | F4: 20 | G4: =E4*F4 -> 20300
A5: 2 | B5: 1.12 | C5: Wiring for light/ power plug with 2X4 sq. mm FRLS PVC insulated copper conductor single core cable in surface/ recessed medium class PVC conduit along with 1 No 4 sq. mm FRLS PVC insulated copper conductor single core cable for loop earthing as required. | D5: mtr | E5: 334 | F5: 180 | G5: =E5*F5 -> 60120
A6: 3 | B6: 1.14 | C6: Wiring for circuit/ submain wiring along with earth wire with the following sizes of FRLS PVC insulated copper conductor, single core cable in surface/ recessed medium class PVC conduit as required
B7: 1.14.2 | C7: 2 X 2.5 sq. mm + 1 X 2.5 sq. mm earth wire | D7: mtr | E7: 275 | F7: 240 | G7: =E7*F7 -> 66000
B8: 1.14.3 | C8: 2 X 4 sq. mm + 1 X 4 sq. mm earth wire | D8: Metre | E8: 334 | F8: 140 | G8: =E8*F8 -> 46760
B9: 1.14.4 | C9: 2 X 6 sq. mm + 1 X 6 sq. mm earth wire | D9: mtr | E9: 439 | F9: 100 | G9: =E9*F9 -> 43900
A10: 4 | B10: 1.24 | C10: Supplying and fixing following modular switch/ socket on the existing modular plate & switch box including connections but excluding modular plate etc. as required.
B11: 1.24.1 | C11: 5/6 amps switch | D11: each | E11: 103 | F11: 8 | G11: =E11*F11 -> 824
B12: 1.24.3 | C12: 15/16 amp switch | D12: each | E12: 156 | F12: 12 | G12: =E12*F12 -> 1872
B13: 1.24.4 | C13: 3 pin 5/6 amp socket outlet | D13: each | E13: 122 | F13: 8 | G13: =E13*F13 -> 976
B14: 1.24.5 | C14: 6 pin 15/16 amp socket outlet | D14: each | E14: 197 | F14: 12 | G14: =E14*F14 -> 2364
A15: 5 | B15: 1.25 | C15: Supplying and fixing two module stepped type electronic fan regulator on the existing modular plate switch box including connections but excluding modular plate etc. as required. | D15: each | E15: 369 | F15: 6 | G15: =E15*F15 -> 2214
A16: 6 | B16: 1.27 | C16: Supplying and fixing following size/ modules, GI box along with modular base & cover plate for modular switches in recess etc as required.
B17: 1.27.1 | C17: 1 or 2 Module (75mmX75mm) | D17: each | E17: 298 | F17: 8 | G17: =E17*F17 -> 2384
B18: 1.27.3 | C18: 4 Module (125mmX75mm) | D18: each | E18: 343 | F18: 4 | G18: =E18*F18 -> 1372
B19: 1.27.6 | C19: 12 Module (200mmX150mm) | D19: each | E19: 547 | F19: 4 | G19: =E19*F19 -> 2188
A20: 7 | B20: 1.28 | C20: Supplying and fixing following Modular base & cover plate on existing modular metal boxes etc. as required.
B21: 1.28.1 | C21: 1 or 2 Module | D21: each | E21: 133 | F21: 8 | G21: =E21*F21 -> 1064
B22: 1.28.3 | C22: 4 Module | D22: each | E22: 158 | F22: 4 | G22: =E22*F22 -> 632
B23: 1.28.6 | C23: 12 Module | D23: each | E23: 272 | F23: 4 | G23: =E23*F23 -> 1088
A24: 8 | B24: 1.44 | C24: Installation, testing and commissioning of ceiling fan, including wiring the down rods of standard length (upto 30 cm) with 1.5 sq. mm FRLS PVC insulated, copper conductor, single core cable etc. as required. | D24: Metre | E24: 171 | F24: 8 | G24: =E24*F24 -> 1368
A25: 9 | B25: 19.1 | C25: Supply ,installation ,testing and commissioning of 1200 mm sweep ,BEE 5 Star rated, ceiling fan with brushless direct curretnt(BLDC) Motor | D25: each | E25: 2730 | F25: 8 | G25: =E25*F25 -> 21840
A26: 10 | B26: A-1 | C26: Supplying fitting and fixing of 9 Watt LED Bulb ( Make Havell's / Equivallent ) | D26: each | E26: 213 | F26: 8 | G26: =E26*F26 -> 1704
A27: 11 | B27: A-2 | C27: Supplying fitting and fixing Basic all purpose surface and wall mounted LED batten with polycarbonate housing & integrated electronic driver, Item of Description LUMILINEBS20W LED 865SPCWH, HSN CODE 9405, HAVELS MAKE or equivalent (Equivalent will be selected by the deptt considering the mother items rate) (equivalent PHILIPS/ WIPRO/ BAJAJ/ Havells/ HPL/ SOLAR/ JAQUAR make).Fixture size (LxWxB) (1150x25x40 mm for 20W) | D27: each | E27: 1010 | F27: 10 | G27: =E27*F27 -> 10100
A28: 12 | B28: A-3 | C28: Supplying fitting and fixing of Electric Storage Water Heater 10 L capacity.( Havells make -Puro Turbo Dx.item code-. GHWAPXTPI010) | D28: each | E28: =[50]Electrical!$E$28 -> 14820 | F28: 4 | G28: =E28*F28 -> 59280
A29: 13 | B29: A-4 | C29: Supplying with installation testing and commissioning of Hi -- wall 3 star rating non ducted split inverter type air conditioner of the following capacity with cordless remote complete with indoor and outdoor unit, copper pipe and electrical connection as approved by the Deptt.)up to 5 m between the room unit and out door unit as directed by the department.
C30: 1.5 T capacity Voltas make | D30: each | E30: =[50]Electrical!$E$30 -> 62027 | F30: 6 | G30: =E30*F30 -> 372162
E31: Total | F31: Rs. | G31: =SUM(G3:G30) -> 720512
C33: =CU40 -> (Rupees seven lakh twenty thousand five hundred twelve) only.
B37: Assistant Engineer, PWD Asstt. Ex. Engineer,PWD Executive Engineer,PWD
B38: Jorhat Electrical Division Jorhat Electrical Sub-Division Jorhat Electrical Division
B39: Golaghat Section Jorhat Jorhat
A40: =G31 -> 720512 | B40: COPY CELLS=> | C40: 1 | D40: one | E40: 2 | F40: two | G40: 3 | H40: three | I40: 4 | J40: four | K40: 5 | L40: five | M40: 6 | N40: six | O40: 7 | P40: seven | Q40: 8 | R40: eight | S40: 9 | T40: nine | U40: 10 | V40: ten | W40: 11 | X40: eleven | Y40: 12 | Z40: twelve | AA40: 13 | AB40: thirteen | AC40: 14 | AD40: fourteen | AE40: 15 | AF40: fifteen | AG40: 16 | AH40: sixteen | AI40: 17 | AJ40: seventeen | AK40: 18 | AL40: eighteen | AM40: 19 | AN40: nineteen | AO40: <=COPY CELLS | AP40: WORDS-> | AQ40: CRORE | AR40: =IF(AX40="","",IF(AX40>=90,"ninety "&IF((AX40-ROUNDDOWN(AX40,-1))=C40,D40,"")&IF((AX40-ROUNDDOWN(AX40,-1))=E40,F40,"")&IF((AX40-ROUNDDOWN(AX40,-1))=G40,H40,"")&IF((AX40-ROUNDDOWN(AX40,-1))=I40,J40,"")&IF((AX40-ROUNDDOWN(AX40,-1))=K40,L40,"")&IF((AX40-ROUNDDOWN(AX40,-1))=M40,N40,"")&IF((AX40-ROUNDDOWN(AX40,-1))=O40,P40,"")&IF((AX40-ROUNDDOWN(AX40,-1))=Q40,R40,"")&IF((AX40-ROUNDDOWN(AX40,-1))=S40,T40,""),IF(AX40>=80,"eighty "&IF((AX40-ROUNDDOWN(AX40,-1))=1,D40,"")&IF((AX40-ROUNDDOWN(AX40,-1))=2,F40,"")&IF((AX40-ROUNDDOWN(AX40,-1))=G40,H40,"")&IF((AX40-ROUNDDOWN(AX40,-1))=I40,J40,"")&IF((AX40-ROUNDDOWN(AX40,-1))=K40,L40,"")&IF((AX40-ROUNDDOWN(AX40,-1))=M40,N40,"")&IF((AX40-ROUNDDOWN(AX40,-1))=O40,P40,"")&IF((AX40-ROUNDDOWN(AX40,-1))=Q40,R40,"")&IF((AX40-ROUNDDOWN(AX40,-1))=S40,T40,""),""))) | AS40: =IF(AX40="","",IF(AX40>79,"",IF(AX40>=70,"seventy "&IF((AX40-ROUNDDOWN(AX40,-1))=C40,D40,"")&IF((AX40-ROUNDDOWN(AX40,-1))=E40,F40,"")&IF((AX40-ROUNDDOWN(AX40,-1))=G40,H40,"")&IF((AX40-ROUNDDOWN(AX40,-1))=I40,J40,"")&IF((AX40-ROUNDDOWN(AX40,-1))=K40,L40,"")&IF((AX40-ROUNDDOWN(AX40,-1))=M40,N40,"")&IF((AX40-ROUNDDOWN(AX40,-1))=O40,P40,"")&IF((AX40-ROUNDDOWN(AX40,-1))=Q40,R40,"")&IF((AX40-ROUNDDOWN(AX40,-1))=S40,T40,""),IF(AX40>=60,"sixty "&IF((AX40-ROUNDDOWN(AX40,-1))=1,D40,"")&IF((AX40-ROUNDDOWN(AX40,-1))=2,F40,"")&IF((AX40-ROUNDDOWN(AX40,-1))=G40,H40,"")&IF((AX40-ROUNDDOWN(AX40,-1))=I40,J40,"")&IF((AX40-ROUNDDOWN(AX40,-1))=K40,L40,"")&IF((AX40-ROUNDDOWN(AX40,-1))=M40,N40,"")&IF((AX40-ROUNDDOWN(AX40,-1))=O40,P40,"")&IF((AX40-ROUNDDOWN(AX40,-1))=Q40,R40,"")&IF((AX40-ROUNDDOWN(AX40,-1))=S40,T40,""),"")))) | AT40: =IF(AX40="","",IF(AX40>59,"",IF(AX40>=50,"fifty "&IF((AX40-ROUNDDOWN(AX40,-1))=C40,D40,"")&IF((AX40-ROUNDDOWN(AX40,-1))=E40,F40,"")&IF((AX40-ROUNDDOWN(AX40,-1))=G40,H40,"")&IF((AX40-ROUNDDOWN(AX40,-1))=I40,J40,"")&IF((AX40-ROUNDDOWN(AX40,-1))=K40,L40,"")&IF((AX40-ROUNDDOWN(AX40,-1))=M40,N40,"")&IF((AX40-ROUNDDOWN(AX40,-1))=O40,P40,"")&IF((AX40-ROUNDDOWN(AX40,-1))=Q40,R40,"")&IF((AX40-ROUNDDOWN(AX40,-1))=S40,T40,""),IF(AX40>=40,"forty "&IF((AX40-ROUNDDOWN(AX40,-1))=1,D40,"")&IF((AX40-ROUNDDOWN(AX40,-1))=2,F40,"")&IF((AX40-ROUNDDOWN(AX40,-1))=G40,H40,"")&IF((AX40-ROUNDDOWN(AX40,-1))=I40,J40,"")&IF((AX40-ROUNDDOWN(AX40,-1))=K40,L40,"")&IF((AX40-ROUNDDOWN(AX40,-1))=M40,N40,"")&IF((AX40-ROUNDDOWN(AX40,-1))=O40,P40,"")&IF((AX40-ROUNDDOWN(AX40,-1))=Q40,R40,"")&IF((AX40-ROUNDDOWN(AX40,-1))=S40,T40,""),"")))) | AU40: =IF(AX40="","",IF(AX40>39,"",IF(AX40>=30,"thirty "&IF((AX40-ROUNDDOWN(AX40,-1))=C40,D40,"")&IF((AX40-ROUNDDOWN(AX40,-1))=E40,F40,"")&IF((AX40-ROUNDDOWN(AX40,-1))=G40,H40,"")&IF((AX40-ROUNDDOWN(AX40,-1))=I40,J40,"")&IF((AX40-ROUNDDOWN(AX40,-1))=K40,L40,"")&IF((AX40-ROUNDDOWN(AX40,-1))=M40,N40,"")&IF((AX40-ROUNDDOWN(AX40,-1))=O40,P40,"")&IF((AX40-ROUNDDOWN(AX40,-1))=Q40,R40,"")&IF((AX40-ROUNDDOWN(AX40,-1))=S40,T40,""),IF(AX40>=20,"twenty "&IF((AX40-ROUNDDOWN(AX40,-1))=1,D40,"")&IF((AX40-ROUNDDOWN(AX40,-1))=2,F40,"")&IF((AX40-ROUNDDOWN(AX40,-1))=G40,H40,"")&IF((AX40-ROUNDDOWN(AX40,-1))=I40,J40,"")&IF((AX40-ROUNDDOWN(AX40,-1))=K40,L40,"")&IF((AX40-ROUNDDOWN(AX40,-1))=M40,N40,"")&IF((AX40-ROUNDDOWN(AX40,-1))=O40,P40,"")&IF((AX40-ROUNDDOWN(AX40,-1))=Q40,R40,"")&IF((AX40-ROUNDDOWN(AX40,-1))=S40,T40,""),"")))) | AV40: =IF(AX40="","",IF(AX40=C40,D40,"")&IF(AX40=E40,F40,"")&IF(AX40=G40,H40,"")&IF(AX40=I40,J40,"")&IF(AX40=K40,L40,"")&IF(AX40=M40,N40,"")&IF(AX40=O40,P40,"")&IF(AX40=Q40,R40,"")&IF(AX40=S40,T40,"")&IF(AX40=U40,V40,"")&IF(AX40=W40,X40,"")&IF(AX40=Y40,Z40,"")&IF(AX40=AA40,AB40,"")&IF(AX40=AC40,AD40,"")&IF(AX40=AE40,AF40,"")&IF(AX40=AG40,AH40,"")&IF(AX40=AI40,AJ40,"")&IF(AX40=AK40,AL40,"")&IF(AX40=AM40,AN40,"")) | AX40: =IF(A40>=10000000,ROUNDDOWN(A40,-7)/10000000,"") | AY40: =IF(AR40="","",AR40)&IF(AS40="","",AS40)&IF(AT40="","",AT40)&IF(AU40="","",AU40)&IF(AV40="","",AV40) | AZ40: LAKH | BA40: =IF(BG40="","",IF(BG40>=90,"ninety "&IF((BG40-ROUNDDOWN(BG40,-1))=C40,D40,"")&IF((BG40-ROUNDDOWN(BG40,-1))=E40,F40,"")&IF((BG40-ROUNDDOWN(BG40,-1))=G40,H40,"")&IF((BG40-ROUNDDOWN(BG40,-1))=I40,J40,"")&IF((BG40-ROUNDDOWN(BG40,-1))=K40,L40,"")&IF((BG40-ROUNDDOWN(BG40,-1))=M40,N40,"")&IF((BG40-ROUNDDOWN(BG40,-1))=O40,P40,"")&IF((BG40-ROUNDDOWN(BG40,-1))=Q40,R40,"")&IF((BG40-ROUNDDOWN(BG40,-1))=S40,T40,""),IF(BG40>=80,"eighty "&IF((BG40-ROUNDDOWN(BG40,-1))=1,D40,"")&IF((BG40-ROUNDDOWN(BG40,-1))=2,F40,"")&IF((BG40-ROUNDDOWN(BG40,-1))=G40,H40,"")&IF((BG40-ROUNDDOWN(BG40,-1))=I40,J40,"")&IF((BG40-ROUNDDOWN(BG40,-1))=K40,L40,"")&IF((BG40-ROUNDDOWN(BG40,-1))=M40,N40,"")&IF((BG40-ROUNDDOWN(BG40,-1))=O40,P40,"")&IF((BG40-ROUNDDOWN(BG40,-1))=Q40,R40,"")&IF((BG40-ROUNDDOWN(BG40,-1))=S40,T40,""),""))) | BB40: =IF(BG40="","",IF(BG40>79,"",IF(BG40>=70,"seventy "&IF((BG40-ROUNDDOWN(BG40,-1))=C40,D40,"")&IF((BG40-ROUNDDOWN(BG40,-1))=E40,F40,"")&IF((BG40-ROUNDDOWN(BG40,-1))=G40,H40,"")&IF((BG40-ROUNDDOWN(BG40,-1))=I40,J40,"")&IF((BG40-ROUNDDOWN(BG40,-1))=K40,L40,"")&IF((BG40-ROUNDDOWN(BG40,-1))=M40,N40,"")&IF((BG40-ROUNDDOWN(BG40,-1))=O40,P40,"")&IF((BG40-ROUNDDOWN(BG40,-1))=Q40,R40,"")&IF((BG40-ROUNDDOWN(BG40,-1))=S40,T40,""),IF(BG40>=60,"sixty "&IF((BG40-ROUNDDOWN(BG40,-1))=1,D40,"")&IF((BG40-ROUNDDOWN(BG40,-1))=2,F40,"")&IF((BG40-ROUNDDOWN(BG40,-1))=G40,H40,"")&IF((BG40-ROUNDDOWN(BG40,-1))=I40,J40,"")&IF((BG40-ROUNDDOWN(BG40,-1))=K40,L40,"")&IF((BG40-ROUNDDOWN(BG40,-1))=M40,N40,"")&IF((BG40-ROUNDDOWN(BG40,-1))=O40,P40,"")&IF((BG40-ROUNDDOWN(BG40,-1))=Q40,R40,"")&IF((BG40-ROUNDDOWN(BG40,-1))=S40,T40,""),"")))) | BC40: =IF(BG40="","",IF(BG40>59,"",IF(BG40>=50,"fifty "&IF((BG40-ROUNDDOWN(BG40,-1))=C40,D40,"")&IF((BG40-ROUNDDOWN(BG40,-1))=E40,F40,"")&IF((BG40-ROUNDDOWN(BG40,-1))=G40,H40,"")&IF((BG40-ROUNDDOWN(BG40,-1))=I40,J40,"")&IF((BG40-ROUNDDOWN(BG40,-1))=K40,L40,"")&IF((BG40-ROUNDDOWN(BG40,-1))=M40,N40,"")&IF((BG40-ROUNDDOWN(BG40,-1))=O40,P40,"")&IF((BG40-ROUNDDOWN(BG40,-1))=Q40,R40,"")&IF((BG40-ROUNDDOWN(BG40,-1))=S40,T40,""),IF(BG40>=40,"forty "&IF((BG40-ROUNDDOWN(BG40,-1))=1,D40,"")&IF((BG40-ROUNDDOWN(BG40,-1))=2,F40,"")&IF((BG40-ROUNDDOWN(BG40,-1))=G40,H40,"")&IF((BG40-ROUNDDOWN(BG40,-1))=I40,J40,"")&IF((BG40-ROUNDDOWN(BG40,-1))=K40,L40,"")&IF((BG40-ROUNDDOWN(BG40,-1))=M40,N40,"")&IF((BG40-ROUNDDOWN(BG40,-1))=O40,P40,"")&IF((BG40-ROUNDDOWN(BG40,-1))=Q40,R40,"")&IF((BG40-ROUNDDOWN(BG40,-1))=S40,T40,""),"")))) | BD40: =IF(BG40="","",IF(BG40>39,"",IF(BG40>=30,"thirty "&IF((BG40-ROUNDDOWN(BG40,-1))=C40,D40,"")&IF((BG40-ROUNDDOWN(BG40,-1))=E40,F40,"")&IF((BG40-ROUNDDOWN(BG40,-1))=G40,H40,"")&IF((BG40-ROUNDDOWN(BG40,-1))=I40,J40,"")&IF((BG40-ROUNDDOWN(BG40,-1))=K40,L40,"")&IF((BG40-ROUNDDOWN(BG40,-1))=M40,N40,"")&IF((BG40-ROUNDDOWN(BG40,-1))=O40,P40,"")&IF((BG40-ROUNDDOWN(BG40,-1))=Q40,R40,"")&IF((BG40-ROUNDDOWN(BG40,-1))=S40,T40,""),IF(BG40>=20,"twenty "&IF((BG40-ROUNDDOWN(BG40,-1))=1,D40,"")&IF((BG40-ROUNDDOWN(BG40,-1))=2,F40,"")&IF((BG40-ROUNDDOWN(BG40,-1))=G40,H40,"")&IF((BG40-ROUNDDOWN(BG40,-1))=I40,J40,"")&IF((BG40-ROUNDDOWN(BG40,-1))=K40,L40,"")&IF((BG40-ROUNDDOWN(BG40,-1))=M40,N40,"")&IF((BG40-ROUNDDOWN(BG40,-1))=O40,P40,"")&IF((BG40-ROUNDDOWN(BG40,-1))=Q40,R40,"")&IF((BG40-ROUNDDOWN(BG40,-1))=S40,T40,""),"")))) | BE40: =IF(BG40="","",IF(BG40=C40,D40,"")&IF(BG40=E40,F40,"")&IF(BG40=G40,H40,"")&IF(BG40=I40,J40,"")&IF(BG40=K40,L40,"")&IF(BG40=M40,N40,"")&IF(BG40=O40,P40,"")&IF(BG40=Q40,R40,"")&IF(BG40=S40,T40,"")&IF(BG40=U40,V40,"")&IF(BG40=W40,X40,"")&IF(BG40=Y40,Z40,"")&IF(BG40=AA40,AB40,"")&IF(BG40=AC40,AD40,"")&IF(BG40=AE40,AF40,"")&IF(BG40=AG40,AH40,"")&IF(BG40=AI40,AJ40,"")&IF(BG40=AK40,AL40,"")&IF(BG40=AM40,AN40,"")) -> seven | BG40: =IF(A40>=100000,ROUNDDOWN((ROUND(A40,-4)-ROUNDDOWN(A40,-7))/100000,0),"") -> 7 | BH40: =IF(BA40="","",BA40)&IF(BB40="","",BB40)&IF(BC40="","",BC40)&IF(BD40="","",BD40)&IF(BE40="","",BE40) -> seven | BI40: THOUSAND | BJ40: =IF(BP40="","",IF(BP40>=90,"ninety "&IF((BP40-ROUNDDOWN(BP40,-1))=1,D40,"")&IF((BP40-ROUNDDOWN(BP40,-1))=2,F40,"")&IF((BP40-ROUNDDOWN(BP40,-1))=G40,H40,"")&IF((BP40-ROUNDDOWN(BP40,-1))=I40,J40,"")&IF((BP40-ROUNDDOWN(BP40,-1))=K40,L40,"")&IF((BP40-ROUNDDOWN(BP40,-1))=M40,N40,"")&IF((BP40-ROUNDDOWN(BP40,-1))=O40,P40,"")&IF((BP40-ROUNDDOWN(BP40,-1))=Q40,R40,"")&IF((BP40-ROUNDDOWN(BP40,-1))=S40,T40,""),IF(BP40>=80,"eighty "&IF((BP40-ROUNDDOWN(BP40,-1))=1,D40,"")&IF((BP40-ROUNDDOWN(BP40,-1))=2,F40,"")&IF((BP40-ROUNDDOWN(BP40,-1))=G40,H40,"")&IF((BP40-ROUNDDOWN(BP40,-1))=I40,J40,"")&IF((BP40-ROUNDDOWN(BP40,-1))=K40,L40,"")&IF((BP40-ROUNDDOWN(BP40,-1))=M40,N40,"")&IF((BP40-ROUNDDOWN(BP40,-1))=O40,P40,"")&IF((BP40-ROUNDDOWN(BP40,-1))=Q40,R40,"")&IF((BP40-ROUNDDOWN(BP40,-1))=S40,T40,""),""))) | BK40: =IF(BP40="","",IF(BP40>79,"",IF(BP40>=70,"seventy "&IF((BP40-ROUNDDOWN(BP40,-1))=1,D40,"")&IF((BP40-ROUNDDOWN(BP40,-1))=2,F40,"")&IF((BP40-ROUNDDOWN(BP40,-1))=G40,H40,"")&IF((BP40-ROUNDDOWN(BP40,-1))=I40,J40,"")&IF((BP40-ROUNDDOWN(BP40,-1))=K40,L40,"")&IF((BP40-ROUNDDOWN(BP40,-1))=M40,N40,"")&IF((BP40-ROUNDDOWN(BP40,-1))=O40,P40,"")&IF((BP40-ROUNDDOWN(BP40,-1))=Q40,R40,"")&IF((BP40-ROUNDDOWN(BP40,-1))=S40,T40,""),IF(BP40>=60,"sixty "&IF((BP40-ROUNDDOWN(BP40,-1))=1,D40,"")&IF((BP40-ROUNDDOWN(BP40,-1))=2,F40,"")&IF((BP40-ROUNDDOWN(BP40,-1))=G40,H40,"")&IF((BP40-ROUNDDOWN(BP40,-1))=I40,J40,"")&IF((BP40-ROUNDDOWN(BP40,-1))=K40,L40,"")&IF((BP40-ROUNDDOWN(BP40,-1))=M40,N40,"")&IF((BP40-ROUNDDOWN(BP40,-1))=O40,P40,"")&IF((BP40-ROUNDDOWN(BP40,-1))=Q40,R40,"")&IF((BP40-ROUNDDOWN(BP40,-1))=S40,T40,""),"")))) | BL40: =IF(BP40="","",IF(BP40>59,"",IF(BP40>=50,"fifty "&IF((BP40-ROUNDDOWN(BP40,-1))=1,D40,"")&IF((BP40-ROUNDDOWN(BP40,-1))=2,F40,"")&IF((BP40-ROUNDDOWN(BP40,-1))=G40,H40,"")&IF((BP40-ROUNDDOWN(BP40,-1))=I40,J40,"")&IF((BP40-ROUNDDOWN(BP40,-1))=K40,L40,"")&IF((BP40-ROUNDDOWN(BP40,-1))=M40,N40,"")&IF((BP40-ROUNDDOWN(BP40,-1))=O40,P40,"")&IF((BP40-ROUNDDOWN(BP40,-1))=Q40,R40,"")&IF((BP40-ROUNDDOWN(BP40,-1))=S40,T40,""),IF(BP40>=40,"forty "&IF((BP40-ROUNDDOWN(BP40,-1))=1,D40,"")&IF((BP40-ROUNDDOWN(BP40,-1))=2,F40,"")&IF((BP40-ROUNDDOWN(BP40,-1))=G40,H40,"")&IF((BP40-ROUNDDOWN(BP40,-1))=I40,J40,"")&IF((BP40-ROUNDDOWN(BP40,-1))=K40,L40,"")&IF((BP40-ROUNDDOWN(BP40,-1))=M40,N40,"")&IF((BP40-ROUNDDOWN(BP40,-1))=O40,P40,"")&IF((BP40-ROUNDDOWN(BP40,-1))=Q40,R40,"")&IF((BP40-ROUNDDOWN(BP40,-1))=S40,T40,""),"")))) | BM40: =IF(BP40="","",IF(BP40>39,"",IF(BP40>=30,"thirty "&IF((BP40-ROUNDDOWN(BP40,-1))=1,D40,"")&IF((BP40-ROUNDDOWN(BP40,-1))=2,F40,"")&IF((BP40-ROUNDDOWN(BP40,-1))=G40,H40,"")&IF((BP40-ROUNDDOWN(BP40,-1))=I40,J40,"")&IF((BP40-ROUNDDOWN(BP40,-1))=K40,L40,"")&IF((BP40-ROUNDDOWN(BP40,-1))=M40,N40,"")&IF((BP40-ROUNDDOWN(BP40,-1))=O40,P40,"")&IF((BP40-ROUNDDOWN(BP40,-1))=Q40,R40,"")&IF((BP40-ROUNDDOWN(BP40,-1))=S40,T40,""),IF(BP40>=20,"twenty "&IF((BP40-ROUNDDOWN(BP40,-1))=1,D40,"")&IF((BP40-ROUNDDOWN(BP40,-1))=2,F40,"")&IF((BP40-ROUNDDOWN(BP40,-1))=G40,H40,"")&IF((BP40-ROUNDDOWN(BP40,-1))=I40,J40,"")&IF((BP40-ROUNDDOWN(BP40,-1))=K40,L40,"")&IF((BP40-ROUNDDOWN(BP40,-1))=M40,N40,"")&IF((BP40-ROUNDDOWN(BP40,-1))=O40,P40,"")&IF((BP40-ROUNDDOWN(BP40,-1))=Q40,R40,"")&IF((BP40-ROUNDDOWN(BP40,-1))=S40,T40,""),"")))) -> twenty | BN40: =IF(BP40="","",IF(BP40=C40,D40,"")&IF(BP40=E40,F40,"")&IF(BP40=G40,H40,"")&IF(BP40=I40,J40,"")&IF(BP40=K40,L40,"")&IF(BP40=M40,N40,"")&IF(BP40=O40,P40,"")&IF(BP40=Q40,R40,"")&IF(BP40=S40,T40,"")&IF(BP40=U40,V40,"")&IF(BP40=W40,X40,"")&IF(BP40=Y40,Z40,"")&IF(BP40=AA40,AB40,"")&IF(BP40=AC40,AD40,"")&IF(BP40=AE40,AF40,"")&IF(BP40=AG40,AH40,"")&IF(BP40=AI40,AJ40,"")&IF(BP40=AK40,AL40,"")&IF(BP40=AM40,AN40,"")) | BP40: =IF(A40>=1000,ROUNDDOWN((A40-ROUNDDOWN(A40,-5))/1000,0),"") -> 20 | BQ40: =IF(BJ40="","",BJ40)&IF(BK40="","",BK40)&IF(BL40="","",BL40)&IF(BM40="","",BM40)&IF(BN40="","",BN40) -> twenty | BR40: HUNDRED | BS40: =IF(BY40="","",IF(BY40>=90,"ninety "&IF((BY40-ROUNDDOWN(BY40,-1))=1,D40,"")&IF((BY40-ROUNDDOWN(BY40,-1))=2,F40,"")&IF((BY40-ROUNDDOWN(BY40,-1))=G40,H40,"")&IF((BY40-ROUNDDOWN(BY40,-1))=I40,J40,"")&IF((BY40-ROUNDDOWN(BY40,-1))=K40,L40,"")&IF((BY40-ROUNDDOWN(BY40,-1))=M40,N40,"")&IF((BY40-ROUNDDOWN(BY40,-1))=O40,P40,"")&IF((BY40-ROUNDDOWN(BY40,-1))=Q40,R40,"")&IF((BY40-ROUNDDOWN(BY40,-1))=S40,T40,""),IF(BY40>=80,"eighty "&IF((BY40-ROUNDDOWN(BY40,-1))=1,D40,"")&IF((BY40-ROUNDDOWN(BY40,-1))=2,F40,"")&IF((BY40-ROUNDDOWN(BY40,-1))=G40,H40,"")&IF((BY40-ROUNDDOWN(BY40,-1))=I40,J40,"")&IF((BY40-ROUNDDOWN(BY40,-1))=K40,L40,"")&IF((BY40-ROUNDDOWN(BY40,-1))=M40,N40,"")&IF((BY40-ROUNDDOWN(BY40,-1))=O40,P40,"")&IF((BY40-ROUNDDOWN(BY40,-1))=Q40,R40,"")&IF((BY40-ROUNDDOWN(BY40,-1))=S40,T40,""),""))) | BT40: =IF(BY40="","",IF(BY40>79,"",IF(BY40>=70,"seventy "&IF((BY40-ROUNDDOWN(BY40,-1))=1,D40,"")&IF((BY40-ROUNDDOWN(BY40,-1))=2,F40,"")&IF((BY40-ROUNDDOWN(BY40,-1))=G40,H40,"")&IF((BY40-ROUNDDOWN(BY40,-1))=I40,J40,"")&IF((BY40-ROUNDDOWN(BY40,-1))=K40,L40,"")&IF((BY40-ROUNDDOWN(BY40,-1))=M40,N40,"")&IF((BY40-ROUNDDOWN(BY40,-1))=O40,P40,"")&IF((BY40-ROUNDDOWN(BY40,-1))=Q40,R40,"")&IF((BY40-ROUNDDOWN(BY40,-1))=S40,T40,""),IF(BY40>=60,"sixty "&IF((BY40-ROUNDDOWN(BY40,-1))=1,D40,"")&IF((BY40-ROUNDDOWN(BY40,-1))=2,F40,"")&IF((BY40-ROUNDDOWN(BY40,-1))=G40,H40,"")&IF((BY40-ROUNDDOWN(BY40,-1))=I40,J40,"")&IF((BY40-ROUNDDOWN(BY40,-1))=K40,L40,"")&IF((BY40-ROUNDDOWN(BY40,-1))=M40,N40,"")&IF((BY40-ROUNDDOWN(BY40,-1))=O40,P40,"")&IF((BY40-ROUNDDOWN(BY40,-1))=Q40,R40,"")&IF((BY40-ROUNDDOWN(BY40,-1))=S40,T40,""),"")))) | BU40: =IF(BY40="","",IF(BY40>59,"",IF(BY40>=50,"fifty "&IF((BY40-ROUNDDOWN(BY40,-1))=1,D40,"")&IF((BY40-ROUNDDOWN(BY40,-1))=2,F40,"")&IF((BY40-ROUNDDOWN(BY40,-1))=G40,H40,"")&IF((BY40-ROUNDDOWN(BY40,-1))=I40,J40,"")&IF((BY40-ROUNDDOWN(BY40,-1))=K40,L40,"")&IF((BY40-ROUNDDOWN(BY40,-1))=M40,N40,"")&IF((BY40-ROUNDDOWN(BY40,-1))=O40,P40,"")&IF((BY40-ROUNDDOWN(BY40,-1))=Q40,R40,"")&IF((BY40-ROUNDDOWN(BY40,-1))=S40,T40,""),IF(BY40>=40,"forty "&IF((BY40-ROUNDDOWN(BY40,-1))=1,D40,"")&IF((BY40-ROUNDDOWN(BY40,-1))=2,F40,"")&IF((BY40-ROUNDDOWN(BY40,-1))=G40,H40,"")&IF((BY40-ROUNDDOWN(BY40,-1))=I40,J40,"")&IF((BY40-ROUNDDOWN(BY40,-1))=K40,L40,"")&IF((BY40-ROUNDDOWN(BY40,-1))=M40,N40,"")&IF((BY40-ROUNDDOWN(BY40,-1))=O40,P40,"")&IF((BY40-ROUNDDOWN(BY40,-1))=Q40,R40,"")&IF((BY40-ROUNDDOWN(BY40,-1))=S40,T40,""),"")))) | BV40: =IF(BY40="","",IF(BY40>39,"",IF(BY40>=30,"thirty "&IF((BY40-ROUNDDOWN(BY40,-1))=1,D40,"")&IF((BY40-ROUNDDOWN(BY40,-1))=2,F40,"")&IF((BY40-ROUNDDOWN(BY40,-1))=G40,H40,"")&IF((BY40-ROUNDDOWN(BY40,-1))=I40,J40,"")&IF((BY40-ROUNDDOWN(BY40,-1))=K40,L40,"")&IF((BY40-ROUNDDOWN(BY40,-1))=M40,N40,"")&IF((BY40-ROUNDDOWN(BY40,-1))=O40,P40,"")&IF((BY40-ROUNDDOWN(BY40,-1))=Q40,R40,"")&IF((BY40-ROUNDDOWN(BY40,-1))=S40,T40,""),IF(BY40>=20,"twenty "&IF((BY40-ROUNDDOWN(BY40,-1))=1,D40,"")&IF((BY40-ROUNDDOWN(BY40,-1))=2,F40,"")&IF((BY40-ROUNDDOWN(BY40,-1))=G40,H40,"")&IF((BY40-ROUNDDOWN(BY40,-1))=I40,J40,"")&IF((BY40-ROUNDDOWN(BY40,-1))=K40,L40,"")&IF((BY40-ROUNDDOWN(BY40,-1))=M40,N40,"")&IF((BY40-ROUNDDOWN(BY40,-1))=O40,P40,"")&IF((BY40-ROUNDDOWN(BY40,-1))=Q40,R40,"")&IF((BY40-ROUNDDOWN(BY40,-1))=S40,T40,""),"")))) | BW40: =IF(BY40="","",IF(BY40=C40,D40,"")&IF(BY40=E40,F40,"")&IF(BY40=G40,H40,"")&IF(BY40=I40,J40,"")&IF(BY40=K40,L40,"")&IF(BY40=M40,N40,"")&IF(BY40=O40,P40,"")&IF(BY40=Q40,R40,"")&IF(BY40=S40,T40,"")&IF(BY40=U40,V40,"")&IF(BY40=W40,X40,"")&IF(BY40=Y40,Z40,"")&IF(BY40=AA40,AB40,"")&IF(BY40=AC40,AD40,"")&IF(BY40=AE40,AF40,"")&IF(BY40=AG40,AH40,"")&IF(BY40=AI40,AJ40,"")&IF(BY40=AK40,AL40,"")&IF(BY40=AM40,AN40,"")) -> five | BY40: =IF(A40>=100,ROUNDDOWN((A40-ROUNDDOWN(A40,-3))/100,0),"") -> 5 | BZ40: =IF(BS40="","",BS40)&IF(BT40="","",BT40)&IF(BU40="","",BU40)&IF(BV40="","",BV40)&IF(BW40="","",BW40) -> five | CA40: TENS | CB40: =IF(CH40="","",IF(CH40>=90,"ninety "&IF((CH40-ROUNDDOWN(CH40,-1))=1,D40,"")&IF((CH40-ROUNDDOWN(CH40,-1))=2,F40,"")&IF((CH40-ROUNDDOWN(CH40,-1))=G40,H40,"")&IF((CH40-ROUNDDOWN(CH40,-1))=I40,J40,"")&IF((CH40-ROUNDDOWN(CH40,-1))=K40,L40,"")&IF((CH40-ROUNDDOWN(CH40,-1))=M40,N40,"")&IF((CH40-ROUNDDOWN(CH40,-1))=O40,P40,"")&IF((CH40-ROUNDDOWN(CH40,-1))=Q40,R40,"")&IF((CH40-ROUNDDOWN(CH40,-1))=S40,T40,""),IF(CH40>=80,"eighty "&IF((CH40-ROUNDDOWN(CH40,-1))=1,D40,"")&IF((CH40-ROUNDDOWN(CH40,-1))=2,F40,"")&IF((CH40-ROUNDDOWN(CH40,-1))=G40,H40,"")&IF((CH40-ROUNDDOWN(CH40,-1))=I40,J40,"")&IF((CH40-ROUNDDOWN(CH40,-1))=K40,L40,"")&IF((CH40-ROUNDDOWN(CH40,-1))=M40,N40,"")&IF((CH40-ROUNDDOWN(CH40,-1))=O40,P40,"")&IF((CH40-ROUNDDOWN(CH40,-1))=Q40,R40,"")&IF((CH40-ROUNDDOWN(CH40,-1))=S40,T40,""),""))) | CC40: =IF(CH40="","",IF(CH40>79,"",IF(CH40>=70,"seventy "&IF((CH40-ROUNDDOWN(CH40,-1))=1,D40,"")&IF((CH40-ROUNDDOWN(CH40,-1))=2,F40,"")&IF((CH40-ROUNDDOWN(CH40,-1))=G40,H40,"")&IF((CH40-ROUNDDOWN(CH40,-1))=I40,J40,"")&IF((CH40-ROUNDDOWN(CH40,-1))=K40,L40,"")&IF((CH40-ROUNDDOWN(CH40,-1))=M40,N40,"")&IF((CH40-ROUNDDOWN(CH40,-1))=O40,P40,"")&IF((CH40-ROUNDDOWN(CH40,-1))=Q40,R40,"")&IF((CH40-ROUNDDOWN(CH40,-1))=S40,T40,""),IF(CH40>=60,"sixty "&IF((CH40-ROUNDDOWN(CH40,-1))=1,D40,"")&IF((CH40-ROUNDDOWN(CH40,-1))=2,F40,"")&IF((CH40-ROUNDDOWN(CH40,-1))=G40,H40,"")&IF((CH40-ROUNDDOWN(CH40,-1))=I40,J40,"")&IF((CH40-ROUNDDOWN(CH40,-1))=K40,L40,"")&IF((CH40-ROUNDDOWN(CH40,-1))=M40,N40,"")&IF((CH40-ROUNDDOWN(CH40,-1))=O40,P40,"")&IF((CH40-ROUNDDOWN(CH40,-1))=Q40,R40,"")&IF((CH40-ROUNDDOWN(CH40,-1))=S40,T40,""),"")))) | CD40: =IF(CH40="","",IF(CH40>59,"",IF(CH40>=50,"fifty "&IF((CH40-ROUNDDOWN(CH40,-1))=1,D40,"")&IF((CH40-ROUNDDOWN(CH40,-1))=2,F40,"")&IF((CH40-ROUNDDOWN(CH40,-1))=G40,H40,"")&IF((CH40-ROUNDDOWN(CH40,-1))=I40,J40,"")&IF((CH40-ROUNDDOWN(CH40,-1))=K40,L40,"")&IF((CH40-ROUNDDOWN(CH40,-1))=M40,N40,"")&IF((CH40-ROUNDDOWN(CH40,-1))=O40,P40,"")&IF((CH40-ROUNDDOWN(CH40,-1))=Q40,R40,"")&IF((CH40-ROUNDDOWN(CH40,-1))=S40,T40,""),IF(CH40>=40,"forty "&IF((CH40-ROUNDDOWN(CH40,-1))=1,D40,"")&IF((CH40-ROUNDDOWN(CH40,-1))=2,F40,"")&IF((CH40-ROUNDDOWN(CH40,-1))=G40,H40,"")&IF((CH40-ROUNDDOWN(CH40,-1))=I40,J40,"")&IF((CH40-ROUNDDOWN(CH40,-1))=K40,L40,"")&IF((CH40-ROUNDDOWN(CH40,-1))=M40,N40,"")&IF((CH40-ROUNDDOWN(CH40,-1))=O40,P40,"")&IF((CH40-ROUNDDOWN(CH40,-1))=Q40,R40,"")&IF((CH40-ROUNDDOWN(CH40,-1))=S40,T40,""),"")))) | CE40: =IF(CH40="","",IF(CH40>39,"",IF(CH40>=30,"thirty "&IF((CH40-ROUNDDOWN(CH40,-1))=1,D40,"")&IF((CH40-ROUNDDOWN(CH40,-1))=2,F40,"")&IF((CH40-ROUNDDOWN(CH40,-1))=G40,H40,"")&IF((CH40-ROUNDDOWN(CH40,-1))=I40,J40,"")&IF((CH40-ROUNDDOWN(CH40,-1))=K40,L40,"")&IF((CH40-ROUNDDOWN(CH40,-1))=M40,N40,"")&IF((CH40-ROUNDDOWN(CH40,-1))=O40,P40,"")&IF((CH40-ROUNDDOWN(CH40,-1))=Q40,R40,"")&IF((CH40-ROUNDDOWN(CH40,-1))=S40,T40,""),IF(CH40>=20,"twenty "&IF((CH40-ROUNDDOWN(CH40,-1))=1,D40,"")&IF((CH40-ROUNDDOWN(CH40,-1))=2,F40,"")&IF((CH40-ROUNDDOWN(CH40,-1))=G40,H40,"")&IF((CH40-ROUNDDOWN(CH40,-1))=I40,J40,"")&IF((CH40-ROUNDDOWN(CH40,-1))=K40,L40,"")&IF((CH40-ROUNDDOWN(CH40,-1))=M40,N40,"")&IF((CH40-ROUNDDOWN(CH40,-1))=O40,P40,"")&IF((CH40-ROUNDDOWN(CH40,-1))=Q40,R40,"")&IF((CH40-ROUNDDOWN(CH40,-1))=S40,T40,""),"")))) | CF40: =IF(CH40="","",IF(CH40=C40,D40,"")&IF(CH40=E40,F40,"")&IF(CH40=G40,H40,"")&IF(CH40=I40,J40,"")&IF(CH40=K40,L40,"")&IF(CH40=M40,N40,"")&IF(CH40=O40,P40,"")&IF(CH40=Q40,R40,"")&IF(CH40=S40,T40,"")&IF(CH40=U40,V40,"")&IF(CH40=W40,X40,"")&IF(CH40=Y40,Z40,"")&IF(CH40=AA40,AB40,"")&IF(CH40=AC40,AD40,"")&IF(CH40=AE40,AF40,"")&IF(CH40=AG40,AH40,"")&IF(CH40=AI40,AJ40,"")&IF(CH40=AK40,AL40,"")&IF(CH40=AM40,AN40,"")) -> twelve | CH40: =IF(A40>=1,ROUNDDOWN(A40-ROUNDDOWN(A40,-2),0),"") -> 12 | CI40: =IF(CB40="","",CB40)&IF(CC40="","",CC40)&IF(CD40="","",CD40)&IF(CE40="","",CE40)&IF(CF40="","",CF40) -> twelve | CJ40: PAISE | CK40: =IF(CQ40="","",IF(CQ40>=90,"ninety "&IF((CQ40-ROUNDDOWN(CQ40,-1))=1,D40,"")&IF((CQ40-ROUNDDOWN(CQ40,-1))=2,F40,"")&IF((CQ40-ROUNDDOWN(CQ40,-1))=G40,H40,"")&IF((CQ40-ROUNDDOWN(CQ40,-1))=I40,J40,"")&IF((CQ40-ROUNDDOWN(CQ40,-1))=K40,L40,"")&IF((CQ40-ROUNDDOWN(CQ40,-1))=M40,N40,"")&IF((CQ40-ROUNDDOWN(CQ40,-1))=O40,P40,"")&IF((CQ40-ROUNDDOWN(CQ40,-1))=Q40,R40,"")&IF((CQ40-ROUNDDOWN(CQ40,-1))=S40,T40,""),IF(CQ40>=80,"eighty "&IF((CQ40-ROUNDDOWN(CQ40,-1))=1,D40,"")&IF((CQ40-ROUNDDOWN(CQ40,-1))=2,F40,"")&IF((CQ40-ROUNDDOWN(CQ40,-1))=G40,H40,"")&IF((CQ40-ROUNDDOWN(CQ40,-1))=I40,J40,"")&IF((CQ40-ROUNDDOWN(CQ40,-1))=K40,L40,"")&IF((CQ40-ROUNDDOWN(CQ40,-1))=M40,N40,"")&IF((CQ40-ROUNDDOWN(CQ40,-1))=O40,P40,"")&IF((CQ40-ROUNDDOWN(CQ40,-1))=Q40,R40,"")&IF((CQ40-ROUNDDOWN(CQ40,-1))=S40,T40,""),""))) | CL40: =IF(CQ40="","",IF(CQ40>79,"",IF(CQ40>=70,"seventy "&IF((CQ40-ROUNDDOWN(CQ40,-1))=1,D40,"")&IF((CQ40-ROUNDDOWN(CQ40,-1))=2,F40,"")&IF((CQ40-ROUNDDOWN(CQ40,-1))=G40,H40,"")&IF((CQ40-ROUNDDOWN(CQ40,-1))=I40,J40,"")&IF((CQ40-ROUNDDOWN(CQ40,-1))=K40,L40,"")&IF((CQ40-ROUNDDOWN(CQ40,-1))=M40,N40,"")&IF((CQ40-ROUNDDOWN(CQ40,-1))=O40,P40,"")&IF((CQ40-ROUNDDOWN(CQ40,-1))=Q40,R40,"")&IF((CQ40-ROUNDDOWN(CQ40,-1))=S40,T40,""),IF(CQ40>=60,"sixty "&IF((CQ40-ROUNDDOWN(CQ40,-1))=1,D40,"")&IF((CQ40-ROUNDDOWN(CQ40,-1))=2,F40,"")&IF((CQ40-ROUNDDOWN(CQ40,-1))=G40,H40,"")&IF((CQ40-ROUNDDOWN(CQ40,-1))=I40,J40,"")&IF((CQ40-ROUNDDOWN(CQ40,-1))=K40,L40,"")&IF((CQ40-ROUNDDOWN(CQ40,-1))=M40,N40,"")&IF((CQ40-ROUNDDOWN(CQ40,-1))=O40,P40,"")&IF((CQ40-ROUNDDOWN(CQ40,-1))=Q40,R40,"")&IF((CQ40-ROUNDDOWN(CQ40,-1))=S40,T40,""),"")))) | CM40: =IF(CQ40="","",IF(CQ40>59,"",IF(CQ40>=50,"fifty "&IF((CQ40-ROUNDDOWN(CQ40,-1))=1,D40,"")&IF((CQ40-ROUNDDOWN(CQ40,-1))=2,F40,"")&IF((CQ40-ROUNDDOWN(CQ40,-1))=G40,H40,"")&IF((CQ40-ROUNDDOWN(CQ40,-1))=I40,J40,"")&IF((CQ40-ROUNDDOWN(CQ40,-1))=K40,L40,"")&IF((CQ40-ROUNDDOWN(CQ40,-1))=M40,N40,"")&IF((CQ40-ROUNDDOWN(CQ40,-1))=O40,P40,"")&IF((CQ40-ROUNDDOWN(CQ40,-1))=Q40,R40,"")&IF((CQ40-ROUNDDOWN(CQ40,-1))=S40,T40,""),IF(CQ40>=40,"forty "&IF((CQ40-ROUNDDOWN(CQ40,-1))=1,D40,"")&IF((CQ40-ROUNDDOWN(CQ40,-1))=2,F40,"")&IF((CQ40-ROUNDDOWN(CQ40,-1))=G40,H40,"")&IF((CQ40-ROUNDDOWN(CQ40,-1))=I40,J40,"")&IF((CQ40-ROUNDDOWN(CQ40,-1))=K40,L40,"")&IF((CQ40-ROUNDDOWN(CQ40,-1))=M40,N40,"")&IF((CQ40-ROUNDDOWN(CQ40,-1))=O40,P40,"")&IF((CQ40-ROUNDDOWN(CQ40,-1))=Q40,R40,"")&IF((CQ40-ROUNDDOWN(CQ40,-1))=S40,T40,""),"")))) | CN40: =IF(CQ40="","",IF(CQ40>39,"",IF(CQ40>=30,"thirty "&IF((CQ40-ROUNDDOWN(CQ40,-1))=1,D40,"")&IF((CQ40-ROUNDDOWN(CQ40,-1))=2,F40,"")&IF((CQ40-ROUNDDOWN(CQ40,-1))=G40,H40,"")&IF((CQ40-ROUNDDOWN(CQ40,-1))=I40,J40,"")&IF((CQ40-ROUNDDOWN(CQ40,-1))=K40,L40,"")&IF((CQ40-ROUNDDOWN(CQ40,-1))=M40,N40,"")&IF((CQ40-ROUNDDOWN(CQ40,-1))=O40,P40,"")&IF((CQ40-ROUNDDOWN(CQ40,-1))=Q40,R40,"")&IF((CQ40-ROUNDDOWN(CQ40,-1))=S40,T40,""),IF(CQ40>=20,"twenty "&IF((CQ40-ROUNDDOWN(CQ40,-1))=1,D40,"")&IF((CQ40-ROUNDDOWN(CQ40,-1))=2,F40,"")&IF((CQ40-ROUNDDOWN(CQ40,-1))=G40,H40,"")&IF((CQ40-ROUNDDOWN(CQ40,-1))=I40,J40,"")&IF((CQ40-ROUNDDOWN(CQ40,-1))=K40,L40,"")&IF((CQ40-ROUNDDOWN(CQ40,-1))=M40,N40,"")&IF((CQ40-ROUNDDOWN(CQ40,-1))=O40,P40,"")&IF((CQ40-ROUNDDOWN(CQ40,-1))=Q40,R40,"")&IF((CQ40-ROUNDDOWN(CQ40,-1))=S40,T40,""),"")))) | CO40: =IF(CQ40="","",IF(CQ40=C40,D40,"")&IF(CQ40=E40,F40,"")&IF(CQ40=G40,H40,"")&IF(CQ40=I40,J40,"")&IF(CQ40=K40,L40,"")&IF(CQ40=M40,N40,"")&IF(CQ40=O40,P40,"")&IF(CQ40=Q40,R40,"")&IF(CQ40=S40,T40,"")&IF(CQ40=U40,V40,"")&IF(CQ40=W40,X40,"")&IF(CQ40=Y40,Z40,"")&IF(CQ40=AA40,AB40,"")&IF(CQ40=AC40,AD40,"")&IF(CQ40=AE40,AF40,"")&IF(CQ40=AG40,AH40,"")&IF(CQ40=AI40,AJ40,"")&IF(CQ40=AK40,AL40,"")&IF(CQ40=AM40,AN40,"")) | CQ40: =IF((A40-ROUNDDOWN(A40,0))>0,ROUND((A40-ROUNDDOWN(A40,0))*100,0),"") | CR40: =IF(CK40="","",CK40)&IF(CL40="","",CL40)&IF(CM40="","",CM40)&IF(CN40="","",CN40)&IF(CO40="","",CO40) | CS40: <= IN WORDS | CU40: =IF(A40="","","(Rupees "&IF(AY40="","",AY40&" crore ")&IF(BH40="","",BH40&" lakh ")&IF(BQ40="","",BQ40&" thousand ")&IF(BZ40="","",BZ40&" hundred ")&IF(CI40="","",CI40)&IF(CR40="",""," and paise "&CR40)&") only.") -> (Rupees seven lakh twenty thousand five hundred twelve) only.

Sheet PLAN
A1: =Cover!B16 &Cover!E16&Cover!F16 -> Name of Work:-Repairing and Renovation of Circuit House at Bokakhat Co District under Golaghat District
N27: NOTE: 1) All Dimensions are in millimeters.

Sheet Septic Tank
A1: {='Electrical Works'!A1:A1} -> Name of Work :- Repairing and Renovation of Circuit House at Bokakhat Co District under Golaghat District
A2: SEPTIC TANK
A4: Sl.No. | B4: DSR | C4: Description | J4: Unit | K4: Qnty | L4: Rate | M4: Amount
B5: 2021
B6: Item No.
B8: 2 | C8: EARTH WORK
B9: 2.8 | C9: EARTHWORK IN EXCAVATION
C10: Earth work in excavation by mechanical means (Hydraulic excavator) / manual means in foundation trenches or drains (not exceeding 1.5 m in width or 10 sqm on plan), including dressing of sides and ramming of bottoms, lift upto 1.5 m, including getting out the excavated soil and disposal of surplus excavated soil as directed, within a lead of 50 m and lift upto 1.5 m.
A11: 1 | B11: 2.8.1 | C11: All kinds of soil. | J11: Cu.M. | K11: =Sheet5!I5 -> 17.95 | L11: 286.85 | M11: =ROUND(L11*K11,0) -> 5149
B12: 4 | C12: CONCRETE WORK
C13: CEMENT CONCRETE (CAST IN SITU)
C14: Providing and laying in position cement concrete of specified grade excluding the cost of centering and shuttering - All work up to plinth level :
A15: 2 | B15: 4.1.5 | C15: 1:3:6 (1 Cement : 3 coarse sand (zone-III) deliverd from natural sources: 6 graded stone aggregate 20 mm nominal size deliverd from natural sources) | J15: Cu.M. | K15: =Sheet5!I10 -> 1.5 | L15: 6833.4 | M15: =ROUND(K15*L15,0) -> 10250
B16: 5 | C16: REINFORCED CEMENT CONCRETE WORKS
B17: 5.1 | C17: Providing and laying in position specified grade of reinforced cement concrete, excluding the cost of centering, shuttering, finishing and reinforcement - All work up to plinth level :
A18: 3 | B18: 5.1.2 | C18: 1:1.5:3 (1 cement : 1.5 coarse sand (zone-III)deliverd from natural sources: 3 graded stone aggregate 20 mm nominal size deliverd from natural sources) | J18: Cu.M. | K18: =Sheet5!I17 -> 1.19 | L18: 8364.2 | M18: =ROUND(K18*L18,0) -> 9953
B19: 5.9 | C19: FORM WORK
C20: Centering and shuttering including strutting, propping etc. and removal of form for :
A21: 4 | B21: 5.9.3 | C21: Suspended floors, roofs, landings, balconies and access platform | J21: Sq.M. | K21: =Sheet5!I24 -> 7 | L21: 766.55 | M21: =ROUND(K21*L21,0) -> 5366
C22: REINFORCEMENT
B23: 5.22 | C23: Steel reinforcement for R.C.C. work including straightening, cutting, bending, placing in position and binding all complete upto plinth level.
A24: 5 | B24: 5.22.6 | C24: Thermo-Mechanically Treated bars of grade Fe-500D or more. | J24: Kg | K24: ='[52]ANX-7A'!$J$45 -> 104.92 | L24: 89.65 | M24: =ROUND(K24*L24,0) -> 9406
C25: BRICK MASONRY WORKS
B26: 6.1 | C26: Brick work with common burnt clay F.P.S. (non modular) bricks of class designation 7.5 in foundation and plinth in:
A27: 6 | B27: 6.1.1 | C27: Cement mortar 1:4 (1 cement : 4 coarse sand) | J27: Cu.M. | K27: =Sheet5!I48 -> 4.61 | L27: 6882 | M27: =ROUND(K27*L27,0) -> 31726
C28: CEMENT PLASTER WITH A FLOATING COAT OF NEAT CEMENT
B29: 13.8 | C29: 15 mm cement plaster on rough side of single or half brick wall finished with a floating coat of neat cement of mix :
A30: 7 | B30: 13.8.2 | C30: 1:4 (1 cement: 4 fine sand) | J30: Sq.M. | K30: =Sheet5!I55 -> 64.38 | L30: 406.1 | M30: =ROUND(K30*L30,0) -> 26145
A31: 8 | B31: 13.21 | C31: Extra for providing and mixing water proofing material in cement plaster work in proportion recommended by the manufacturers. | J31: per bag of 50kg cement used in the mix | K31: =K30*0.048 -> 3.09 | L31: 60.55 | M31: =ROUND(K31*L31,0) -> 187
B32: 19.32 | C32: Making soak pit 2.5 m diameter 3.0 metre deep with 45 x 45 cm dry brick honey comb shaft with bricks and S.W. drain pipe 100 mm diameter, 1.8 m long complete as per standard design.
A33: 9 | B33: 19.32.1 | C33: With common burnt clay F.P.S. (non modular) bricks of class designation 7.5 | J33: Each | K33: 1 | L33: 28029.15 | M33: =ROUND(K33*L33,0) -> 28029
B34: TOTAL CPWD SCHEDULED CIVIL WORKS = | M34: =SUM(M10:M33) -> 126211
A35: SAY= | M35: =M34 -> 126211
A36: =CU39 -> (Rupees one lakh twenty six thousand two hundred eleven) only.
